{
  "type": "Feature",
  "properties": {
    "gn:admin1_code":"14",
    "gn:admin2_code":"339.0",
    "gn:asciiname":"Burge",
    "gn:country_code":"JM",
    "gn:dem":79,
    "gn:feature_class":"P",
    "gn:feature_code":"PPL",
    "gn:name":"Burge",
    "gn:population":0,
    "gn:timezone":"America/Jamaica",
    "iso:country":"JM",
    "wof:name":"Burge",
    "wof:placetype":"locality"
},
  "geometry": {"coordinates":[-76.65000000000001,17.93332999999999],"type":"Point"}
}