{
  "type": "Feature",
  "properties": {
    "gn:admin1_code":"9.0",
    "gn:admin2_code":"640",
    "gn:asciiname":"Lower Tooting",
    "gn:country_code":"JM",
    "gn:dem":583,
    "gn:feature_class":"P",
    "gn:feature_code":"PPL",
    "gn:name":"Lower Tooting",
    "gn:population":0,
    "gn:timezone":"America/Jamaica",
    "iso:country":"JM",
    "wof:name":"Lower Tooting",
    "wof:placetype":"locality"
},
  "geometry": {"coordinates":[-77.40000000000001,18.31667],"type":"Point"}
}