{
  "type": "Feature",
  "properties": {
    "gn:admin1_code":"14",
    "gn:admin2_code":"301.0",
    "gn:asciiname":"Hagley Gap",
    "gn:country_code":"JM",
    "gn:dem":642,
    "gn:feature_class":"P",
    "gn:feature_code":"PPL",
    "gn:name":"Hagley Gap",
    "gn:population":0,
    "gn:timezone":"America/Jamaica",
    "iso:country":"JM",
    "name:ceb_x_preferred":[
        "Hagley Gap"
    ],
    "name:swe_x_preferred":[
        "Hagley Gap"
    ],
    "wof:name":"Hagley Gap",
    "wof:placetype":"locality"
},
  "geometry": {"coordinates":[-76.61762,18.01718],"type":"Point"}
}