{
  "type": "Feature",
  "properties": {
    "gn:admin1_code":"4.0",
    "gn:admin2_code":"1274",
    "gn:asciiname":"Victoria Town",
    "gn:country_code":"JM",
    "gn:dem":180,
    "gn:feature_class":"P",
    "gn:feature_code":"PPL",
    "gn:name":"Victoria Town",
    "gn:population":0,
    "gn:timezone":"America/Jamaica",
    "iso:country":"JM",
    "wof:name":"Victoria Town",
    "wof:placetype":"locality"
},
  "geometry": {"coordinates":[-77.38176999999997,17.91793999999999],"type":"Point"}
}