{
  "type": "Feature",
  "properties": {
    "gn:admin1_code":"15.0",
    "gn:admin2_code":"708",
    "gn:asciiname":"Refuge",
    "gn:country_code":"JM",
    "gn:dem":188,
    "gn:feature_class":"P",
    "gn:feature_code":"PPL",
    "gn:name":"Refuge",
    "gn:population":0,
    "gn:timezone":"America/Jamaica",
    "iso:country":"JM",
    "wof:name":"Refuge",
    "wof:placetype":"locality"
},
  "geometry": {"coordinates":[-77.57481999999997,18.46309],"type":"Point"}
}