{
  "type": "Feature",
  "properties": {
    "gn:admin1_code":"1.0",
    "gn:admin2_code":"1371",
    "gn:asciiname":"Salt River",
    "gn:country_code":"JM",
    "gn:dem":7,
    "gn:feature_class":"P",
    "gn:feature_code":"PPL",
    "gn:name":"Salt River",
    "gn:population":0,
    "gn:timezone":"America/Jamaica",
    "iso:country":"JM",
    "wof:name":"Salt River",
    "wof:placetype":"locality"
},
  "geometry": {"coordinates":[-77.16869,17.83729],"type":"Point"}
}