{
  "type": "Feature",
  "properties": {
    "gn:admin1_code":"11.0",
    "gn:admin2_code":"1123",
    "gn:asciiname":"Selington",
    "gn:country_code":"JM",
    "gn:dem":27,
    "gn:feature_class":"P",
    "gn:feature_code":"PPL",
    "gn:name":"Selington",
    "gn:population":0,
    "gn:timezone":"America/Jamaica",
    "iso:country":"JM",
    "wof:name":"Selington",
    "wof:placetype":"locality"
},
  "geometry": {"coordinates":[-77.90533000000001,18.0706],"type":"Point"}
}