{
  "type": "Feature",
  "properties": {
    "gn:admin1_code":"09",
    "gn:admin2_code":"638.0",
    "gn:asciiname":"Aberly",
    "gn:country_code":"JM",
    "gn:dem":638,
    "gn:feature_class":"P",
    "gn:feature_code":"PPL",
    "gn:name":"Aberly",
    "gn:population":0,
    "gn:timezone":"America/Jamaica",
    "iso:country":"JM",
    "wof:name":"Aberly",
    "wof:placetype":"locality"
},
  "geometry": {"coordinates":[-77.36667,18.26667],"type":"Point"}
}