{
  "type": "Feature",
  "properties": {
    "gn:admin1_code":"07",
    "gn:admin2_code":"426.0",
    "gn:asciiname":"Ecclesdown",
    "gn:country_code":"JM",
    "gn:dem":242,
    "gn:feature_class":"P",
    "gn:feature_code":"PPLL",
    "gn:name":"Ecclesdown",
    "gn:population":0,
    "gn:timezone":"America/Jamaica",
    "iso:country":"JM",
    "wof:name":"Ecclesdown",
    "wof:placetype":"locality"
},
  "geometry": {"coordinates":[-76.33608000000002,18.05842],"type":"Point"}
}