{
  "type": "Feature",
  "properties": {
    "gn:admin1_code":"1.0",
    "gn:admin2_code":"1382",
    "gn:asciiname":"Pusey Hall Pen",
    "gn:country_code":"JM",
    "gn:dem":140,
    "gn:feature_class":"P",
    "gn:feature_code":"PPL",
    "gn:name":"Pusey Hall Pen",
    "gn:population":0,
    "gn:timezone":"America/Jamaica",
    "iso:country":"JM",
    "wof:name":"Pusey Hall Pen",
    "wof:placetype":"locality"
},
  "geometry": {"coordinates":[-77.16667,17.75],"type":"Point"}
}