{
  "type": "Feature",
  "properties": {
    "gn:admin1_code":"01",
    "gn:admin2_code":"1306.0",
    "gn:asciiname":"Johns Hall",
    "gn:country_code":"JM",
    "gn:dem":461,
    "gn:feature_class":"P",
    "gn:feature_code":"PPL",
    "gn:name":"Johns Hall",
    "gn:population":0,
    "gn:timezone":"America/Jamaica",
    "iso:country":"JM",
    "wof:name":"Johns Hall",
    "wof:placetype":"locality"
},
  "geometry": {"coordinates":[-77.37505999999998,18.17478],"type":"Point"}
}