{
  "type": "Feature",
  "properties": {
    "gn:admin1_code":"13",
    "gn:asciiname":"Copse",
    "gn:country_code":"JM",
    "gn:dem":229,
    "gn:feature_class":"P",
    "gn:feature_code":"PPL",
    "gn:name":"Copse",
    "gn:population":0,
    "gn:timezone":"America/Jamaica",
    "iso:country":"JM",
    "wof:name":"Copse",
    "wof:placetype":"locality"
},
  "geometry": {"coordinates":[-77.96865,18.37629],"type":"Point"}
}