{
  "type": "Feature",
  "properties": {
    "gn:admin1_code":"10.0",
    "gn:admin2_code":"1429",
    "gn:asciiname":"Spring Village",
    "gn:country_code":"JM",
    "gn:dem":31,
    "gn:feature_class":"P",
    "gn:feature_code":"PPL",
    "gn:name":"Spring Village",
    "gn:population":0,
    "gn:timezone":"America/Jamaica",
    "iso:country":"JM",
    "name:deu_x_preferred":[
        "Spring Village"
    ],
    "name:und_x_variant":[
        "Spring",
        "Spring Village"
    ],
    "wof:name":"Spring Village",
    "wof:placetype":"locality"
},
  "geometry": {"coordinates":[-77.07304000000001,17.95973],"type":"Point"}
}