{
  "type": "Feature",
  "properties": {
    "gn:admin1_code":"02",
    "gn:admin2_code":"933.0",
    "gn:asciiname":"Cave Valley",
    "gn:country_code":"JM",
    "gn:dem":30,
    "gn:feature_class":"P",
    "gn:feature_code":"PPL",
    "gn:name":"Cave Valley",
    "gn:population":0,
    "gn:timezone":"America/Jamaica",
    "iso:country":"JM",
    "wof:name":"Cave Valley",
    "wof:placetype":"locality"
},
  "geometry": {"coordinates":[-78.27306999999998,18.32802],"type":"Point"}
}