{
  "type": "Feature",
  "properties": {
    "gn:admin1_code":"02",
    "gn:admin2_code":"924.0",
    "gn:asciiname":"Georgia",
    "gn:country_code":"JM",
    "gn:dem":37,
    "gn:feature_class":"P",
    "gn:feature_code":"PPL",
    "gn:name":"Georgia",
    "gn:population":0,
    "gn:timezone":"America/Jamaica",
    "iso:country":"JM",
    "wof:name":"Georgia",
    "wof:placetype":"locality"
},
  "geometry": {"coordinates":[-78.13679,18.41937],"type":"Point"}
}