{
  "type": "Feature",
  "properties": {
    "gn:country":"JM",
    "gn:fcode":"PPL",
    "gn:pop":3305,
    "iso:country":"JM",
    "name:dut_x_preferred":[
        "Gayle"
    ],
    "name:eng_x_preferred":[
        "Gayle"
    ],
    "name:unk_x_variant":[
        "Gayle Village"
    ],
    "qs:name":"Gayle",
    "qs:photos_9r":0,
    "qs:photos_sr":0,
    "qs:pop_sr":"4",
    "wd:wordcount":49,
    "wof:name":"Gayle",
    "wof:placetype":"locality",
    "wof:population":3305
},
  "geometry": {"coordinates":[-77.00971,18.32642],"type":"Point"}
}