{
  "type": "Feature",
  "properties": {
    "gn:admin1_code":"12.0",
    "gn:admin2_code":"829",
    "gn:asciiname":"Salters Hill",
    "gn:country_code":"JM",
    "gn:dem":209,
    "gn:feature_class":"P",
    "gn:feature_code":"PPL",
    "gn:name":"Salters Hill",
    "gn:population":0,
    "gn:timezone":"America/Jamaica",
    "iso:country":"JM",
    "name:und_x_variant":[
        "Sadlers Hill",
        "Salters Hill"
    ],
    "wof:name":"Salters Hill",
    "wof:placetype":"locality"
},
  "geometry": {"coordinates":[-77.83551999999997,18.4287],"type":"Point"}
}