{
  "type": "Feature",
  "properties": {
    "gn:admin1_code":"10.0",
    "gn:admin2_code":"1401",
    "gn:asciiname":"Orange Valley",
    "gn:country_code":"JM",
    "gn:dem":460,
    "gn:feature_class":"P",
    "gn:feature_code":"PPL",
    "gn:name":"Orange Valley",
    "gn:population":0,
    "gn:timezone":"America/Jamaica",
    "iso:country":"JM",
    "wof:name":"Orange Valley",
    "wof:placetype":"locality"
},
  "geometry": {"coordinates":[-77.18333,18.13333],"type":"Point"}
}