{
  "type": "Feature",
  "properties": {
    "gn:admin1_code":"10.0",
    "gn:admin2_code":"1429",
    "gn:asciiname":"Marlie Mount",
    "gn:country_code":"JM",
    "gn:dem":33,
    "gn:feature_class":"P",
    "gn:feature_code":"PPL",
    "gn:name":"Marlie Mount",
    "gn:population":0,
    "gn:timezone":"America/Jamaica",
    "iso:country":"JM",
    "name:und_x_variant":[
        "Marlie Hill",
        "Marlie",
        "Marly",
        "Marlie Mount"
    ],
    "wof:name":"Marlie Mount",
    "wof:placetype":"locality"
},
  "geometry": {"coordinates":[-77.10275,17.94453],"type":"Point"}
}