{
  "type": "Feature",
  "properties": {
    "gn:country":"JM",
    "gn:fcode":"PPL",
    "gn:population":9450,
    "iso:country":"JM",
    "name:ara_x_preferred":[
        "\u0623\u0648\u062a\u0634\u0648 \u0631\u064a\u0648\u0633"
    ],
    "name:bel_x_preferred":[
        "\u041e\u0447\u0430-\u0420\u044b\u044f\u0441"
    ],
    "name:ceb_x_preferred":[
        "Ocho Rios"
    ],
    "name:ces_x_preferred":[
        "Ocho Rios"
    ],
    "name:deu_x_preferred":[
        "Ocho Rios"
    ],
    "name:ell_x_preferred":[
        "\u038c\u03c4\u03c3\u03bf \u03a1\u03af\u03bf\u03c2"
    ],
    "name:eng_x_preferred":[
        "Ocho Rios"
    ],
    "name:fra_x_preferred":[
        "Ocho Rios"
    ],
    "name:heb_x_preferred":[
        "\u05d0\u05d5\u05e6'\u05d5 \u05e8\u05d9\u05d5\u05e1"
    ],
    "name:ita_x_preferred":[
        "Ocho Rios"
    ],
    "name:jpn_x_preferred":[
        "\u30aa\u30fc\u30c1\u30e7\u30fb\u30ea\u30aa\u30b9"
    ],
    "name:nld_x_preferred":[
        "Ocho Rios"
    ],
    "name:nob_x_preferred":[
        "Ocho R\u00edos"
    ],
    "name:nor_x_preferred":[
        "Ocho R\u00edos"
    ],
    "name:pol_x_preferred":[
        "Ocho Rios"
    ],
    "name:por_x_preferred":[
        "Ocho Rios"
    ],
    "name:rus_x_preferred":[
        "\u041e\u0447\u043e-\u0420\u0438\u043e\u0441"
    ],
    "name:spa_x_preferred":[
        "Ocho R\u00edos"
    ],
    "name:spa_x_variant":[
        "Ocho r\u00edos"
    ],
    "name:swe_x_preferred":[
        "Ocho Rios"
    ],
    "name:ukr_x_preferred":[
        "\u041e\u0447\u043e-\u0420\u0456\u043e\u0441"
    ],
    "name:und_x_variant":[
        "Las Chorreras"
    ],
    "name:wuu_x_preferred":[
        "\u5967\u55ac\u91cc\u5967\u65af"
    ],
    "name:zho_x_preferred":[
        "\u5967\u55ac\u91cc\u5967\u65af"
    ],
    "qs_pg:aaroncc":"JM",
    "qs_pg:gn_country":"JM",
    "qs_pg:gn_fcode":"PPL",
    "qs_pg:gn_pop":9450,
    "qs_pg:name":"Ocho Rios",
    "qs_pg:photos_9r":0,
    "qs_pg:photos_sr":0,
    "qs_pg:pop_sr":5,
    "qs_pg:qs_pg_placetype":"locality",
    "wof:name":"Ocho Rios",
    "wof:placetype":"locality",
    "wof:population":9450
},
  "geometry": {"coordinates":[-77.1048,18.4025],"type":"Point"}
}