{
  "type": "Feature",
  "properties": {
    "gn:admin1_code":"04",
    "gn:admin2_code":"1214.0",
    "gn:asciiname":"Clandon",
    "gn:country_code":"JM",
    "gn:dem":862,
    "gn:feature_class":"P",
    "gn:feature_code":"PPL",
    "gn:name":"Clandon",
    "gn:population":0,
    "gn:timezone":"America/Jamaica",
    "iso:country":"JM",
    "name:und_x_variant":[
        "Clanden",
        "Clandon"
    ],
    "wof:name":"Clandon",
    "wof:placetype":"locality"
},
  "geometry": {"coordinates":[-77.46824000000002,18.15144],"type":"Point"}
}