{
  "type": "Feature",
  "properties": {
    "gn:admin1_code":"8.0",
    "gn:admin2_code":"15122",
    "gn:asciiname":"Lebanon",
    "gn:country_code":"JM",
    "gn:dem":966,
    "gn:feature_class":"P",
    "gn:feature_code":"PPL",
    "gn:name":"Lebanon",
    "gn:population":0,
    "gn:timezone":"America/Jamaica",
    "iso:country":"JM",
    "wof:name":"Lebanon",
    "wof:placetype":"locality"
},
  "geometry": {"coordinates":[-76.67961,18.0538],"type":"Point"}
}