{
  "type": "Feature",
  "properties": {
    "gn:admin1_code":"14.0",
    "gn:admin2_code":"347",
    "gn:asciiname":"Red Hill",
    "gn:country_code":"JM",
    "gn:dem":14,
    "gn:feature_class":"P",
    "gn:feature_code":"PPL",
    "gn:name":"Red Hill",
    "gn:population":0,
    "gn:timezone":"America/Jamaica",
    "iso:country":"JM",
    "name:ceb_x_preferred":[
        "Red Hill"
    ],
    "name:deu_x_preferred":[
        "Red Hill"
    ],
    "name:fra_x_preferred":[
        "Red Hill"
    ],
    "name:ita_x_preferred":[
        "Red Hill"
    ],
    "name:mlg_x_preferred":[
        "Red Hill"
    ],
    "name:nld_x_preferred":[
        "Red Hill"
    ],
    "name:pol_x_preferred":[
        "Red Hill"
    ],
    "name:srp_x_preferred":[
        "\u0420\u0435\u0434 \u0425\u0438\u043b"
    ],
    "name:swe_x_preferred":[
        "Red Hill"
    ],
    "name:ukr_x_preferred":[
        "\u0420\u0435\u0434-\u0413\u0456\u043b\u043b"
    ],
    "name:vol_x_preferred":[
        "Red Hill"
    ],
    "wof:name":"Red Hill",
    "wof:placetype":"locality"
},
  "geometry": {"coordinates":[-76.41667,17.88332999999999],"type":"Point"}
}