{
  "type": "Feature",
  "properties": {
    "gn:admin1_code":"13.0",
    "gn:admin2_code":"503",
    "gn:asciiname":"Retreat",
    "gn:country_code":"JM",
    "gn:dem":85,
    "gn:feature_class":"P",
    "gn:feature_code":"PPL",
    "gn:name":"Retreat",
    "gn:population":0,
    "gn:timezone":"America/Jamaica",
    "iso:country":"JM",
    "name:ceb_x_preferred":[
        "Retreat"
    ],
    "name:deu_x_preferred":[
        "Retreat"
    ],
    "name:fra_x_preferred":[
        "Retreat"
    ],
    "name:mlg_x_preferred":[
        "Retreat"
    ],
    "name:rus_x_preferred":[
        "\u0420\u0435\u0442\u0440\u0438\u0442"
    ],
    "name:swe_x_preferred":[
        "Retreat"
    ],
    "wof:name":"Retreat",
    "wof:placetype":"locality"
},
  "geometry": {"coordinates":[-77.01666999999998,18.38333],"type":"Point"}
}