{
  "type": "Feature",
  "properties": {
    "iso:country":"JM",
    "name:unk_x_variant":[
        "Norwich Halt"
    ],
    "qs:gn_country":"JM",
    "qs:gn_fcode":"PPL",
    "qs:gn_pop":0,
    "qs:name":"Norwich",
    "qs:name_adm0":"Jamaica",
    "qs:name_adm1":"Portland",
    "qs:photos":71,
    "qs:photos_1k":14,
    "qs:photos_9k":1,
    "qs:photos_9r":2,
    "qs:photos_all":71,
    "qs:photos_sr":2,
    "qs:placetype":"Town",
    "qs:pop_sr":"0",
    "qs:woe_adm0":23424858,
    "wd:wordcount":18117,
    "wof:name":"Norwich",
    "wof:placetype":"locality"
},
  "geometry": {"coordinates":[-76.47110000000001,18.19501],"type":"Point"}
}