{
  "type": "Feature",
  "properties": {
    "gn:admin1_code":"4.0",
    "gn:admin2_code":"1218",
    "gn:asciiname":"Petersfield",
    "gn:country_code":"JM",
    "gn:dem":544,
    "gn:feature_class":"P",
    "gn:feature_code":"PPL",
    "gn:name":"Petersfield",
    "gn:population":0,
    "gn:timezone":"America/Jamaica",
    "iso:country":"JM",
    "wof:name":"Petersfield",
    "wof:placetype":"locality"
},
  "geometry": {"coordinates":[-77.55,18.11667000000001],"type":"Point"}
}