{
  "type": "Feature",
  "properties": {
    "gn:admin1_code":"4.0",
    "gn:admin2_code":"1218",
    "gn:asciiname":"Petersfield",
    "gn:country_code":"JM",
    "gn:dem":544,
    "gn:feature_class":"P",
    "gn:feature_code":"PPL",
    "gn:name":"Petersfield",
    "gn:population":0,
    "gn:timezone":"America/Jamaica",
    "iso:country":"JM",
    "name:azb_x_preferred":[
        "\u067e\u06cc\u062a\u0631\u0633\u0641\u06cc\u0644\u062f"
    ],
    "name:bul_x_preferred":[
        "\u041f\u0438\u0442\u044a\u0440\u0441\u0444\u0438\u043b\u0434"
    ],
    "name:cym_x_preferred":[
        "Petersfield"
    ],
    "name:deu_x_preferred":[
        "Petersfield"
    ],
    "name:fas_x_preferred":[
        "\u067e\u06cc\u062a\u0631\u0633\u0641\u06cc\u0644\u062f"
    ],
    "name:fra_x_preferred":[
        "Petersfield"
    ],
    "name:gle_x_preferred":[
        "Petersfield"
    ],
    "name:ita_x_preferred":[
        "Petersfield"
    ],
    "name:lat_x_preferred":[
        "Petersfield"
    ],
    "name:nld_x_preferred":[
        "Petersfield"
    ],
    "name:nno_x_preferred":[
        "Petersfield"
    ],
    "name:pol_x_preferred":[
        "Petersfield"
    ],
    "name:ron_x_preferred":[
        "Petersfield"
    ],
    "name:snd_x_preferred":[
        "\u067e\u064a\u067d\u0631\u0632 \u0641\u064a\u0644\u068a"
    ],
    "name:spa_x_preferred":[
        "Petersfield"
    ],
    "name:swe_x_preferred":[
        "Petersfield"
    ],
    "name:vol_x_preferred":[
        "Petersfield"
    ],
    "name:zho_x_preferred":[
        "\u5f7c\u5f97\u65af\u83f2\u723e\u5fb7"
    ],
    "wof:name":"Petersfield",
    "wof:placetype":"locality"
},
  "geometry": {"coordinates":[-77.55,18.11667000000001],"type":"Point"}
}