{
  "type": "Feature",
  "properties": {
    "gn:admin1_code":"02",
    "gn:admin2_code":"924.0",
    "gn:asciiname":"Askenish",
    "gn:country_code":"JM",
    "gn:dem":161,
    "gn:feature_class":"P",
    "gn:feature_code":"PPL",
    "gn:name":"Askenish",
    "gn:population":0,
    "gn:timezone":"America/Jamaica",
    "iso:country":"JM",
    "name:und_x_variant":[
        "Askinish",
        "Askenish"
    ],
    "wof:name":"Askenish",
    "wof:placetype":"locality"
},
  "geometry": {"coordinates":[-78.15000000000001,18.3846],"type":"Point"}
}