{
  "type": "Feature",
  "properties": {
    "gn:admin1_code":"16.0",
    "gn:admin2_code":"1050",
    "gn:asciiname":"Kingswood",
    "gn:cc2":"JM",
    "gn:country_code":"JM",
    "gn:dem":8,
    "gn:feature_class":"P",
    "gn:feature_code":"PPL",
    "gn:name":"Kingswood",
    "gn:population":0,
    "gn:timezone":"America/Jamaica",
    "iso:country":"JM",
    "name:ceb_x_preferred":[
        "Kingswood"
    ],
    "name:cym_x_preferred":[
        "Kingswood"
    ],
    "name:deu_x_preferred":[
        "Kingswood"
    ],
    "name:fra_x_preferred":[
        "Kingswood"
    ],
    "name:ita_x_preferred":[
        "Kingswood"
    ],
    "name:kor_x_preferred":[
        "\ud0b9\uc2a4\uc6b0\ub4dc"
    ],
    "name:nld_x_preferred":[
        "Kingswood"
    ],
    "name:pol_x_preferred":[
        "Kingswood"
    ],
    "name:spa_x_preferred":[
        "Kingswood"
    ],
    "name:swe_x_preferred":[
        "Kingswood"
    ],
    "name:und_x_variant":[
        "Kingwood",
        "Kingswood"
    ],
    "wof:name":"Kingswood",
    "wof:placetype":"locality"
},
  "geometry": {"coordinates":[-78.13333,18.23333],"type":"Point"}
}