{
  "type": "Feature",
  "properties": {
    "gn:admin1_code":"16",
    "gn:admin2_code":"1064.0",
    "gn:asciiname":"Anglesea",
    "gn:country_code":"JM",
    "gn:dem":53,
    "gn:feature_class":"P",
    "gn:feature_code":"PPL",
    "gn:name":"Anglesea",
    "gn:population":0,
    "gn:timezone":"America/Jamaica",
    "iso:country":"JM",
    "wof:name":"Anglesea",
    "wof:placetype":"locality"
},
  "geometry": {"coordinates":[-78.06667,18.23333],"type":"Point"}
}