{
  "type": "Feature",
  "properties": {
    "gn:admin1_code":"02",
    "gn:admin2_code":"906.0",
    "gn:asciiname":"Elgin Town",
    "gn:country_code":"JM",
    "gn:dem":7,
    "gn:feature_class":"P",
    "gn:feature_code":"PPL",
    "gn:name":"Elgin Town",
    "gn:population":0,
    "gn:timezone":"America/Jamaica",
    "iso:country":"JM",
    "wof:name":"Elgin Town",
    "wof:placetype":"locality"
},
  "geometry": {"coordinates":[-78.15209,18.44529],"type":"Point"}
}