{
  "type": "Feature",
  "properties": {
    "gn:admin1_code":"15.0",
    "gn:admin2_code":"733",
    "gn:asciiname":"The Alps",
    "gn:cc2":"JM",
    "gn:country_code":"JM",
    "gn:dem":499,
    "gn:feature_class":"P",
    "gn:feature_code":"PPL",
    "gn:name":"The Alps",
    "gn:population":0,
    "gn:timezone":"America/Jamaica",
    "iso:country":"JM",
    "name:und_x_variant":[
        "Alps",
        "The Alps"
    ],
    "wof:name":"The Alps",
    "wof:placetype":"locality"
},
  "geometry": {"coordinates":[-77.51666999999998,18.33333],"type":"Point"}
}