{
  "type": "Feature",
  "properties": {
    "gn:admin1_code":"9.0",
    "gn:admin2_code":"618",
    "gn:asciiname":"Whitehorns Thicket",
    "gn:cc2":"JM",
    "gn:country_code":"JM",
    "gn:dem":379,
    "gn:feature_class":"P",
    "gn:feature_code":"PPL",
    "gn:name":"Whitehorns Thicket",
    "gn:population":0,
    "gn:timezone":"America/Jamaica",
    "iso:country":"JM",
    "name:und_x_variant":[
        "Whitehorns Thickets",
        "Thickets",
        "Whitehorns Thicket"
    ],
    "wof:name":"Whitehorns Thicket",
    "wof:placetype":"locality"
},
  "geometry": {"coordinates":[-77.16667,18.36667000000001],"type":"Point"}
}