{
  "type": "Feature",
  "properties": {
    "iso:country":"JM",
    "name:ceb_x_preferred":[
        "Lluidas Vale"
    ],
    "name:eng_x_preferred":[
        "Luidas Vale"
    ],
    "name:eng_x_variant":[
        "Lluidas Vale"
    ],
    "name:nld_x_preferred":[
        "Lluidas Vale"
    ],
    "name:swe_x_preferred":[
        "Lluidas Vale"
    ],
    "qs:gn_country":"JM",
    "qs:gn_fcode":"PPL",
    "qs:gn_pop":3163,
    "qs:name":"Lluidas Vale",
    "qs:name_adm0":"Jamaica",
    "qs:name_adm1":"Saint Catherine",
    "qs:photos":0,
    "qs:photos_1k":0,
    "qs:photos_9k":0,
    "qs:photos_9r":0,
    "qs:photos_all":0,
    "qs:photos_sr":0,
    "qs:placetype":"Town",
    "qs:pop_sr":"4",
    "qs:woe_adm0":23424858,
    "wd:wordcount":61,
    "wof:name":"Lluidas Vale",
    "wof:placetype":"locality",
    "wof:population":3163
},
  "geometry": {"coordinates":[-77.14764,18.12784],"type":"Point"}
}