{
  "type": "Feature",
  "properties": {
    "gn:admin1_code":"11.0",
    "gn:admin2_code":"1155",
    "gn:asciiname":"Williamsfield",
    "gn:country_code":"JM",
    "gn:dem":21,
    "gn:feature_class":"P",
    "gn:feature_code":"PPL",
    "gn:name":"Williamsfield",
    "gn:population":0,
    "gn:timezone":"America/Jamaica",
    "iso:country":"JM",
    "name:ceb_x_preferred":[
        "Williamsfield"
    ],
    "name:fra_x_preferred":[
        "Williamsfield"
    ],
    "name:pol_x_preferred":[
        "Williamsfield"
    ],
    "name:swe_x_preferred":[
        "Williamsfield"
    ],
    "name:vol_x_preferred":[
        "Williamsfield"
    ],
    "wof:name":"Williamsfield",
    "wof:placetype":"locality"
},
  "geometry": {"coordinates":[-77.76385000000001,17.94426],"type":"Point"}
}