{
  "type": "Feature",
  "properties": {
    "gn:admin1_code":"15",
    "gn:admin2_code":"707.0",
    "gn:asciiname":"Georgia",
    "gn:country_code":"JM",
    "gn:dem":241,
    "gn:feature_class":"P",
    "gn:feature_code":"PPL",
    "gn:name":"Georgia",
    "gn:population":0,
    "gn:timezone":"America/Jamaica",
    "iso:country":"JM",
    "wof:name":"Georgia",
    "wof:placetype":"locality"
},
  "geometry": {"coordinates":[-77.53783,18.44961],"type":"Point"}
}