{
  "type": "Feature",
  "properties": {
    "gn:admin1_code":"09",
    "gn:admin2_code":"629.0",
    "gn:asciiname":"Industry",
    "gn:country_code":"JM",
    "gn:dem":648,
    "gn:feature_class":"P",
    "gn:feature_code":"PPL",
    "gn:name":"Industry",
    "gn:population":0,
    "gn:timezone":"America/Jamaica",
    "iso:country":"JM",
    "wof:name":"Industry",
    "wof:placetype":"locality"
},
  "geometry": {"coordinates":[-77.24829,18.38413],"type":"Point"}
}