{
  "type": "Feature",
  "properties": {
    "gn:admin1_code":"12",
    "gn:asciiname":"Hermitage",
    "gn:country_code":"JM",
    "gn:dem":244,
    "gn:feature_class":"P",
    "gn:feature_code":"PPL",
    "gn:name":"Hermitage",
    "gn:population":0,
    "gn:timezone":"America/Jamaica",
    "iso:country":"JM",
    "wof:name":"Hermitage",
    "wof:placetype":"locality"
},
  "geometry": {"coordinates":[-77.90075,18.27293],"type":"Point"}
}