{
  "type": "Feature",
  "properties": {
    "gn:admin1_code":"8.0",
    "gn:admin2_code":"15129",
    "gn:asciiname":"Mount Dispute",
    "gn:country_code":"JM",
    "gn:dem":980,
    "gn:feature_class":"P",
    "gn:feature_code":"PPL",
    "gn:name":"Mount Dispute",
    "gn:population":0,
    "gn:timezone":"America/Jamaica",
    "iso:country":"JM",
    "wof:name":"Mount Dispute",
    "wof:placetype":"locality"
},
  "geometry": {"coordinates":[-76.67123000000002,17.99873999999999],"type":"Point"}
}