{
  "type": "Feature",
  "properties": {
    "gn:admin1_code":"9.0",
    "gn:admin2_code":"635",
    "gn:asciiname":"Staketon",
    "gn:country_code":"JM",
    "gn:dem":346,
    "gn:feature_class":"P",
    "gn:feature_code":"PPL",
    "gn:name":"Staketon",
    "gn:population":0,
    "gn:timezone":"America/Jamaica",
    "iso:country":"JM",
    "wof:name":"Staketon",
    "wof:placetype":"locality"
},
  "geometry": {"coordinates":[-77.13333,18.31667],"type":"Point"}
}