{
  "type": "Feature",
  "properties": {
    "gn:admin1_code":"12",
    "gn:admin2_code":"868.0",
    "gn:asciiname":"Jericho",
    "gn:country_code":"JM",
    "gn:dem":487,
    "gn:feature_class":"P",
    "gn:feature_code":"PPL",
    "gn:name":"Jericho",
    "gn:population":0,
    "gn:timezone":"America/Jamaica",
    "iso:country":"JM",
    "wof:name":"Jericho",
    "wof:placetype":"locality"
},
  "geometry": {"coordinates":[-77.85208,18.32965],"type":"Point"}
}