{
  "type": "Feature",
  "properties": {
    "gn:admin1_code":"08",
    "gn:admin2_code":"15003.0",
    "gn:asciiname":"College Commons",
    "gn:country_code":"JM",
    "gn:dem":170,
    "gn:feature_class":"P",
    "gn:feature_code":"PPL",
    "gn:name":"College Commons",
    "gn:population":0,
    "gn:timezone":"America/Jamaica",
    "iso:country":"JM",
    "wof:name":"College Commons",
    "wof:placetype":"locality"
},
  "geometry": {"coordinates":[-76.74993000000001,17.99922],"type":"Point"}
}