{
  "type": "Feature",
  "properties": {
    "gn:admin1_code":"14",
    "gn:admin2_code":"325.0",
    "gn:asciiname":"Grossett Village",
    "gn:cc2":"JM",
    "gn:country_code":"JM",
    "gn:dem":89,
    "gn:feature_class":"P",
    "gn:feature_code":"PPL",
    "gn:name":"Grossett Village",
    "gn:population":0,
    "gn:timezone":"America/Jamaica",
    "iso:country":"JM",
    "name:und_x_variant":[
        "Grossett",
        "Grossett Village"
    ],
    "wof:name":"Grossett Village",
    "wof:placetype":"locality"
},
  "geometry": {"coordinates":[-76.34999999999999,17.93332999999999],"type":"Point"}
}