{
  "type": "Feature",
  "properties": {
    "gn:admin1_code":"16.0",
    "gn:asciiname":"New Shafton",
    "gn:cc2":"JM",
    "gn:country_code":"JM",
    "gn:dem":77,
    "gn:feature_class":"P",
    "gn:feature_code":"PPL",
    "gn:name":"New Shafton",
    "gn:population":0,
    "gn:timezone":"America/Jamaica",
    "iso:country":"JM",
    "name:und_x_variant":[
        "Shafeston",
        "Shafston",
        "New Shafton"
    ],
    "wof:name":"New Shafton",
    "wof:placetype":"locality"
},
  "geometry": {"coordinates":[-78.03333000000001,18.16667],"type":"Point"}
}