{
  "type": "Feature",
  "properties": {
    "iso:country":"JM",
    "name:cat_x_preferred":[
        "Good Hope"
    ],
    "name:deu_x_preferred":[
        "Good Hope"
    ],
    "name:ell_x_preferred":[
        "\u0393\u03ba\u03bf\u03c5\u03bd\u03c4 \u03a7\u03cc\u03bf\u03c5\u03c0"
    ],
    "name:fra_x_preferred":[
        "Goodhope"
    ],
    "name:hbs_x_preferred":[
        "Gud Houp"
    ],
    "name:ind_x_preferred":[
        "Good Hope"
    ],
    "name:ita_x_preferred":[
        "Good Hope"
    ],
    "name:nld_x_preferred":[
        "Good Hope"
    ],
    "name:pol_x_preferred":[
        "Good Hope"
    ],
    "name:por_x_preferred":[
        "Good Hope"
    ],
    "name:slv_x_preferred":[
        "Good Hope"
    ],
    "name:spa_x_preferred":[
        "Good Hope"
    ],
    "name:srp_x_preferred":[
        "\u0413\u0443\u0434 \u0425\u043e\u0443\u043f"
    ],
    "name:vol_x_preferred":[
        "Good Hope"
    ],
    "qs:gn_country":"JM",
    "qs:gn_fcode":"PPL",
    "qs:gn_pop":0,
    "qs:name":"Good Hope",
    "qs:name_adm0":"Jamaica",
    "qs:name_adm1":"Westmoreland",
    "qs:photos":388,
    "qs:photos_1k":79,
    "qs:photos_9k":2,
    "qs:photos_9r":5,
    "qs:photos_all":388,
    "qs:photos_sr":6,
    "qs:placetype":"Town",
    "qs:pop_sr":"0",
    "qs:woe_adm0":23424858,
    "wd:wordcount":152,
    "wof:name":"Good Hope",
    "wof:placetype":"locality"
},
  "geometry": {"coordinates":[-78.33796,18.26492],"type":"Point"}
}