{
  "type": "Feature",
  "properties": {
    "gn:admin1_code":"1.0",
    "gn:admin2_code":"1382",
    "gn:asciiname":"Liberty Hill",
    "gn:country_code":"JM",
    "gn:dem":5,
    "gn:feature_class":"P",
    "gn:feature_code":"PPL",
    "gn:name":"Liberty Hill",
    "gn:population":0,
    "gn:timezone":"America/Jamaica",
    "iso:country":"JM",
    "name:ceb_x_preferred":[
        "Liberty Hill"
    ],
    "name:deu_x_preferred":[
        "Liberty Hill"
    ],
    "name:swe_x_preferred":[
        "Liberty Hill"
    ],
    "wof:name":"Liberty Hill",
    "wof:placetype":"locality"
},
  "geometry": {"coordinates":[-77.23333000000002,17.76667],"type":"Point"}
}