{
  "type": "Feature",
  "properties": {
    "iso:country":"JM",
    "name:eng_x_preferred":[
        "Drapers"
    ],
    "qs:gn_country":"JM",
    "qs:gn_fcode":"PPL",
    "qs:gn_pop":0,
    "qs:name":"Drapers",
    "qs:name_adm0":"Jamaica",
    "qs:name_adm1":"Portland",
    "qs:photos":73,
    "qs:photos_1k":15,
    "qs:photos_9k":1,
    "qs:photos_9r":2,
    "qs:photos_all":73,
    "qs:photos_sr":2,
    "qs:placetype":"Town",
    "qs:pop_sr":"0",
    "qs:woe_adm0":23424858,
    "wd:wordcount":444,
    "wof:name":"Drapers",
    "wof:placetype":"locality"
},
  "geometry": {"coordinates":[-76.40946,18.17519],"type":"Point"}
}