{
  "type": "Feature",
  "properties": {
    "gn:admin1_code":"1.0",
    "gn:admin2_code":"1383",
    "gn:asciiname":"Moreland",
    "gn:country_code":"JM",
    "gn:dem":7,
    "gn:feature_class":"P",
    "gn:feature_code":"PPL",
    "gn:name":"Moreland",
    "gn:population":0,
    "gn:timezone":"America/Jamaica",
    "iso:country":"JM",
    "wof:name":"Moreland",
    "wof:placetype":"locality"
},
  "geometry": {"coordinates":[-77.21602,17.81888],"type":"Point"}
}