{
  "type": "Feature",
  "properties": {
    "gn:admin1_code":"01",
    "gn:admin2_code":"1378.0",
    "gn:asciiname":"Heathfield",
    "gn:cc2":"JM",
    "gn:country_code":"JM",
    "gn:dem":9,
    "gn:feature_class":"P",
    "gn:feature_code":"PPL",
    "gn:name":"Heathfield",
    "gn:population":0,
    "gn:timezone":"America/Jamaica",
    "iso:country":"JM",
    "name:ceb_x_preferred":[
        "Heathfield"
    ],
    "name:deu_x_preferred":[
        "Heathfield"
    ],
    "name:ita_x_preferred":[
        "Heathfield"
    ],
    "name:pol_x_preferred":[
        "Heathfield"
    ],
    "name:swe_x_preferred":[
        "Heathfield"
    ],
    "name:und_x_variant":[
        "Healthfield",
        "Heathfield"
    ],
    "wof:name":"Heathfield",
    "wof:placetype":"locality"
},
  "geometry": {"coordinates":[-77.28333000000001,17.81667000000001],"type":"Point"}
}