{
  "type": "Feature",
  "properties": {
    "gn:admin1_code":"11.0",
    "gn:admin2_code":"1145",
    "gn:asciiname":"Lower Warminster",
    "gn:country_code":"JM",
    "gn:dem":192,
    "gn:feature_class":"P",
    "gn:feature_code":"PPL",
    "gn:name":"Lower Warminster",
    "gn:population":0,
    "gn:timezone":"America/Jamaica",
    "iso:country":"JM",
    "wof:name":"Lower Warminster",
    "wof:placetype":"locality"
},
  "geometry": {"coordinates":[-77.63333,17.95],"type":"Point"}
}