{
  "type": "Feature",
  "properties": {
    "gn:admin1_code":"2.0",
    "gn:admin2_code":"916",
    "gn:asciiname":"Ramble Pen",
    "gn:country_code":"JM",
    "gn:dem":281,
    "gn:feature_class":"P",
    "gn:feature_code":"PPL",
    "gn:name":"Ramble Pen",
    "gn:population":0,
    "gn:timezone":"America/Jamaica",
    "iso:country":"JM",
    "name:und_x_variant":[
        "Ramble House",
        "Ramble Pen"
    ],
    "wof:name":"Ramble Pen",
    "wof:placetype":"locality"
},
  "geometry": {"coordinates":[-78.01682,18.3333],"type":"Point"}
}