{
  "type": "Feature",
  "properties": {
    "gn:admin1_code":"7.0",
    "gn:admin2_code":"437",
    "gn:asciiname":"Skibo",
    "gn:country_code":"JM",
    "gn:dem":46,
    "gn:feature_class":"P",
    "gn:feature_code":"PPL",
    "gn:name":"Skibo",
    "gn:population":0,
    "gn:timezone":"America/Jamaica",
    "iso:country":"JM",
    "wof:name":"Skibo",
    "wof:placetype":"locality"
},
  "geometry": {"coordinates":[-76.63441999999998,18.19219],"type":"Point"}
}