{
  "type": "Feature",
  "properties": {
    "gn:admin1_code":"7.0",
    "gn:admin2_code":"402",
    "gn:asciiname":"Whitehall",
    "gn:country_code":"JM",
    "gn:dem":250,
    "gn:feature_class":"P",
    "gn:feature_code":"PPL",
    "gn:name":"Whitehall",
    "gn:population":0,
    "gn:timezone":"America/Jamaica",
    "iso:country":"JM",
    "name:ara_x_preferred":[
        "\u0648\u0627\u064a\u062a \u0647\u0648\u0644"
    ],
    "name:ast_x_preferred":[
        "Whitehall"
    ],
    "name:aze_x_preferred":[
        "Uaythol"
    ],
    "name:bel_x_preferred":[
        "\u0423\u0430\u0439\u0442\u0445\u043e\u043b"
    ],
    "name:cat_x_preferred":[
        "Whitehall"
    ],
    "name:ces_x_preferred":[
        "Whitehall"
    ],
    "name:cym_x_preferred":[
        "Whitehall"
    ],
    "name:dan_x_preferred":[
        "Whitehall"
    ],
    "name:deu_x_preferred":[
        "Whitehall"
    ],
    "name:epo_x_preferred":[
        "Whitehall"
    ],
    "name:est_x_preferred":[
        "Whitehall"
    ],
    "name:fas_x_preferred":[
        "\u0648\u0627\u06cc\u062a\u200c\u0647\u0627\u0644"
    ],
    "name:fin_x_preferred":[
        "Whitehall"
    ],
    "name:fra_x_preferred":[
        "Whitehall"
    ],
    "name:gle_x_preferred":[
        "Whitehall"
    ],
    "name:heb_x_preferred":[
        "\u05d5\u05d9\u05d9\u05d8\u05d4\u05d5\u05dc"
    ],
    "name:hye_x_preferred":[
        "\u0548\u0582\u0561\u0575\u0569\u0570\u0578\u056c"
    ],
    "name:ind_x_preferred":[
        "Whitehall"
    ],
    "name:ita_x_preferred":[
        "Whitehall"
    ],
    "name:jpn_x_preferred":[
        "\u30db\u30ef\u30a4\u30c8\u30db\u30fc\u30eb"
    ],
    "name:kaz_x_preferred":[
        "\u0423\u0430\u0439\u0442\u0445\u043e\u043b\u043b"
    ],
    "name:mri_x_preferred":[
        "Whitehall"
    ],
    "name:nld_x_preferred":[
        "Whitehall"
    ],
    "name:nno_x_preferred":[
        "Whitehall"
    ],
    "name:nor_x_preferred":[
        "Whitehall"
    ],
    "name:pnb_x_preferred":[
        "\u0648\u0627\u0626\u06cc\u0679 \u06c1\u0627\u0644"
    ],
    "name:pol_x_preferred":[
        "Whitehall"
    ],
    "name:por_x_preferred":[
        "Whitehall"
    ],
    "name:rus_x_preferred":[
        "\u0423\u0430\u0439\u0442\u0445\u043e\u043b\u043b"
    ],
    "name:slk_x_preferred":[
        "Whitehall"
    ],
    "name:spa_x_preferred":[
        "Whitehall"
    ],
    "name:swe_x_preferred":[
        "Whitehall"
    ],
    "name:tur_x_preferred":[
        "Whitehall"
    ],
    "name:ukr_x_preferred":[
        "\u0412\u0430\u0439\u0442\u0445\u043e\u043b"
    ],
    "name:urd_x_preferred":[
        "\u0648\u0627\u0626\u0679 \u06c1\u0627\u0644"
    ],
    "name:vie_x_preferred":[
        "Whitehall"
    ],
    "wof:name":"Whitehall",
    "wof:placetype":"locality"
},
  "geometry": {"coordinates":[-76.71581,18.20959],"type":"Point"}
}