{
  "type": "Feature",
  "properties": {
    "gn:admin1_code":"16.0",
    "gn:admin2_code":"1038",
    "gn:asciiname":"Masemure",
    "gn:country_code":"JM",
    "gn:dem":26,
    "gn:feature_class":"P",
    "gn:feature_code":"PPL",
    "gn:name":"Masemure",
    "gn:population":0,
    "gn:timezone":"America/Jamaica",
    "iso:country":"JM",
    "wof:name":"Masemure",
    "wof:placetype":"locality"
},
  "geometry": {"coordinates":[-78.21689000000001,18.27468],"type":"Point"}
}