{
  "type": "Feature",
  "properties": {
    "gn:admin1_code":"7.0",
    "gn:admin2_code":"401",
    "gn:asciiname":"Windsor Castle",
    "gn:country_code":"JM",
    "gn:dem":23,
    "gn:feature_class":"P",
    "gn:feature_code":"PPL",
    "gn:name":"Windsor Castle",
    "gn:population":0,
    "gn:timezone":"America/Jamaica",
    "iso:country":"JM",
    "wof:name":"Windsor Castle",
    "wof:placetype":"locality"
},
  "geometry": {"coordinates":[-76.69935,18.2598],"type":"Point"}
}