{
  "type": "Feature",
  "properties": {
    "gn:admin1_code":"07",
    "gn:admin2_code":"405.0",
    "gn:asciiname":"Friendship",
    "gn:country_code":"JM",
    "gn:dem":294,
    "gn:feature_class":"P",
    "gn:feature_code":"PPL",
    "gn:name":"Friendship",
    "gn:population":0,
    "gn:timezone":"America/Jamaica",
    "iso:country":"JM",
    "wof:name":"Friendship",
    "wof:placetype":"locality"
},
  "geometry": {"coordinates":[-76.61667,18.18333],"type":"Point"}
}