{
  "type": "Feature",
  "properties": {
    "gn:admin1_code":"13",
    "gn:admin2_code":"529.0",
    "gn:asciiname":"Aleppo",
    "gn:country_code":"JM",
    "gn:dem":198,
    "gn:feature_class":"P",
    "gn:feature_code":"PPL",
    "gn:name":"Aleppo",
    "gn:population":0,
    "gn:timezone":"America/Jamaica",
    "iso:country":"JM",
    "wof:name":"Aleppo",
    "wof:placetype":"locality"
},
  "geometry": {"coordinates":[-76.86301,18.23879],"type":"Point"}
}