{
  "type": "Feature",
  "properties": {
    "gn:admin1_code":"15.0",
    "gn:admin2_code":"715",
    "gn:asciiname":"Windsor",
    "gn:country_code":"JM",
    "gn:dem":103,
    "gn:feature_class":"P",
    "gn:feature_code":"PPL",
    "gn:name":"Windsor",
    "gn:population":0,
    "gn:timezone":"America/Jamaica",
    "iso:country":"JM",
    "name:ara_x_preferred":[
        "\u0648\u0646\u0632\u0631"
    ],
    "name:ast_x_preferred":[
        "Windsor"
    ],
    "name:azb_x_preferred":[
        "\u0648\u06cc\u0646\u0632\u0631"
    ],
    "name:ben_x_preferred":[
        "\u0989\u0987\u09a8\u09cd\u09a1\u09b8\u09b0"
    ],
    "name:bul_x_preferred":[
        "\u0423\u0438\u043d\u0434\u0437\u043e\u0440"
    ],
    "name:cat_x_preferred":[
        "Windsor"
    ],
    "name:ceb_x_preferred":[
        "Windsor"
    ],
    "name:ces_x_preferred":[
        "Windsor"
    ],
    "name:dan_x_preferred":[
        "Windsor"
    ],
    "name:deu_x_preferred":[
        "Windsor"
    ],
    "name:ell_x_preferred":[
        "\u0393\u03bf\u03c5\u03af\u03bd\u03c4\u03c3\u03bf\u03c1"
    ],
    "name:epo_x_preferred":[
        "Windsor"
    ],
    "name:est_x_preferred":[
        "Windsor"
    ],
    "name:eus_x_preferred":[
        "Windsor"
    ],
    "name:fas_x_preferred":[
        "\u0648\u06cc\u0646\u062f\u0633\u0648\u0631"
    ],
    "name:fin_x_preferred":[
        "Windsor"
    ],
    "name:fra_x_preferred":[
        "Windsor"
    ],
    "name:heb_x_preferred":[
        "\u05d5\u05d5\u05d9\u05e0\u05d3\u05d6\u05d5\u05e8"
    ],
    "name:hin_x_preferred":[
        "\u0935\u093f\u0902\u0921\u0938\u0930"
    ],
    "name:ind_x_preferred":[
        "Windsor"
    ],
    "name:isl_x_preferred":[
        "Windsor"
    ],
    "name:ita_x_preferred":[
        "Windsor"
    ],
    "name:jpn_x_preferred":[
        "\u30a6\u30a3\u30f3\u30b6\u30fc"
    ],
    "name:kat_x_preferred":[
        "\u10e3\u10d8\u10dc\u10eb\u10dd\u10e0\u10d8"
    ],
    "name:kor_x_preferred":[
        "\uc708\uc800"
    ],
    "name:lav_x_preferred":[
        "Vindzors"
    ],
    "name:lit_x_preferred":[
        "Vindzoras"
    ],
    "name:ltz_x_preferred":[
        "Windsor"
    ],
    "name:nld_x_preferred":[
        "Windsor"
    ],
    "name:nno_x_preferred":[
        "Windsor"
    ],
    "name:nor_x_preferred":[
        "Windsor"
    ],
    "name:pol_x_preferred":[
        "Windsor"
    ],
    "name:por_x_preferred":[
        "Windsor"
    ],
    "name:ron_x_preferred":[
        "Windsor"
    ],
    "name:rus_x_preferred":[
        "\u0412\u0438\u043d\u0434\u0437\u043e\u0440"
    ],
    "name:sco_x_preferred":[
        "Windsor"
    ],
    "name:slk_x_preferred":[
        "Windsor"
    ],
    "name:spa_x_preferred":[
        "Windsor"
    ],
    "name:srp_x_preferred":[
        "\u0412\u0438\u043d\u0434\u0437\u043e\u0440"
    ],
    "name:swe_x_preferred":[
        "Windsor"
    ],
    "name:tur_x_preferred":[
        "Windsor"
    ],
    "name:ukr_x_preferred":[
        "\u0412\u0456\u043d\u0434\u0437\u043e\u0440"
    ],
    "name:urd_x_preferred":[
        "\u0648\u0646\u0688\u0633\u0648\u0631"
    ],
    "name:vie_x_preferred":[
        "Windsor"
    ],
    "name:vol_x_preferred":[
        "Windsor"
    ],
    "name:zho_cn_x_preferred":[
        "\u6e29\u838e"
    ],
    "name:zho_tw_x_preferred":[
        "\u6eab\u838e"
    ],
    "name:zho_x_preferred":[
        "\u6eab\u838e"
    ],
    "wof:name":"Windsor",
    "wof:placetype":"locality"
},
  "geometry": {"coordinates":[-77.64776000000001,18.35945],"type":"Point"}
}