{
  "type": "Feature",
  "properties": {
    "gn:admin1_code":"15.0",
    "gn:admin2_code":"715",
    "gn:asciiname":"Windsor",
    "gn:country_code":"JM",
    "gn:dem":103,
    "gn:feature_class":"P",
    "gn:feature_code":"PPL",
    "gn:name":"Windsor",
    "gn:population":0,
    "gn:timezone":"America/Jamaica",
    "iso:country":"JM",
    "wof:name":"Windsor",
    "wof:placetype":"locality"
},
  "geometry": {"coordinates":[-77.64775999999998,18.35945],"type":"Point"}
}