{
  "type": "Feature",
  "properties": {
    "gn:admin1_code":"14.0",
    "gn:admin2_code":"308",
    "gn:asciiname":"Serge Island",
    "gn:country_code":"JM",
    "gn:dem":109,
    "gn:feature_class":"P",
    "gn:feature_code":"PPL",
    "gn:name":"Serge Island",
    "gn:population":0,
    "gn:timezone":"America/Jamaica",
    "iso:country":"JM",
    "wof:name":"Serge Island",
    "wof:placetype":"locality"
},
  "geometry": {"coordinates":[-76.48333000000002,17.95],"type":"Point"}
}