{
  "type": "Feature",
  "properties": {
    "gn:admin1_code":"14",
    "gn:admin2_code":"303.0",
    "gn:asciiname":"Arntally",
    "gn:country_code":"JM",
    "gn:dem":889,
    "gn:feature_class":"P",
    "gn:feature_code":"PPL",
    "gn:name":"Arntally",
    "gn:population":0,
    "gn:timezone":"America/Jamaica",
    "iso:country":"JM",
    "name:und_x_variant":[
        "Arntully"
    ],
    "wof:name":"Arntally",
    "wof:placetype":"locality"
},
  "geometry": {"coordinates":[-76.59999999999999,18.01667],"type":"Point"}
}