{
  "type": "Feature",
  "properties": {
    "gn:admin1_code":"07",
    "gn:admin2_code":"434.0",
    "gn:asciiname":"Albany",
    "gn:country_code":"JM",
    "gn:dem":644,
    "gn:feature_class":"P",
    "gn:feature_code":"PPL",
    "gn:name":"Albany",
    "gn:population":0,
    "gn:timezone":"America/Jamaica",
    "iso:country":"JM",
    "name:bel_x_preferred":[
        "\u041e\u043b\u0431\u0430\u043d\u0456"
    ],
    "name:bul_x_preferred":[
        "\u041e\u043b\u0431\u0430\u043d\u0438"
    ],
    "name:cat_x_preferred":[
        "Albany"
    ],
    "name:ceb_x_preferred":[
        "Albany"
    ],
    "name:ces_x_preferred":[
        "Albany"
    ],
    "name:cym_x_preferred":[
        "Albany"
    ],
    "name:dan_x_preferred":[
        "Albany"
    ],
    "name:deu_x_preferred":[
        "Albany"
    ],
    "name:epo_x_preferred":[
        "Albany"
    ],
    "name:est_x_preferred":[
        "Albany"
    ],
    "name:eus_x_preferred":[
        "Albany"
    ],
    "name:fas_x_preferred":[
        "\u0622\u0644\u0628\u0627\u0646\u06cc"
    ],
    "name:fin_x_preferred":[
        "Albany"
    ],
    "name:fra_x_preferred":[
        "Albany"
    ],
    "name:glg_x_preferred":[
        "Albany"
    ],
    "name:heb_x_preferred":[
        "\u05d0\u05d5\u05dc\u05d1\u05e0\u05d9"
    ],
    "name:hun_x_preferred":[
        "Albany"
    ],
    "name:ido_x_preferred":[
        "Albany"
    ],
    "name:ita_x_preferred":[
        "Albany"
    ],
    "name:jpn_x_preferred":[
        "\u30aa\u30fc\u30eb\u30d0\u30cb"
    ],
    "name:kor_x_preferred":[
        "\uc62c\ubc84\ub2c8"
    ],
    "name:mlg_x_preferred":[
        "Albany"
    ],
    "name:nld_x_preferred":[
        "Albany"
    ],
    "name:nor_x_preferred":[
        "Albany"
    ],
    "name:oci_x_preferred":[
        "Albany"
    ],
    "name:pol_x_preferred":[
        "Albany"
    ],
    "name:por_x_preferred":[
        "Albany"
    ],
    "name:ron_x_preferred":[
        "Albany"
    ],
    "name:rus_x_preferred":[
        "\u041e\u043b\u0431\u0430\u043d\u0438"
    ],
    "name:slk_x_preferred":[
        "Albany"
    ],
    "name:spa_x_preferred":[
        "Albany"
    ],
    "name:srp_x_preferred":[
        "\u041e\u043b\u0431\u0430\u043d\u0438"
    ],
    "name:swa_x_preferred":[
        "Albany"
    ],
    "name:swe_x_preferred":[
        "Albany"
    ],
    "name:tha_x_preferred":[
        "\u0e2d\u0e2d\u0e25\u0e41\u0e1a\u0e19\u0e35"
    ],
    "name:tur_x_preferred":[
        "Albany"
    ],
    "name:ukr_x_preferred":[
        "\u041e\u043b\u0431\u0430\u043d\u0456"
    ],
    "name:urd_x_preferred":[
        "\u0627\u0644\u0628\u0627\u0646\u06cc"
    ],
    "name:vol_x_preferred":[
        "Albany"
    ],
    "name:war_x_preferred":[
        "Albany"
    ],
    "name:zho_x_preferred":[
        "\u5965\u5c14\u5df4\u5c3c"
    ],
    "wof:name":"Albany",
    "wof:placetype":"locality"
},
  "geometry": {"coordinates":[-76.61667,18.13333],"type":"Point"}
}