{
  "type": "Feature",
  "properties": {
    "gn:admin1_code":"07",
    "gn:admin2_code":"434.0",
    "gn:asciiname":"Albany",
    "gn:country_code":"JM",
    "gn:dem":644,
    "gn:feature_class":"P",
    "gn:feature_code":"PPL",
    "gn:name":"Albany",
    "gn:population":0,
    "gn:timezone":"America/Jamaica",
    "iso:country":"JM",
    "wof:name":"Albany",
    "wof:placetype":"locality"
},
  "geometry": {"coordinates":[-76.61667,18.13333],"type":"Point"}
}