{
  "type": "Feature",
  "properties": {
    "gn:admin1_code":"09",
    "gn:admin2_code":"630.0",
    "gn:asciiname":"Carton",
    "gn:country_code":"JM",
    "gn:dem":405,
    "gn:feature_class":"P",
    "gn:feature_code":"PPL",
    "gn:name":"Carton",
    "gn:population":0,
    "gn:timezone":"America/Jamaica",
    "iso:country":"JM",
    "name:fas_x_preferred":[
        "\u06a9\u0627\u0631\u062a\u0646"
    ],
    "name:fra_x_preferred":[
        "Carton"
    ],
    "name:kor_x_preferred":[
        "\uc885\uc774\uac11"
    ],
    "name:srp_x_preferred":[
        "Karton"
    ],
    "wof:name":"Carton",
    "wof:placetype":"locality"
},
  "geometry": {"coordinates":[-77.18333,18.35],"type":"Point"}
}