{
  "type": "Feature",
  "properties": {
    "gn:admin1_code":"14",
    "gn:admin2_code":"303.0",
    "gn:asciiname":"Whitfield Hall",
    "gn:country_code":"JM",
    "gn:dem":846,
    "gn:feature_class":"P",
    "gn:feature_code":"PPLL",
    "gn:name":"Whitfield Hall",
    "gn:population":0,
    "gn:timezone":"America/Jamaica",
    "iso:country":"JM",
    "wof:name":"Whitfield Hall",
    "wof:placetype":"locality"
},
  "geometry": {"coordinates":[-76.59811999999999,18.00722],"type":"Point"}
}