{
  "type": "Feature",
  "properties": {
    "gn:admin1_code":"14.0",
    "gn:admin2_code":"310",
    "gn:asciiname":"White Hall",
    "gn:country_code":"JM",
    "gn:dem":228,
    "gn:feature_class":"P",
    "gn:feature_code":"PPLL",
    "gn:name":"White Hall",
    "gn:population":0,
    "gn:timezone":"America/Jamaica",
    "iso:country":"JM",
    "wof:name":"White Hall",
    "wof:placetype":"locality"
},
  "geometry": {"coordinates":[-76.44781999999999,17.95932999999999],"type":"Point"}
}