{
  "type": "Feature",
  "properties": {
    "gn:admin1_code":"14.0",
    "gn:admin2_code":"310",
    "gn:asciiname":"White Hall",
    "gn:country_code":"JM",
    "gn:dem":228,
    "gn:feature_class":"P",
    "gn:feature_code":"PPLL",
    "gn:name":"White Hall",
    "gn:population":0,
    "gn:timezone":"America/Jamaica",
    "iso:country":"JM",
    "name:cat_x_preferred":[
        "White Hall"
    ],
    "name:ceb_x_preferred":[
        "White Hall"
    ],
    "name:deu_x_preferred":[
        "White Hall"
    ],
    "name:fra_x_preferred":[
        "White Hall"
    ],
    "name:ita_x_preferred":[
        "White Hall"
    ],
    "name:nld_x_preferred":[
        "White Hall"
    ],
    "name:pol_x_preferred":[
        "White Hall"
    ],
    "name:por_x_preferred":[
        "White Hall"
    ],
    "name:srp_x_preferred":[
        "\u0412\u0430\u0458\u0442 \u0425\u043e\u043b"
    ],
    "name:vol_x_preferred":[
        "White Hall"
    ],
    "wof:name":"White Hall",
    "wof:placetype":"locality"
},
  "geometry": {"coordinates":[-76.44781999999999,17.95932999999999],"type":"Point"}
}