{
  "type": "Feature",
  "properties": {
    "gn:admin1_code":"11",
    "gn:admin2_code":"1153.0",
    "gn:asciiname":"Iver Cottage",
    "gn:country_code":"JM",
    "gn:dem":484,
    "gn:feature_class":"P",
    "gn:feature_code":"PPL",
    "gn:name":"Iver Cottage",
    "gn:population":0,
    "gn:timezone":"America/Jamaica",
    "iso:country":"JM",
    "name:und_x_variant":[
        "Iver",
        "Iver Cottage"
    ],
    "wof:name":"Iver Cottage",
    "wof:placetype":"locality"
},
  "geometry": {"coordinates":[-77.7133,17.95756],"type":"Point"}
}