{
  "type": "Feature",
  "properties": {
    "gn:admin1_code":"11",
    "gn:admin2_code":"1129.0",
    "gn:asciiname":"Elim",
    "gn:country_code":"JM",
    "gn:dem":21,
    "gn:feature_class":"P",
    "gn:feature_code":"PPL",
    "gn:name":"Elim",
    "gn:population":0,
    "gn:timezone":"America/Jamaica",
    "iso:country":"JM",
    "name:azb_x_preferred":[
        "\u0627\u0644\u06cc\u0645"
    ],
    "name:bre_x_preferred":[
        "Elim"
    ],
    "name:ceb_x_preferred":[
        "Elim"
    ],
    "name:deu_x_preferred":[
        "Elim"
    ],
    "name:fra_x_preferred":[
        "Elim"
    ],
    "name:ita_x_preferred":[
        "Elim"
    ],
    "name:nld_x_preferred":[
        "Elim"
    ],
    "name:pol_x_preferred":[
        "Elim"
    ],
    "name:por_x_preferred":[
        "Elim"
    ],
    "name:rus_x_preferred":[
        "\u042d\u043b\u0438\u043c"
    ],
    "name:srp_x_preferred":[
        "\u0415\u043b\u0438\u043c"
    ],
    "name:ukr_x_preferred":[
        "\u0415\u043b\u0456\u043c"
    ],
    "name:vol_x_preferred":[
        "Elim"
    ],
    "wof:name":"Elim",
    "wof:placetype":"locality"
},
  "geometry": {"coordinates":[-77.68124,18.12245],"type":"Point"}
}