{
  "type": "Feature",
  "properties": {
    "iso:country":"JM",
    "name:bul_x_preferred":[
        "\u0414\u0430\u043b\u0432\u0435\u0439"
    ],
    "name:ceb_x_preferred":[
        "Dalvey"
    ],
    "name:eng_x_preferred":[
        "Dalvey"
    ],
    "name:nld_x_preferred":[
        "Dalvey"
    ],
    "name:swe_x_preferred":[
        "Dalvey"
    ],
    "name:und_x_variant":[
        "Dalvy"
    ],
    "qs:gn_country":"JM",
    "qs:gn_fcode":"PPL",
    "qs:gn_pop":3037,
    "qs:name":"Dalvey",
    "qs:name_adm0":"Jamaica",
    "qs:name_adm1":"Saint Thomas",
    "qs:photos":22,
    "qs:photos_1k":4,
    "qs:photos_9k":1,
    "qs:photos_9r":1,
    "qs:photos_all":22,
    "qs:photos_sr":1,
    "qs:placetype":"Town",
    "qs:pop_sr":"4",
    "qs:woe_adm0":23424858,
    "wd:wordcount":26,
    "wof:name":"Dalvey",
    "wof:placetype":"locality",
    "wof:population":3037
},
  "geometry": {"coordinates":[-76.24863999999999,17.91184],"type":"Point"}
}