{
  "type": "Feature",
  "properties": {
    "iso:country":"JM",
    "qs:gn_country":"JM",
    "qs:gn_fcode":"PPLX",
    "qs:gn_pop":0,
    "qs:name":"Three Mile",
    "qs:name_adm0":"Jamaica",
    "qs:name_adm1":"Saint Andrew",
    "qs:photos":1,
    "qs:photos_1k":1,
    "qs:photos_9k":1,
    "qs:photos_9r":1,
    "qs:photos_all":1,
    "qs:photos_sr":1,
    "qs:placetype":"Suburb",
    "qs:pop_sr":"0",
    "qs:woe_adm0":23424858,
    "wd:wordcount":49,
    "wof:name":"Three Mile",
    "wof:placetype":"neighbourhood"
},
  "geometry": {"coordinates":[-76.81986999999999,17.99764],"type":"Point"}
}