{
  "type": "Feature",
  "properties": {
    "gn:country":"JM",
    "gn:fcode":"PPL",
    "gn:pop":2321,
    "iso:country":"JM",
    "qs:name":"Limit",
    "qs:photos_9r":0,
    "qs:photos_sr":0,
    "qs:pop_sr":"4",
    "wd:wordcount":203,
    "wof:name":"Limit",
    "wof:placetype":"locality",
    "wof:population":2321
},
  "geometry": {"coordinates":[-77.47121,18.15287],"type":"Point"}
}