{
  "type": "Feature",
  "properties": {
    "gn:country":"JM",
    "gn:fcode":"PPL",
    "gn:pop":2321,
    "iso:country":"JM",
    "name:ceb_x_preferred":[
        "Limit"
    ],
    "name:ces_x_preferred":[
        "Limit"
    ],
    "name:deu_x_preferred":[
        "Limit"
    ],
    "name:heb_x_preferred":[
        "\u05d2\u05d1\u05d5\u05dc"
    ],
    "name:hin_x_preferred":[
        "\u0938\u0940\u092e\u093e"
    ],
    "name:hun_x_preferred":[
        "Korl\u00e1t"
    ],
    "name:jpn_x_preferred":[
        "\u30ea\u30df\u30c3\u30c8"
    ],
    "name:kat_x_preferred":[
        "\u10d6\u10e6\u10d5\u10d0\u10e0\u10d8"
    ],
    "name:kor_x_preferred":[
        "\ub9ac\ubbf8\ud2b8"
    ],
    "name:mar_x_preferred":[
        "\u0938\u0940\u092e\u093e"
    ],
    "name:rus_x_preferred":[
        "\u041f\u0440\u0435\u0434\u0435\u043b"
    ],
    "name:sun_x_preferred":[
        "Limit"
    ],
    "name:swe_x_preferred":[
        "Limit"
    ],
    "name:ukr_x_preferred":[
        "\u041b\u0456\u043c\u0456\u0442"
    ],
    "qs:name":"Limit",
    "qs:photos_9r":0,
    "qs:photos_sr":0,
    "qs:pop_sr":"4",
    "wd:wordcount":203,
    "wof:name":"Limit",
    "wof:placetype":"locality",
    "wof:population":2321
},
  "geometry": {"coordinates":[-77.47121,18.15287],"type":"Point"}
}