{
  "type": "Feature",
  "properties": {
    "gn:admin1_code":"15",
    "gn:admin2_code":"712.0",
    "gn:asciiname":"Georges Valley",
    "gn:country_code":"JM",
    "gn:dem":97,
    "gn:feature_class":"P",
    "gn:feature_code":"PPL",
    "gn:name":"Georges Valley",
    "gn:population":0,
    "gn:timezone":"America/Jamaica",
    "iso:country":"JM",
    "wof:name":"Georges Valley",
    "wof:placetype":"locality"
},
  "geometry": {"coordinates":[-77.71666999999999,18.46667],"type":"Point"}
}