{
  "type": "Feature",
  "properties": {
    "gn:admin1_code":"13.0",
    "gn:admin2_code":"532",
    "gn:asciiname":"Rosend",
    "gn:country_code":"JM",
    "gn:dem":166,
    "gn:feature_class":"P",
    "gn:feature_code":"PPL",
    "gn:name":"Rosend",
    "gn:population":0,
    "gn:timezone":"America/Jamaica",
    "iso:country":"JM",
    "wof:name":"Rosend",
    "wof:placetype":"locality"
},
  "geometry": {"coordinates":[-76.83785,18.29677],"type":"Point"}
}