{
  "type": "Feature",
  "properties": {
    "gn:admin1_code":"14.0",
    "gn:admin2_code":"348",
    "gn:asciiname":"Readers Pen",
    "gn:country_code":"JM",
    "gn:dem":37,
    "gn:feature_class":"P",
    "gn:feature_code":"PPL",
    "gn:name":"Readers Pen",
    "gn:population":0,
    "gn:timezone":"America/Jamaica",
    "iso:country":"JM",
    "wof:name":"Readers Pen",
    "wof:placetype":"locality"
},
  "geometry": {"coordinates":[-76.40000000000001,17.88332999999999],"type":"Point"}
}