{
  "type": "Feature",
  "properties": {
    "gn:admin1_code":"09",
    "gn:admin2_code":"602.0",
    "gn:asciiname":"Dublin Castle",
    "gn:country_code":"JM",
    "gn:dem":119,
    "gn:feature_class":"P",
    "gn:feature_code":"PPL",
    "gn:name":"Dublin Castle",
    "gn:population":0,
    "gn:timezone":"America/Jamaica",
    "iso:country":"JM",
    "wof:name":"Dublin Castle",
    "wof:placetype":"locality"
},
  "geometry": {"coordinates":[-77.34999999999999,18.45],"type":"Point"}
}