{
  "type": "Feature",
  "properties": {
    "gn:admin1_code":"02",
    "gn:admin2_code":"905.0",
    "gn:asciiname":"Johnson Town",
    "gn:country_code":"JM",
    "gn:dem":8,
    "gn:feature_class":"P",
    "gn:feature_code":"PPL",
    "gn:name":"Johnson Town",
    "gn:population":0,
    "gn:timezone":"America/Jamaica",
    "iso:country":"JM",
    "name:und_x_variant":[
        "Johnston Town",
        "Johnsons Town",
        "Johnson Town"
    ],
    "wof:name":"Johnson Town",
    "wof:placetype":"locality"
},
  "geometry": {"coordinates":[-78.16521,18.43732],"type":"Point"}
}