{
  "type": "Feature",
  "properties": {
    "gn:admin1_code":"15.0",
    "gn:admin2_code":"722",
    "gn:asciiname":"Sawyers",
    "gn:country_code":"JM",
    "gn:dem":306,
    "gn:feature_class":"P",
    "gn:feature_code":"PPL",
    "gn:name":"Sawyers",
    "gn:population":0,
    "gn:timezone":"America/Jamaica",
    "iso:country":"JM",
    "name:und_x_variant":[
        "Sawyers Market",
        "Sawyers"
    ],
    "wof:name":"Sawyers",
    "wof:placetype":"locality"
},
  "geometry": {"coordinates":[-77.48765999999998,18.37716],"type":"Point"}
}