{
  "type": "Feature",
  "properties": {
    "gn:admin1_code":"10.0",
    "gn:admin2_code":"1412",
    "gn:asciiname":"Zion Hill",
    "gn:country_code":"JM",
    "gn:dem":206,
    "gn:feature_class":"P",
    "gn:feature_code":"PPL",
    "gn:name":"Zion Hill",
    "gn:population":0,
    "gn:timezone":"America/Jamaica",
    "iso:country":"JM",
    "wof:name":"Zion Hill",
    "wof:placetype":"locality"
},
  "geometry": {"coordinates":[-76.89336,18.11574],"type":"Point"}
}