{
  "type": "Feature",
  "properties": {
    "gn:admin1_code":"02",
    "gn:admin2_code":"910.0",
    "gn:asciiname":"Chigwell",
    "gn:country_code":"JM",
    "gn:dem":244,
    "gn:feature_class":"P",
    "gn:feature_code":"PPL",
    "gn:name":"Chigwell",
    "gn:population":0,
    "gn:timezone":"America/Jamaica",
    "iso:country":"JM",
    "wof:name":"Chigwell",
    "wof:placetype":"locality"
},
  "geometry": {"coordinates":[-78.03848000000001,18.40095],"type":"Point"}
}