{
  "type": "Feature",
  "properties": {
    "gn:admin1_code":"02",
    "gn:admin2_code":"910.0",
    "gn:asciiname":"Chigwell",
    "gn:country_code":"JM",
    "gn:dem":244,
    "gn:feature_class":"P",
    "gn:feature_code":"PPL",
    "gn:name":"Chigwell",
    "gn:population":0,
    "gn:timezone":"America/Jamaica",
    "iso:country":"JM",
    "name:afr_x_preferred":[
        "Chigwell"
    ],
    "name:ceb_x_preferred":[
        "Chigwell"
    ],
    "name:fas_x_preferred":[
        "\u0686\u06cc\u06af\u0648\u0644"
    ],
    "name:fra_x_preferred":[
        "Chigwell"
    ],
    "name:gle_x_preferred":[
        "Chigwell"
    ],
    "name:ita_x_preferred":[
        "Chigwell"
    ],
    "name:nld_x_preferred":[
        "Chigwell"
    ],
    "name:pol_x_preferred":[
        "Chigwell"
    ],
    "name:spa_x_preferred":[
        "Chigwell"
    ],
    "name:swe_x_preferred":[
        "Chigwell"
    ],
    "name:tur_x_preferred":[
        "Chigwell"
    ],
    "name:vol_x_preferred":[
        "Chigwell"
    ],
    "name:zho_x_preferred":[
        "\u9f4a\u683c\u5a01\u723e"
    ],
    "wof:name":"Chigwell",
    "wof:placetype":"locality"
},
  "geometry": {"coordinates":[-78.03848000000001,18.40095],"type":"Point"}
}