{
  "type": "Feature",
  "properties": {
    "gn:admin1_code":"02",
    "gn:admin2_code":"921.0",
    "gn:asciiname":"Coventry Pen",
    "gn:cc2":"JM",
    "gn:country_code":"JM",
    "gn:dem":164,
    "gn:feature_class":"P",
    "gn:feature_code":"PPL",
    "gn:name":"Coventry Pen",
    "gn:population":0,
    "gn:timezone":"America/Jamaica",
    "iso:country":"JM",
    "name:und_x_variant":[
        "Coventry",
        "Coventry Pen"
    ],
    "wof:name":"Coventry Pen",
    "wof:placetype":"locality"
},
  "geometry": {"coordinates":[-78.06667,18.41667],"type":"Point"}
}