{
  "type": "Feature",
  "properties": {
    "gn:admin1_code":"09",
    "gn:admin2_code":"651.0",
    "gn:asciiname":"Hutchensons Hale",
    "gn:cc2":"JM",
    "gn:country_code":"JM",
    "gn:dem":635,
    "gn:feature_class":"P",
    "gn:feature_code":"PPL",
    "gn:name":"Hutchensons Hale",
    "gn:population":0,
    "gn:timezone":"America/Jamaica",
    "iso:country":"JM",
    "name:und_x_variant":[
        "Hutchensons Hole",
        "Hutchensons Hale"
    ],
    "wof:name":"Hutchensons Hale",
    "wof:placetype":"locality"
},
  "geometry": {"coordinates":[-77.21666999999999,18.25],"type":"Point"}
}