{
  "type": "Feature",
  "properties": {
    "gn:admin1_code":"14",
    "gn:admin2_code":"327.0",
    "gn:asciiname":"Highland Castle",
    "gn:country_code":"JM",
    "gn:dem":104,
    "gn:feature_class":"P",
    "gn:feature_code":"PPL",
    "gn:name":"Highland Castle",
    "gn:population":0,
    "gn:timezone":"America/Jamaica",
    "iso:country":"JM",
    "wof:name":"Highland Castle",
    "wof:placetype":"locality"
},
  "geometry": {"coordinates":[-76.43333,17.91667],"type":"Point"}
}