{
  "type": "Feature",
  "properties": {
    "gn:admin1_code":"11",
    "gn:admin2_code":"1131.0",
    "gn:asciiname":"Gilnock",
    "gn:cc2":"JM",
    "gn:country_code":"JM",
    "gn:dem":26,
    "gn:feature_class":"P",
    "gn:feature_code":"PPL",
    "gn:name":"Gilnock",
    "gn:population":0,
    "gn:timezone":"America/Jamaica",
    "iso:country":"JM",
    "name:und_x_variant":[
        "Gilnock Hall",
        "Gilnock"
    ],
    "wof:name":"Gilnock",
    "wof:placetype":"locality"
},
  "geometry": {"coordinates":[-77.65000000000001,18.05],"type":"Point"}
}