{
  "type": "Feature",
  "properties": {
    "gn:admin1_code":"01",
    "gn:admin2_code":"1310.0",
    "gn:asciiname":"Arthurs Seat",
    "gn:country_code":"JM",
    "gn:dem":475,
    "gn:feature_class":"P",
    "gn:feature_code":"PPL",
    "gn:name":"Arthurs Seat",
    "gn:population":0,
    "gn:timezone":"America/Jamaica",
    "iso:country":"JM",
    "wof:name":"Arthurs Seat",
    "wof:placetype":"locality"
},
  "geometry": {"coordinates":[-77.2277,18.13709],"type":"Point"}
}