{
  "type": "Feature",
  "properties": {
    "gn:admin1_code":"10.0",
    "gn:admin2_code":"1405",
    "gn:asciiname":"Mount Augusta",
    "gn:cc2":"JM",
    "gn:country_code":"JM",
    "gn:dem":346,
    "gn:feature_class":"P",
    "gn:feature_code":"PPL",
    "gn:name":"Mount Augusta",
    "gn:population":0,
    "gn:timezone":"America/Jamaica",
    "iso:country":"JM",
    "name:und_x_variant":[
        "Mount Agusta",
        "Mount Augusta"
    ],
    "wof:name":"Mount Augusta",
    "wof:placetype":"locality"
},
  "geometry": {"coordinates":[-76.95,18.21667],"type":"Point"}
}