{
  "type": "Feature",
  "properties": {
    "gn:admin1_code":"10.0",
    "gn:admin2_code":"1405",
    "gn:asciiname":"Mount Augusta",
    "gn:cc2":"JM",
    "gn:country_code":"JM",
    "gn:dem":346,
    "gn:feature_class":"P",
    "gn:feature_code":"PPL",
    "gn:name":"Mount Augusta",
    "gn:population":0,
    "gn:timezone":"America/Jamaica",
    "iso:country":"JM",
    "name:cat_x_preferred":[
        "Mont Augusta"
    ],
    "name:ceb_x_preferred":[
        "Mount Augusta"
    ],
    "name:ces_x_preferred":[
        "Mount Augusta"
    ],
    "name:deu_x_preferred":[
        "Mount Augusta"
    ],
    "name:ita_x_preferred":[
        "Monte Augusta"
    ],
    "name:pnb_x_preferred":[
        "\u0679\u0644\u06c1 \u0622\u06af\u0633\u0679\u0627"
    ],
    "name:rus_x_preferred":[
        "\u041e\u0433\u0430\u0441\u0442\u0430"
    ],
    "name:swa_x_preferred":[
        "Mlima Augusta"
    ],
    "name:und_x_variant":[
        "Mount Agusta",
        "Mount Augusta"
    ],
    "name:zho_x_preferred":[
        "\u5967\u53e4\u65af\u5854\u5c71"
    ],
    "wof:name":"Mount Augusta",
    "wof:placetype":"locality"
},
  "geometry": {"coordinates":[-76.95,18.21667],"type":"Point"}
}