{
  "type": "Feature",
  "properties": {
    "gn:admin1_code":"1.0",
    "gn:admin2_code":"1357",
    "gn:asciiname":"Whitney Turn",
    "gn:country_code":"JM",
    "gn:dem":132,
    "gn:feature_class":"P",
    "gn:feature_code":"PPL",
    "gn:name":"Whitney Turn",
    "gn:population":0,
    "gn:timezone":"America/Jamaica",
    "iso:country":"JM",
    "name:und_x_variant":[
        "Whitnay Turn",
        "Whitney Turn"
    ],
    "wof:name":"Whitney Turn",
    "wof:placetype":"locality"
},
  "geometry": {"coordinates":[-77.39355,18.03204],"type":"Point"}
}