{
  "type": "Feature",
  "properties": {
    "gn:admin1_code":"02",
    "gn:admin2_code":"916.0",
    "gn:asciiname":"Mt Peto",
    "gn:country_code":"JM",
    "gn:dem":328,
    "gn:feature_class":"P",
    "gn:feature_code":"PPLA2",
    "gn:name":"Mt Peto",
    "gn:population":0,
    "gn:timezone":"America/Jamaica",
    "iso:country":"JM",
    "name:eng_x_preferred":[
        "Axe Adze"
    ],
    "name:eng_x_variant":[
        "Axe and Adze",
        "Mt Peto",
        "Mount Peto"
    ],
    "wof:name":"Mt Peto",
    "wof:placetype":"locality"
},
  "geometry": {"coordinates":[-78.03735999999998,18.3637],"type":"Point"}
}