{
  "type": "Feature",
  "properties": {
    "gn:admin1_code":"16.0",
    "gn:admin2_code":"1045",
    "gn:asciiname":"Long Pond Pen",
    "gn:country_code":"JM",
    "gn:dem":7,
    "gn:feature_class":"P",
    "gn:feature_code":"PPL",
    "gn:name":"Long Pond Pen",
    "gn:population":0,
    "gn:timezone":"America/Jamaica",
    "iso:country":"JM",
    "wof:name":"Long Pond Pen",
    "wof:placetype":"locality"
},
  "geometry": {"coordinates":[-78.21666999999999,18.23333],"type":"Point"}
}