{
  "type": "Feature",
  "properties": {
    "gn:admin1_code":"1.0",
    "gn:admin2_code":"1381",
    "gn:asciiname":"Pusey Hall",
    "gn:country_code":"JM",
    "gn:dem":4,
    "gn:feature_class":"P",
    "gn:feature_code":"PPL",
    "gn:name":"Pusey Hall",
    "gn:population":0,
    "gn:timezone":"America/Jamaica",
    "iso:country":"JM",
    "wof:name":"Pusey Hall",
    "wof:placetype":"locality"
},
  "geometry": {"coordinates":[-77.25,17.78333],"type":"Point"}
}