{
  "type": "Feature",
  "properties": {
    "gn:admin1_code":"10.0",
    "gn:admin2_code":"1429",
    "gn:asciiname":"Wood Hall",
    "gn:country_code":"JM",
    "gn:dem":48,
    "gn:feature_class":"P",
    "gn:feature_code":"PPL",
    "gn:name":"Wood Hall",
    "gn:population":0,
    "gn:timezone":"America/Jamaica",
    "iso:country":"JM",
    "wof:name":"Wood Hall",
    "wof:placetype":"locality"
},
  "geometry": {"coordinates":[-77.11667,17.95],"type":"Point"}
}