{
  "type": "Feature",
  "properties": {
    "gn:admin1_code":"11",
    "gn:admin2_code":"1132.0",
    "gn:asciiname":"Gutters",
    "gn:country_code":"JM",
    "gn:dem":58,
    "gn:feature_class":"P",
    "gn:feature_code":"PPL",
    "gn:name":"Gutters",
    "gn:population":0,
    "gn:timezone":"America/Jamaica",
    "iso:country":"JM",
    "wof:name":"Gutters",
    "wof:placetype":"locality"
},
  "geometry": {"coordinates":[-77.61181999999999,18.03545],"type":"Point"}
}