{
  "type": "Feature",
  "properties": {
    "gn:admin1_code":"13.0",
    "gn:admin2_code":"504",
    "gn:asciiname":"New Ramble",
    "gn:cc2":"JM",
    "gn:country_code":"JM",
    "gn:dem":212,
    "gn:feature_class":"P",
    "gn:feature_code":"PPL",
    "gn:name":"New Ramble",
    "gn:population":0,
    "gn:timezone":"America/Jamaica",
    "iso:country":"JM",
    "name:und_x_variant":[
        "Ramble",
        "New Ramble"
    ],
    "wof:name":"New Ramble",
    "wof:placetype":"locality"
},
  "geometry": {"coordinates":[-76.98333000000002,18.36667000000001],"type":"Point"}
}