{
  "type": "Feature",
  "properties": {
    "gn:admin1_code":"1.0",
    "gn:admin2_code":"1358",
    "gn:asciiname":"Pridees",
    "gn:country_code":"JM",
    "gn:dem":25,
    "gn:feature_class":"P",
    "gn:feature_code":"PPL",
    "gn:name":"Pridees",
    "gn:population":0,
    "gn:timezone":"America/Jamaica",
    "iso:country":"JM",
    "name:und_x_variant":[
        "Priddie\u2019s",
        "Predies",
        "Pridees"
    ],
    "wof:name":"Pridees",
    "wof:placetype":"locality"
},
  "geometry": {"coordinates":[-77.33556999999998,17.88156],"type":"Point"}
}