{
  "type": "Feature",
  "properties": {
    "gn:admin1_code":"02",
    "gn:admin2_code":"914.0",
    "gn:asciiname":"Chichester",
    "gn:country_code":"JM",
    "gn:dem":201,
    "gn:feature_class":"P",
    "gn:feature_code":"PPL",
    "gn:name":"Chichester",
    "gn:population":0,
    "gn:timezone":"America/Jamaica",
    "iso:country":"JM",
    "wof:name":"Chichester",
    "wof:placetype":"locality"
},
  "geometry": {"coordinates":[-77.99126,18.33526],"type":"Point"}
}