{
  "type": "Feature",
  "properties": {
    "gn:admin1_code":"16.0",
    "gn:admin2_code":"1001",
    "gn:asciiname":"Mint",
    "gn:country_code":"JM",
    "gn:dem":31,
    "gn:feature_class":"P",
    "gn:feature_code":"PPL",
    "gn:name":"Mint",
    "gn:population":0,
    "gn:timezone":"America/Jamaica",
    "iso:country":"JM",
    "name:deu_x_preferred":[
        "Mint"
    ],
    "name:fra_x_preferred":[
        "Mint"
    ],
    "name:jpn_x_preferred":[
        "Mint"
    ],
    "name:nld_x_preferred":[
        "Mint"
    ],
    "name:pol_x_preferred":[
        "Mint"
    ],
    "name:por_x_preferred":[
        "Mint"
    ],
    "name:rus_x_preferred":[
        "Mint"
    ],
    "name:swe_x_preferred":[
        "Mint"
    ],
    "name:tha_x_preferred":[
        "\u0e21\u0e34\u0e19\u0e15\u0e4c"
    ],
    "wof:name":"Mint",
    "wof:placetype":"locality"
},
  "geometry": {"coordinates":[-78.21202,18.32278],"type":"Point"}
}