{
  "type": "Feature",
  "properties": {
    "gn:admin1_code":"10.0",
    "gn:admin2_code":"1429",
    "gn:asciiname":"Logens Pen",
    "gn:country_code":"JM",
    "gn:dem":29,
    "gn:feature_class":"P",
    "gn:feature_code":"PPL",
    "gn:name":"Logens Pen",
    "gn:population":0,
    "gn:timezone":"America/Jamaica",
    "iso:country":"JM",
    "wof:name":"Logens Pen",
    "wof:placetype":"locality"
},
  "geometry": {"coordinates":[-77.13333,17.93332999999999],"type":"Point"}
}