{
  "type": "Feature",
  "properties": {
    "gn:admin1_code":"07",
    "gn:admin2_code":"412.0",
    "gn:asciiname":"Bryans Bay",
    "gn:country_code":"JM",
    "gn:dem":39,
    "gn:feature_class":"P",
    "gn:feature_code":"PPL",
    "gn:name":"Bryans Bay",
    "gn:population":0,
    "gn:timezone":"America/Jamaica",
    "iso:country":"JM",
    "wof:name":"Bryans Bay",
    "wof:placetype":"locality"
},
  "geometry": {"coordinates":[-76.47141999999999,18.19095],"type":"Point"}
}