{
  "type": "Feature",
  "properties": {
    "gn:admin1_code":"7.0",
    "gn:admin2_code":"406",
    "gn:asciiname":"Lennox",
    "gn:cc2":"JM",
    "gn:country_code":"JM",
    "gn:dem":75,
    "gn:feature_class":"P",
    "gn:feature_code":"PPL",
    "gn:name":"Lennox",
    "gn:population":0,
    "gn:timezone":"America/Jamaica",
    "iso:country":"JM",
    "name:und_x_variant":[
        "Lenox",
        "Lennox"
    ],
    "wof:name":"Lennox",
    "wof:placetype":"locality"
},
  "geometry": {"coordinates":[-76.59999999999999,18.21667],"type":"Point"}
}