{
  "type": "Feature",
  "properties": {
    "gn:admin1_code":"2.0",
    "gn:admin2_code":"934",
    "gn:asciiname":"Mount Pleasant",
    "gn:country_code":"JM",
    "gn:dem":45,
    "gn:feature_class":"P",
    "gn:feature_code":"PPL",
    "gn:name":"Mount Pleasant",
    "gn:population":0,
    "gn:timezone":"America/Jamaica",
    "iso:country":"JM",
    "wof:name":"Mount Pleasant",
    "wof:placetype":"locality"
},
  "geometry": {"coordinates":[-78.29351,18.36832],"type":"Point"}
}