{
  "type": "Feature",
  "properties": {
    "gn:country":"JM",
    "gn:fcode":"PPL",
    "gn:pop":4550,
    "iso:country":"JM",
    "name:eng_x_preferred":[
        "Seaforth"
    ],
    "name:nld_x_preferred":[
        "Seaforth"
    ],
    "name:swe_x_preferred":[
        "Seaforth"
    ],
    "name:unk_x_variant":[
        "Seaforth Village"
    ],
    "qs:name":"Seaforth",
    "qs:photos_9r":0,
    "qs:photos_sr":0,
    "qs:pop_sr":"4",
    "wd:wordcount":181,
    "wof:name":"Seaforth",
    "wof:placetype":"locality",
    "wof:population":4550
},
  "geometry": {"coordinates":[-76.4573,17.93578],"type":"Point"}
}