{
  "type": "Feature",
  "properties": {
    "gn:admin1_code":"14",
    "gn:admin2_code":"312.0",
    "gn:asciiname":"Four Feet",
    "gn:country_code":"JM",
    "gn:dem":303,
    "gn:feature_class":"P",
    "gn:feature_code":"PPL",
    "gn:name":"Four Feet",
    "gn:population":0,
    "gn:timezone":"America/Jamaica",
    "iso:country":"JM",
    "name:und_x_variant":[
        "Bowden Pen",
        "Four Feet"
    ],
    "wof:name":"Four Feet",
    "wof:placetype":"locality"
},
  "geometry": {"coordinates":[-76.37796999999998,18.01447000000001],"type":"Point"}
}