{
  "type": "Feature",
  "properties": {
    "gn:admin1_code":"07",
    "gn:admin2_code":"434.0",
    "gn:asciiname":"Burton Hall",
    "gn:country_code":"JM",
    "gn:dem":723,
    "gn:feature_class":"P",
    "gn:feature_code":"PPL",
    "gn:name":"Burton Hall",
    "gn:population":0,
    "gn:timezone":"America/Jamaica",
    "iso:country":"JM",
    "wof:name":"Burton Hall",
    "wof:placetype":"locality"
},
  "geometry": {"coordinates":[-76.55,18.11667000000001],"type":"Point"}
}