{
  "type": "Feature",
  "properties": {
    "gn:admin1_code":"09",
    "gn:admin2_code":"601.0",
    "gn:asciiname":"Content",
    "gn:country_code":"JM",
    "gn:dem":302,
    "gn:feature_class":"P",
    "gn:feature_code":"PPL",
    "gn:name":"Content",
    "gn:population":0,
    "gn:timezone":"America/Jamaica",
    "iso:country":"JM",
    "wof:name":"Content",
    "wof:placetype":"locality"
},
  "geometry": {"coordinates":[-77.39924999999999,18.42709],"type":"Point"}
}