{
  "type": "Feature",
  "properties": {
    "gn:admin1_code":"09",
    "gn:admin2_code":"601.0",
    "gn:asciiname":"Content",
    "gn:country_code":"JM",
    "gn:dem":302,
    "gn:feature_class":"P",
    "gn:feature_code":"PPL",
    "gn:name":"Content",
    "gn:population":0,
    "gn:timezone":"America/Jamaica",
    "iso:country":"JM",
    "name:deu_x_preferred":[
        "Content"
    ],
    "name:fra_x_preferred":[
        "Content"
    ],
    "name:kor_x_preferred":[
        "\ucf58\ud150\uce20"
    ],
    "name:nld_x_preferred":[
        "Content"
    ],
    "name:rus_x_preferred":[
        "\u0421\u043e\u0434\u0435\u0440\u0436\u0430\u043d\u0438\u0435"
    ],
    "name:swa_x_preferred":[
        "Maudhui"
    ],
    "name:tgk_x_preferred":[
        "\u041c\u04ef\u04b3\u0442\u0430\u0432\u043e"
    ],
    "name:ukr_x_preferred":[
        "\u0417\u043c\u0456\u0441\u0442"
    ],
    "wof:name":"Content",
    "wof:placetype":"locality"
},
  "geometry": {"coordinates":[-77.39924999999999,18.42709],"type":"Point"}
}