{
  "type": "Feature",
  "properties": {
    "gn:admin1_code":"11.0",
    "gn:admin2_code":"1101",
    "gn:asciiname":"Pisgah",
    "gn:country_code":"JM",
    "gn:dem":443,
    "gn:feature_class":"P",
    "gn:feature_code":"PPL",
    "gn:name":"Pisgah",
    "gn:population":0,
    "gn:timezone":"America/Jamaica",
    "iso:country":"JM",
    "name:ceb_x_preferred":[
        "Pisgah"
    ],
    "name:deu_x_preferred":[
        "Pisgah"
    ],
    "name:fra_x_preferred":[
        "Pisgah"
    ],
    "name:ita_x_preferred":[
        "Pisgah"
    ],
    "name:nld_x_preferred":[
        "Pisgah"
    ],
    "name:pol_x_preferred":[
        "Pisgah"
    ],
    "name:srp_x_preferred":[
        "\u041f\u0438\u0437\u0433\u0430"
    ],
    "name:swe_x_preferred":[
        "Pisgah"
    ],
    "name:vol_x_preferred":[
        "Pisgah"
    ],
    "wof:name":"Pisgah",
    "wof:placetype":"locality"
},
  "geometry": {"coordinates":[-77.88035000000001,18.20449],"type":"Point"}
}