{
  "type": "Feature",
  "properties": {
    "gn:admin1_code":"14.0",
    "gn:admin2_code":"306",
    "gn:asciiname":"Somerset",
    "gn:country_code":"JM",
    "gn:dem":290,
    "gn:feature_class":"P",
    "gn:feature_code":"PPL",
    "gn:name":"Somerset",
    "gn:population":0,
    "gn:timezone":"America/Jamaica",
    "iso:country":"JM",
    "wof:name":"Somerset",
    "wof:placetype":"locality"
},
  "geometry": {"coordinates":[-76.53564,17.98037],"type":"Point"}
}