{
  "type": "Feature",
  "properties": {
    "gn:country":"JM",
    "gn:fcode":"PPL",
    "gn:population":2763,
    "iso:country":"JM",
    "name:ben_x_preferred":[
        "\u0993\u09af\u09bc\u09c7\u0995\u09ab\u09bf\u09b2\u09cd\u09a1"
    ],
    "name:ell_x_preferred":[
        "\u0393\u03bf\u03c5\u03ad\u03b9\u03ba\u03c6\u03b9\u03bb\u03bd\u03c4"
    ],
    "name:eng_x_preferred":[
        "Wakefield"
    ],
    "name:hin_x_preferred":[
        "\u0935\u0947\u0915\u092b\u0940\u0932\u094d\u0921"
    ],
    "name:ind_x_preferred":[
        "Wakefield"
    ],
    "name:nld_x_preferred":[
        "Wakefield"
    ],
    "name:vie_x_preferred":[
        "Wakefield"
    ],
    "qs_pg:aaroncc":"JM",
    "qs_pg:gn_country":"JM",
    "qs_pg:gn_fcode":"PPL",
    "qs_pg:gn_pop":2763,
    "qs_pg:name":"Wakefield",
    "qs_pg:photos_9r":0,
    "qs_pg:photos_sr":0,
    "qs_pg:pop_sr":4,
    "qs_pg:qs_pg_placetype":"locality",
    "wof:name":"Wakefield",
    "wof:placetype":"locality",
    "wof:population":2763
},
  "geometry": {"coordinates":[-77.72183,18.41211],"type":"Point"}
}