{
  "type": "Feature",
  "properties": {
    "gn:gn_country":"JM",
    "gn:gn_fcode":"PPL",
    "gn:gn_pop":2763,
    "gn:population":2763,
    "iso:country":"JM",
    "name:dut_x_preferred":[
        "Wakefield"
    ],
    "name:eng_x_preferred":[
        "Wakefield"
    ],
    "qs_pg:aaroncc":"JM",
    "qs_pg:gn_country":"JM",
    "qs_pg:gn_fcode":"PPL",
    "qs_pg:gn_pop":2763,
    "qs_pg:name":"Wakefield",
    "qs_pg:photos_9r":0,
    "qs_pg:photos_sr":0,
    "qs_pg:pop_sr":4,
    "qs_pg:qs_pg_placetype":"locality",
    "wof:name":"Wakefield",
    "wof:placetype":"locality",
    "wof:population":2763
},
  "geometry": {"coordinates":[-77.72183,18.41211],"type":"Point"}
}