{
  "type": "Feature",
  "properties": {
    "gn:admin1_code":"15",
    "gn:asciiname":"Gales Valley",
    "gn:country_code":"JM",
    "gn:dem":184,
    "gn:feature_class":"P",
    "gn:feature_code":"PPL",
    "gn:name":"Gales Valley",
    "gn:population":0,
    "gn:timezone":"America/Jamaica",
    "iso:country":"JM",
    "wof:name":"Gales Valley",
    "wof:placetype":"locality"
},
  "geometry": {"coordinates":[-77.75,18.41667],"type":"Point"}
}