{
  "type": "Feature",
  "properties": {
    "gn:admin1_code":"12.0",
    "gn:admin2_code":"859",
    "gn:asciiname":"Spring Mount",
    "gn:cc2":"JM",
    "gn:country_code":"JM",
    "gn:dem":498,
    "gn:feature_class":"P",
    "gn:feature_code":"PPL",
    "gn:name":"Spring Mount",
    "gn:population":0,
    "gn:timezone":"America/Jamaica",
    "iso:country":"JM",
    "name:und_x_variant":[
        "Spring Mount Estate",
        "Spring Mount"
    ],
    "wof:name":"Spring Mount",
    "wof:placetype":"locality"
},
  "geometry": {"coordinates":[-77.84999999999999,18.38333],"type":"Point"}
}