{
  "type": "Feature",
  "properties": {
    "gn:admin1_code":"14",
    "gn:admin2_code":"355.0",
    "gn:asciiname":"Barking Lodge",
    "gn:country_code":"JM",
    "gn:dem":58,
    "gn:feature_class":"P",
    "gn:feature_code":"PPL",
    "gn:name":"Barking Lodge",
    "gn:population":0,
    "gn:timezone":"America/Jamaica",
    "iso:country":"JM",
    "wof:name":"Barking Lodge",
    "wof:placetype":"locality"
},
  "geometry": {"coordinates":[-76.27797,17.89775],"type":"Point"}
}