{
  "type": "Feature",
  "properties": {
    "gn:admin1_code":"15.0",
    "gn:admin2_code":"724",
    "gn:asciiname":"Saint Vincent",
    "gn:country_code":"JM",
    "gn:dem":650,
    "gn:feature_class":"P",
    "gn:feature_code":"PPL",
    "gn:name":"Saint Vincent",
    "gn:population":0,
    "gn:timezone":"America/Jamaica",
    "iso:country":"JM",
    "name:bre_x_preferred":[
        "Saint-Vincent"
    ],
    "name:cat_x_preferred":[
        "Saint Vincent"
    ],
    "name:ceb_x_preferred":[
        "Saint Vincent"
    ],
    "name:deu_x_preferred":[
        "Saint Vincent"
    ],
    "name:epo_x_preferred":[
        "Saint-Vincent"
    ],
    "name:eus_x_preferred":[
        "Saint-Vincent"
    ],
    "name:fas_x_preferred":[
        "\u0633\u0646\u062a \u0648\u06cc\u0646\u0633\u0646\u062a"
    ],
    "name:fin_x_preferred":[
        "Saint Vincent"
    ],
    "name:fra_x_preferred":[
        "Saint-Vincent"
    ],
    "name:ita_x_preferred":[
        "Saint-Vincent"
    ],
    "name:jpn_x_preferred":[
        "\u30b5\u30f3\uff1d\u30f4\u30a1\u30f3\u30b5\u30f3"
    ],
    "name:kor_x_preferred":[
        "\uc138\uc778\ud2b8\ube48\uc13c\ud2b8"
    ],
    "name:lmo_x_preferred":[
        "Saint-Vincent"
    ],
    "name:nds_x_preferred":[
        "Saint Vincent"
    ],
    "name:nld_x_preferred":[
        "Saint-Vincent"
    ],
    "name:pms_x_preferred":[
        "Saint-Vincent"
    ],
    "name:pol_x_preferred":[
        "Saint-Vincent"
    ],
    "name:por_x_preferred":[
        "Saint-Vincent"
    ],
    "name:rus_x_preferred":[
        "\u0421\u0435\u043d-\u0412\u0435\u043d\u0441\u0430\u043d"
    ],
    "name:slk_x_preferred":[
        "Saint Vincent"
    ],
    "name:spa_x_preferred":[
        "Saint-Vincent"
    ],
    "name:swe_x_preferred":[
        "Saint Vincent"
    ],
    "name:tur_x_preferred":[
        "Saint Vincent"
    ],
    "name:ukr_x_preferred":[
        "\u0421\u0435\u043d-\u0412\u0435\u043d\u0441\u0430\u043d"
    ],
    "wof:name":"Saint Vincent",
    "wof:placetype":"locality"
},
  "geometry": {"coordinates":[-77.54850999999999,18.29716],"type":"Point"}
}