{
  "type": "Feature",
  "properties": {
    "gn:admin1_code":"15.0",
    "gn:admin2_code":"724",
    "gn:asciiname":"Saint Vincent",
    "gn:country_code":"JM",
    "gn:dem":650,
    "gn:feature_class":"P",
    "gn:feature_code":"PPL",
    "gn:name":"Saint Vincent",
    "gn:population":0,
    "gn:timezone":"America/Jamaica",
    "iso:country":"JM",
    "wof:name":"Saint Vincent",
    "wof:placetype":"locality"
},
  "geometry": {"coordinates":[-77.54850999999999,18.29716],"type":"Point"}
}