{
  "type": "Feature",
  "properties": {
    "gn:admin1_code":"14.0",
    "gn:admin2_code":"352",
    "gn:asciiname":"Leith Hall",
    "gn:country_code":"JM",
    "gn:dem":27,
    "gn:feature_class":"P",
    "gn:feature_code":"PPL",
    "gn:name":"Leith Hall",
    "gn:population":0,
    "gn:timezone":"America/Jamaica",
    "iso:country":"JM",
    "wof:name":"Leith Hall",
    "wof:placetype":"locality"
},
  "geometry": {"coordinates":[-76.33735,17.8773],"type":"Point"}
}