{
  "type": "Feature",
  "properties": {
    "gn:admin1_code":"12",
    "gn:admin2_code":"847.0",
    "gn:asciiname":"Bonavista",
    "gn:country_code":"JM",
    "gn:dem":311,
    "gn:feature_class":"P",
    "gn:feature_code":"PPL",
    "gn:name":"Bonavista",
    "gn:population":0,
    "gn:timezone":"America/Jamaica",
    "iso:country":"JM",
    "name:cat_x_preferred":[
        "Bonavista"
    ],
    "name:fra_x_preferred":[
        "Bonavista"
    ],
    "name:nld_x_preferred":[
        "Bonavista"
    ],
    "wof:name":"Bonavista",
    "wof:placetype":"locality"
},
  "geometry": {"coordinates":[-77.91835,18.40531],"type":"Point"}
}