{
  "type": "Feature",
  "properties": {
    "gn:admin1_code":"4.0",
    "gn:admin2_code":"1237",
    "gn:asciiname":"Mount Prospect",
    "gn:country_code":"JM",
    "gn:dem":878,
    "gn:feature_class":"P",
    "gn:feature_code":"PPL",
    "gn:name":"Mount Prospect",
    "gn:population":0,
    "gn:timezone":"America/Jamaica",
    "iso:country":"JM",
    "wof:name":"Mount Prospect",
    "wof:placetype":"locality"
},
  "geometry": {"coordinates":[-77.58333,18.06667],"type":"Point"}
}