{
  "type": "Feature",
  "properties": {
    "gn:admin1_code":"1.0",
    "gn:admin2_code":"1334",
    "gn:asciiname":"Mount Nebo",
    "gn:country_code":"JM",
    "gn:dem":671,
    "gn:feature_class":"P",
    "gn:feature_code":"PPL",
    "gn:name":"Mount Nebo",
    "gn:population":0,
    "gn:timezone":"America/Jamaica",
    "iso:country":"JM",
    "wof:name":"Mount Nebo",
    "wof:placetype":"locality"
},
  "geometry": {"coordinates":[-77.34999999999999,18.08333],"type":"Point"}
}