{
  "type": "Feature",
  "properties": {
    "gn:admin1_code":"14.0",
    "gn:admin2_code":"310",
    "gn:asciiname":"Whitehall",
    "gn:country_code":"JM",
    "gn:dem":230,
    "gn:feature_class":"P",
    "gn:feature_code":"PPL",
    "gn:name":"Whitehall",
    "gn:population":0,
    "gn:timezone":"America/Jamaica",
    "iso:country":"JM",
    "wof:name":"Whitehall",
    "wof:placetype":"locality"
},
  "geometry": {"coordinates":[-76.44931,17.95405],"type":"Point"}
}