{
  "type": "Feature",
  "properties": {
    "iso:country":"JM",
    "qs:gn_country":"JM",
    "qs:gn_fcode":"PPL",
    "qs:gn_pop":0,
    "qs:name":"Cinnamon Hill",
    "qs:name_adm0":"Jamaica",
    "qs:name_adm1":"Saint James",
    "qs:photos":328,
    "qs:photos_1k":66,
    "qs:photos_9k":1,
    "qs:photos_9r":5,
    "qs:photos_all":328,
    "qs:photos_sr":5,
    "qs:placetype":"Town",
    "qs:pop_sr":"0",
    "qs:woe_adm0":23424858,
    "wof:name":"Cinnamon Hill",
    "wof:placetype":"locality"
},
  "geometry": {"coordinates":[-77.81667,18.51667],"type":"Point"}
}