{
  "type": "Feature",
  "properties": {
    "gn:admin1_code":"04",
    "gn:admin2_code":"1256.0",
    "gn:asciiname":"Hatfield",
    "gn:country_code":"JM",
    "gn:dem":708,
    "gn:feature_class":"P",
    "gn:feature_code":"PPL",
    "gn:name":"Hatfield",
    "gn:population":0,
    "gn:timezone":"America/Jamaica",
    "iso:country":"JM",
    "name:ceb_x_preferred":[
        "Hatfield"
    ],
    "name:deu_x_preferred":[
        "Hatfield"
    ],
    "name:fin_x_preferred":[
        "Hatfield"
    ],
    "name:fra_x_preferred":[
        "Hatfield"
    ],
    "name:ita_x_preferred":[
        "Hatfield"
    ],
    "name:jpn_x_preferred":[
        "\u30cf\u30c3\u30c8\u30d5\u30a3\u30fc\u30eb\u30c9"
    ],
    "name:nld_x_preferred":[
        "Hatfield"
    ],
    "name:pol_x_preferred":[
        "Hatfield"
    ],
    "name:por_x_preferred":[
        "Hatfield"
    ],
    "name:rus_x_preferred":[
        "\u0425\u0430\u0442\u0444\u0438\u043b\u0434"
    ],
    "name:spa_x_preferred":[
        "Hatfield"
    ],
    "name:srp_x_preferred":[
        "\u0425\u0430\u0442\u0444\u0438\u043b\u0434"
    ],
    "name:swe_x_preferred":[
        "Hatfield"
    ],
    "name:ukr_x_preferred":[
        "\u0413\u0430\u0442\u0444\u0456\u043b\u0434"
    ],
    "name:vol_x_preferred":[
        "Hatfield"
    ],
    "wof:name":"Hatfield",
    "wof:placetype":"locality"
},
  "geometry": {"coordinates":[-77.53081999999998,18.02709],"type":"Point"}
}