{
  "type": "Feature",
  "properties": {
    "gn:admin1_code":"04",
    "gn:admin2_code":"1256.0",
    "gn:asciiname":"Hatfield",
    "gn:country_code":"JM",
    "gn:dem":708,
    "gn:feature_class":"P",
    "gn:feature_code":"PPL",
    "gn:name":"Hatfield",
    "gn:population":0,
    "gn:timezone":"America/Jamaica",
    "iso:country":"JM",
    "wof:name":"Hatfield",
    "wof:placetype":"locality"
},
  "geometry": {"coordinates":[-77.53081999999998,18.02709],"type":"Point"}
}