{
  "type": "Feature",
  "properties": {
    "gn:admin1_code":"07",
    "gn:admin2_code":"421.0",
    "gn:asciiname":"Boston Bay",
    "gn:country_code":"JM",
    "gn:dem":102,
    "gn:feature_class":"P",
    "gn:feature_code":"PPL",
    "gn:name":"Boston Bay",
    "gn:population":0,
    "gn:timezone":"America/Jamaica",
    "iso:country":"JM",
    "name:ceb_x_preferred":[
        "Boston Bay"
    ],
    "name:swe_x_preferred":[
        "Boston Bay"
    ],
    "wof:name":"Boston Bay",
    "wof:placetype":"locality"
},
  "geometry": {"coordinates":[-76.34515,18.12913],"type":"Point"}
}