{
  "type": "Feature",
  "properties": {
    "gn:admin1_code":"16.0",
    "gn:admin2_code":"1036",
    "gn:asciiname":"Paul Island",
    "gn:country_code":"JM",
    "gn:dem":13,
    "gn:feature_class":"P",
    "gn:feature_code":"PPL",
    "gn:name":"Paul Island",
    "gn:population":0,
    "gn:timezone":"America/Jamaica",
    "iso:country":"JM",
    "wof:name":"Paul Island",
    "wof:placetype":"locality"
},
  "geometry": {"coordinates":[-78.19164000000001,18.27413],"type":"Point"}
}