{
  "type": "Feature",
  "properties": {
    "gn:admin1_code":"13",
    "gn:admin2_code":"534.0",
    "gn:asciiname":"Iter Boreale",
    "gn:country_code":"JM",
    "gn:dem":67,
    "gn:feature_class":"P",
    "gn:feature_code":"PPL",
    "gn:name":"Iter Boreale",
    "gn:population":0,
    "gn:timezone":"America/Jamaica",
    "iso:country":"JM",
    "name:und_x_variant":[
        "Inter Boreale",
        "Iter Boreale"
    ],
    "wof:name":"Iter Boreale",
    "wof:placetype":"locality"
},
  "geometry": {"coordinates":[-76.74839,18.27028],"type":"Point"}
}