{
  "type": "Feature",
  "properties": {
    "gn:admin1_code":"09",
    "gn:admin2_code":"635.0",
    "gn:asciiname":"Friendship",
    "gn:country_code":"JM",
    "gn:dem":661,
    "gn:feature_class":"P",
    "gn:feature_code":"PPL",
    "gn:name":"Friendship",
    "gn:population":0,
    "gn:timezone":"America/Jamaica",
    "iso:country":"JM",
    "wof:name":"Friendship",
    "wof:placetype":"locality"
},
  "geometry": {"coordinates":[-77.15498000000002,18.27883],"type":"Point"}
}