{
  "type": "Feature",
  "properties": {
    "gn:admin1_code":"16.0",
    "gn:admin2_code":"1009",
    "gn:asciiname":"Prospect",
    "gn:cc2":"JM",
    "gn:country_code":"JM",
    "gn:dem":48,
    "gn:feature_class":"P",
    "gn:feature_code":"PPL",
    "gn:name":"Prospect",
    "gn:population":0,
    "gn:timezone":"America/Jamaica",
    "iso:country":"JM",
    "name:und_x_variant":[
        "Prospect Park Farm",
        "Prospect"
    ],
    "wof:name":"Prospect",
    "wof:placetype":"locality"
},
  "geometry": {"coordinates":[-78.09999999999999,18.31667],"type":"Point"}
}