{
  "type": "Feature",
  "properties": {
    "gn:admin1_code":"16.0",
    "gn:admin2_code":"1009",
    "gn:asciiname":"Prospect",
    "gn:cc2":"JM",
    "gn:country_code":"JM",
    "gn:dem":48,
    "gn:feature_class":"P",
    "gn:feature_code":"PPL",
    "gn:name":"Prospect",
    "gn:population":0,
    "gn:timezone":"America/Jamaica",
    "iso:country":"JM",
    "name:bar_x_preferred":[
        "Prospect"
    ],
    "name:cat_x_preferred":[
        "Prospect"
    ],
    "name:ceb_x_preferred":[
        "Prospect"
    ],
    "name:deu_x_preferred":[
        "Prospect"
    ],
    "name:fra_x_preferred":[
        "Prospection"
    ],
    "name:heb_x_preferred":[
        "\u05e4\u05e8\u05d5\u05e1\u05e4\u05e7\u05d8"
    ],
    "name:ita_x_preferred":[
        "Prospect"
    ],
    "name:lit_x_preferred":[
        "Prospektas"
    ],
    "name:mlg_x_preferred":[
        "Prospect"
    ],
    "name:nld_x_preferred":[
        "Prospect"
    ],
    "name:pol_x_preferred":[
        "Prospect"
    ],
    "name:por_x_preferred":[
        "Prospect"
    ],
    "name:rus_x_preferred":[
        "\u041f\u0440\u043e\u0441\u043f\u0435\u043a\u0442"
    ],
    "name:spa_x_preferred":[
        "Prospect"
    ],
    "name:srp_x_preferred":[
        "\u041f\u0440\u043e\u0441\u043f\u0435\u043a\u0442"
    ],
    "name:swe_x_preferred":[
        "Prospect"
    ],
    "name:ukr_x_preferred":[
        "\u041f\u0440\u043e\u0441\u043f\u0435\u043a\u0442"
    ],
    "name:und_x_variant":[
        "Prospect Park Farm"
    ],
    "name:vol_x_preferred":[
        "Prospect"
    ],
    "wof:name":"Prospect",
    "wof:placetype":"locality"
},
  "geometry": {"coordinates":[-78.09999999999999,18.31667],"type":"Point"}
}