{
  "type": "Feature",
  "properties": {
    "gn:admin1_code":"11.0",
    "gn:admin2_code":"1147",
    "gn:asciiname":"Punchbowl",
    "gn:country_code":"JM",
    "gn:dem":121,
    "gn:feature_class":"P",
    "gn:feature_code":"PPL",
    "gn:name":"Punchbowl",
    "gn:population":0,
    "gn:timezone":"America/Jamaica",
    "iso:country":"JM",
    "name:ceb_x_preferred":[
        "Punchbowl"
    ],
    "name:deu_x_preferred":[
        "Punchbowl"
    ],
    "name:fra_x_preferred":[
        "Punchbowl"
    ],
    "name:swe_x_preferred":[
        "Punchbowl"
    ],
    "wof:name":"Punchbowl",
    "wof:placetype":"locality"
},
  "geometry": {"coordinates":[-77.61667,17.96667],"type":"Point"}
}