{
  "type": "Feature",
  "properties": {
    "gn:admin1_code":"11",
    "gn:admin2_code":"1108.0",
    "gn:asciiname":"Accompong",
    "gn:country_code":"JM",
    "gn:dem":448,
    "gn:feature_class":"P",
    "gn:feature_code":"PPL",
    "gn:name":"Accompong",
    "gn:population":0,
    "gn:timezone":"America/Jamaica",
    "iso:country":"JM",
    "name:und_x_variant":[
        "Accompong Maroon Village",
        "Accompong Maroon Lands",
        "Accompong Town",
        "Accompong"
    ],
    "wof:name":"Accompong",
    "wof:placetype":"locality"
},
  "geometry": {"coordinates":[-77.75360000000001,18.22627],"type":"Point"}
}