{
  "type": "Feature",
  "properties": {
    "gn:admin1_code":"11",
    "gn:admin2_code":"1108.0",
    "gn:asciiname":"Accompong",
    "gn:country_code":"JM",
    "gn:dem":448,
    "gn:feature_class":"P",
    "gn:feature_code":"PPL",
    "gn:name":"Accompong",
    "gn:population":0,
    "gn:timezone":"America/Jamaica",
    "iso:country":"JM",
    "name:fas_x_preferred":[
        "\u0627\u06a9\u0648\u0645\u067e\u0627\u0646\u06af"
    ],
    "name:jam_x_preferred":[
        "Akompong"
    ],
    "name:jpn_x_preferred":[
        "\u30a2\u30b3\u30f3\u30dd\u30f3"
    ],
    "name:nno_x_preferred":[
        "Accompong"
    ],
    "name:und_x_variant":[
        "Accompong Maroon Village",
        "Accompong Maroon Lands",
        "Accompong Town"
    ],
    "wof:name":"Accompong",
    "wof:placetype":"locality"
},
  "geometry": {"coordinates":[-77.75360000000001,18.22627],"type":"Point"}
}