{
  "type": "Feature",
  "properties": {
    "gn:admin1_code":"01",
    "gn:admin2_code":"1310.0",
    "gn:asciiname":"Grasspiece",
    "gn:country_code":"JM",
    "gn:dem":631,
    "gn:feature_class":"P",
    "gn:feature_code":"PPL",
    "gn:name":"Grasspiece",
    "gn:population":0,
    "gn:timezone":"America/Jamaica",
    "iso:country":"JM",
    "wof:name":"Grasspiece",
    "wof:placetype":"locality"
},
  "geometry": {"coordinates":[-77.25444,18.1609],"type":"Point"}
}