{
  "type": "Feature",
  "properties": {
    "gn:admin1_code":"11",
    "gn:admin2_code":"1125.0",
    "gn:asciiname":"Frenchman",
    "gn:country_code":"JM",
    "gn:dem":4,
    "gn:feature_class":"P",
    "gn:feature_code":"PPL",
    "gn:name":"Frenchman",
    "gn:population":0,
    "gn:timezone":"America/Jamaica",
    "iso:country":"JM",
    "wof:name":"Frenchman",
    "wof:placetype":"locality"
},
  "geometry": {"coordinates":[-77.80705999999998,18.06549],"type":"Point"}
}