{
  "type": "Feature",
  "properties": {
    "gn:admin1_code":"10",
    "gn:admin2_code":"1402.0",
    "gn:asciiname":"Hayfield",
    "gn:country_code":"JM",
    "gn:dem":229,
    "gn:feature_class":"P",
    "gn:feature_code":"PPL",
    "gn:name":"Hayfield",
    "gn:population":0,
    "gn:timezone":"America/Jamaica",
    "iso:country":"JM",
    "wof:name":"Hayfield",
    "wof:placetype":"locality"
},
  "geometry": {"coordinates":[-77.07647,18.18793],"type":"Point"}
}