{
  "type": "Feature",
  "properties": {
    "gn:admin1_code":"9.0",
    "gn:admin2_code":"632",
    "gn:asciiname":"Montpelier",
    "gn:country_code":"JM",
    "gn:dem":421,
    "gn:feature_class":"P",
    "gn:feature_code":"PPL",
    "gn:name":"Montpelier",
    "gn:population":0,
    "gn:timezone":"America/Jamaica",
    "iso:country":"JM",
    "wof:name":"Montpelier",
    "wof:placetype":"locality"
},
  "geometry": {"coordinates":[-77.09999999999999,18.36667000000001],"type":"Point"}
}