{
  "type": "Feature",
  "properties": {
    "gn:admin1_code":"11.0",
    "gn:admin2_code":"1119",
    "gn:asciiname":"Woodstock",
    "gn:country_code":"JM",
    "gn:dem":443,
    "gn:feature_class":"P",
    "gn:feature_code":"PPL",
    "gn:name":"Woodstock",
    "gn:population":0,
    "gn:timezone":"America/Jamaica",
    "iso:country":"JM",
    "wof:name":"Woodstock",
    "wof:placetype":"locality"
},
  "geometry": {"coordinates":[-77.90000000000001,18.15],"type":"Point"}
}