{
  "type": "Feature",
  "properties": {
    "gn:admin1_code":"02",
    "gn:admin2_code":"911.0",
    "gn:asciiname":"Haddington",
    "gn:country_code":"JM",
    "gn:dem":249,
    "gn:feature_class":"P",
    "gn:feature_code":"PPL",
    "gn:name":"Haddington",
    "gn:population":0,
    "gn:timezone":"America/Jamaica",
    "iso:country":"JM",
    "name:cat_x_preferred":[
        "Haddington"
    ],
    "name:ceb_x_preferred":[
        "Haddington"
    ],
    "name:cym_x_preferred":[
        "Haddington"
    ],
    "name:deu_x_preferred":[
        "Haddington"
    ],
    "name:nld_x_preferred":[
        "Haddington"
    ],
    "name:sco_x_preferred":[
        "Haddington"
    ],
    "name:swe_x_preferred":[
        "Haddington"
    ],
    "wof:name":"Haddington",
    "wof:placetype":"locality"
},
  "geometry": {"coordinates":[-78.00434,18.42124],"type":"Point"}
}