{
  "type": "Feature",
  "properties": {
    "gn:admin1_code":"01",
    "gn:admin2_code":"1307.0",
    "gn:asciiname":"Corner Shop",
    "gn:country_code":"JM",
    "gn:dem":606,
    "gn:feature_class":"P",
    "gn:feature_code":"PPL",
    "gn:name":"Corner Shop",
    "gn:population":0,
    "gn:timezone":"America/Jamaica",
    "iso:country":"JM",
    "wof:name":"Corner Shop",
    "wof:placetype":"locality"
},
  "geometry": {"coordinates":[-77.3443,18.1876],"type":"Point"}
}