{
  "type": "Feature",
  "properties": {
    "gn:admin1_code":"10",
    "gn:admin2_code":"1411.0",
    "gn:asciiname":"Everton",
    "gn:country_code":"JM",
    "gn:dem":316,
    "gn:feature_class":"P",
    "gn:feature_code":"PPL",
    "gn:name":"Everton",
    "gn:population":0,
    "gn:timezone":"America/Jamaica",
    "iso:country":"JM",
    "name:cat_x_preferred":[
        "Everton"
    ],
    "name:ceb_x_preferred":[
        "Everton"
    ],
    "name:deu_x_preferred":[
        "Everton"
    ],
    "name:fas_x_preferred":[
        "\u0627\u0648\u0631\u062a\u0648\u0646"
    ],
    "name:fra_x_preferred":[
        "Everton"
    ],
    "name:ita_x_preferred":[
        "Everton"
    ],
    "name:jpn_x_preferred":[
        "\u30a8\u30d0\u30fc\u30c8\u30f3"
    ],
    "name:kor_x_preferred":[
        "\uc5d0\ubc84\ud134"
    ],
    "name:nld_x_preferred":[
        "Everton"
    ],
    "name:pol_x_preferred":[
        "Everton"
    ],
    "name:por_x_preferred":[
        "\u00c9verton"
    ],
    "name:rus_x_preferred":[
        "\u042d\u0432\u0435\u0440\u0442\u043e\u043d"
    ],
    "name:spa_x_preferred":[
        "Everton"
    ],
    "name:srp_x_preferred":[
        "\u0415\u0432\u0435\u0440\u0442\u043e\u043d"
    ],
    "name:swe_x_preferred":[
        "Everton"
    ],
    "name:tur_x_preferred":[
        "Everton"
    ],
    "name:ukr_x_preferred":[
        "\u0415\u0432\u0435\u0440\u0442\u043e\u043d"
    ],
    "name:vie_x_preferred":[
        "Everton"
    ],
    "wof:name":"Everton",
    "wof:placetype":"locality"
},
  "geometry": {"coordinates":[-76.86859,18.09642],"type":"Point"}
}