{
  "type": "Feature",
  "properties": {
    "gn:admin1_code":"10",
    "gn:admin2_code":"1411.0",
    "gn:asciiname":"Everton",
    "gn:country_code":"JM",
    "gn:dem":316,
    "gn:feature_class":"P",
    "gn:feature_code":"PPL",
    "gn:name":"Everton",
    "gn:population":0,
    "gn:timezone":"America/Jamaica",
    "iso:country":"JM",
    "wof:name":"Everton",
    "wof:placetype":"locality"
},
  "geometry": {"coordinates":[-76.86859,18.09642],"type":"Point"}
}