{
  "type": "Feature",
  "properties": {
    "gn:admin1_code":"9.0",
    "gn:admin2_code":"626",
    "gn:asciiname":"Knutsford",
    "gn:country_code":"JM",
    "gn:dem":559,
    "gn:feature_class":"P",
    "gn:feature_code":"PPL",
    "gn:name":"Knutsford",
    "gn:population":0,
    "gn:timezone":"America/Jamaica",
    "iso:country":"JM",
    "name:azb_x_preferred":[
        "\u0646\u0627\u062a\u0633\u0641\u0648\u0631\u062f"
    ],
    "name:ceb_x_preferred":[
        "Knutsford"
    ],
    "name:cym_x_preferred":[
        "Knutsford"
    ],
    "name:deu_x_preferred":[
        "Knutsford"
    ],
    "name:fas_x_preferred":[
        "\u0646\u0627\u062a\u0633\u0641\u0648\u0631\u062f"
    ],
    "name:fra_x_preferred":[
        "Knutsford"
    ],
    "name:gle_x_preferred":[
        "Knutsford"
    ],
    "name:ita_x_preferred":[
        "Knutsford"
    ],
    "name:nld_x_preferred":[
        "Knutsford"
    ],
    "name:nno_x_preferred":[
        "Knutsford"
    ],
    "name:pol_x_preferred":[
        "Knutsford"
    ],
    "name:ron_x_preferred":[
        "Knutsford"
    ],
    "name:rus_x_preferred":[
        "\u041d\u0430\u0442\u0441\u0444\u043e\u0440\u0434"
    ],
    "name:spa_x_preferred":[
        "Knutsford"
    ],
    "name:swe_x_preferred":[
        "Knutsford"
    ],
    "name:szl_x_preferred":[
        "Knutsford"
    ],
    "name:vol_x_preferred":[
        "Knutsford"
    ],
    "name:zho_x_preferred":[
        "\u7d0d\u8328\u798f\u5fb7"
    ],
    "wof:name":"Knutsford",
    "wof:placetype":"locality"
},
  "geometry": {"coordinates":[-77.36667,18.35],"type":"Point"}
}