{
  "type": "Feature",
  "properties": {
    "gn:admin1_code":"9.0",
    "gn:admin2_code":"626",
    "gn:asciiname":"Knutsford",
    "gn:country_code":"JM",
    "gn:dem":559,
    "gn:feature_class":"P",
    "gn:feature_code":"PPL",
    "gn:name":"Knutsford",
    "gn:population":0,
    "gn:timezone":"America/Jamaica",
    "iso:country":"JM",
    "wof:name":"Knutsford",
    "wof:placetype":"locality"
},
  "geometry": {"coordinates":[-77.36667,18.35],"type":"Point"}
}