{
  "type": "Feature",
  "properties": {
    "gn:admin1_code":"13.0",
    "gn:admin2_code":"531",
    "gn:asciiname":"Lower Esher",
    "gn:country_code":"JM",
    "gn:dem":74,
    "gn:feature_class":"P",
    "gn:feature_code":"PPL",
    "gn:name":"Lower Esher",
    "gn:population":0,
    "gn:timezone":"America/Jamaica",
    "iso:country":"JM",
    "wof:name":"Lower Esher",
    "wof:placetype":"locality"
},
  "geometry": {"coordinates":[-76.86719000000002,18.2851],"type":"Point"}
}