{
  "type": "Feature",
  "properties": {
    "iso:country":"JM",
    "name:ara_x_preferred":[
        "\u0628\u0627\u062b(\u062c\u0627\u0645\u0627\u064a\u0643\u0627)"
    ],
    "name:ceb_x_preferred":[
        "Bath"
    ],
    "name:deu_x_preferred":[
        "Bath"
    ],
    "name:eng_x_preferred":[
        "Bath"
    ],
    "name:fas_x_preferred":[
        "\u0628\u062b\u060c \u062c\u0627\u0645\u0627\u0626\u06cc\u06a9\u0627"
    ],
    "name:fas_x_variant":[
        "\u0628\u062b"
    ],
    "name:jpn_x_preferred":[
        "\u30d0\u30fc\u30b9"
    ],
    "name:nld_x_preferred":[
        "Bath"
    ],
    "name:pol_x_preferred":[
        "Bath"
    ],
    "name:swe_x_preferred":[
        "Bath"
    ],
    "name:und_x_variant":[
        "The Bath"
    ],
    "qs:gn_country":"JM",
    "qs:gn_fcode":"PPL",
    "qs:gn_pop":2382,
    "qs:name":"Bath",
    "qs:name_adm0":"Jamaica",
    "qs:name_adm1":"Saint Thomas",
    "qs:photos":0,
    "qs:photos_1k":0,
    "qs:photos_9k":1,
    "qs:photos_9r":1,
    "qs:photos_all":7,
    "qs:photos_sr":0,
    "qs:placetype":"Town",
    "qs:pop_sr":"4",
    "qs:woe_adm0":23424858,
    "wd:wordcount":326,
    "wof:name":"Bath",
    "wof:placetype":"locality",
    "wof:population":2382
},
  "geometry": {"coordinates":[-76.34916,17.9482],"type":"Point"}
}