{
  "type": "Feature",
  "properties": {
    "gn:admin1_code":"11",
    "gn:admin2_code":"1119.0",
    "gn:asciiname":"Croyden",
    "gn:cc2":"JM",
    "gn:country_code":"JM",
    "gn:dem":523,
    "gn:feature_class":"P",
    "gn:feature_code":"PPL",
    "gn:name":"Croyden",
    "gn:population":0,
    "gn:timezone":"America/Jamaica",
    "iso:country":"JM",
    "name:und_x_variant":[
        "Croydon",
        "Croyden"
    ],
    "wof:name":"Croyden",
    "wof:placetype":"locality"
},
  "geometry": {"coordinates":[-77.90000000000001,18.13333],"type":"Point"}
}