{
  "type": "Feature",
  "properties": {
    "gn:admin1_code":"09",
    "gn:admin2_code":"608.0",
    "gn:asciiname":"Breezy Hill",
    "gn:country_code":"JM",
    "gn:dem":526,
    "gn:feature_class":"P",
    "gn:feature_code":"PPL",
    "gn:name":"Breezy Hill",
    "gn:population":0,
    "gn:timezone":"America/Jamaica",
    "iso:country":"JM",
    "wof:name":"Breezy Hill",
    "wof:placetype":"locality"
},
  "geometry": {"coordinates":[-77.14298000000002,18.37551],"type":"Point"}
}