{
  "type": "Feature",
  "properties": {
    "gn:admin1_code":"04",
    "gn:admin2_code":"1248.0",
    "gn:asciiname":"Green Pond",
    "gn:country_code":"JM",
    "gn:dem":453,
    "gn:feature_class":"P",
    "gn:feature_code":"PPL",
    "gn:name":"Green Pond",
    "gn:population":0,
    "gn:timezone":"America/Jamaica",
    "iso:country":"JM",
    "name:ceb_x_preferred":[
        "Green Pond"
    ],
    "name:deu_x_preferred":[
        "Green Pond"
    ],
    "wof:name":"Green Pond",
    "wof:placetype":"locality"
},
  "geometry": {"coordinates":[-77.4341,17.97994],"type":"Point"}
}