{
  "type": "Feature",
  "properties": {
    "gn:admin1_code":"8.0",
    "gn:admin2_code":"15121",
    "gn:asciiname":"Saint Peter's",
    "gn:country_code":"JM",
    "gn:dem":1012,
    "gn:feature_class":"P",
    "gn:feature_code":"PPL",
    "gn:name":"Saint Peter\u2019s",
    "gn:population":0,
    "gn:timezone":"America/Jamaica",
    "iso:country":"JM",
    "wof:name":"Saint Peter's",
    "wof:placetype":"locality"
},
  "geometry": {"coordinates":[-76.68462,18.06701],"type":"Point"}
}