{
  "type": "Feature",
  "properties": {
    "gn:admin1_code":"14.0",
    "gn:admin2_code":"305",
    "gn:asciiname":"New Monklands",
    "gn:country_code":"JM",
    "gn:dem":339,
    "gn:feature_class":"P",
    "gn:feature_code":"PPL",
    "gn:name":"New Monklands",
    "gn:population":0,
    "gn:timezone":"America/Jamaica",
    "iso:country":"JM",
    "name:und_x_variant":[
        "Monklands",
        "New Monklands"
    ],
    "wof:name":"New Monklands",
    "wof:placetype":"locality"
},
  "geometry": {"coordinates":[-76.55419000000001,17.97396],"type":"Point"}
}