{
  "type": "Feature",
  "properties": {
    "gn:admin1_code":"2.0",
    "gn:admin2_code":"906",
    "gn:asciiname":"Paradise",
    "gn:country_code":"JM",
    "gn:dem":21,
    "gn:feature_class":"P",
    "gn:feature_code":"PPL",
    "gn:name":"Paradise",
    "gn:population":0,
    "gn:timezone":"America/Jamaica",
    "iso:country":"JM",
    "wof:name":"Paradise",
    "wof:placetype":"locality"
},
  "geometry": {"coordinates":[-78.12873,18.45701],"type":"Point"}
}