{
  "type": "Feature",
  "properties": {
    "gn:admin1_code":"10",
    "gn:admin2_code":"1403.0",
    "gn:asciiname":"Fellowship Hall",
    "gn:country_code":"JM",
    "gn:dem":349,
    "gn:feature_class":"P",
    "gn:feature_code":"PPL",
    "gn:name":"Fellowship Hall",
    "gn:population":0,
    "gn:timezone":"America/Jamaica",
    "iso:country":"JM",
    "wof:name":"Fellowship Hall",
    "wof:placetype":"locality"
},
  "geometry": {"coordinates":[-77.06998,18.12188],"type":"Point"}
}