{
  "type": "Feature",
  "properties": {
    "gn:admin1_code":"10.0",
    "gn:admin2_code":"1429",
    "gn:asciiname":"Red Ground",
    "gn:country_code":"JM",
    "gn:dem":134,
    "gn:feature_class":"P",
    "gn:feature_code":"PPL",
    "gn:name":"Red Ground",
    "gn:population":0,
    "gn:timezone":"America/Jamaica",
    "iso:country":"JM",
    "name:und_x_variant":[
        "New Forest",
        "Red Ground"
    ],
    "wof:name":"Red Ground",
    "wof:placetype":"locality"
},
  "geometry": {"coordinates":[-77.12262,18.00079],"type":"Point"}
}