{
  "type": "Feature",
  "properties": {
    "gn:admin1_code":"11",
    "gn:admin2_code":"1140.0",
    "gn:asciiname":"Browns Valley",
    "gn:country_code":"JM",
    "gn:dem":13,
    "gn:feature_class":"P",
    "gn:feature_code":"PPL",
    "gn:name":"Browns Valley",
    "gn:population":0,
    "gn:timezone":"America/Jamaica",
    "iso:country":"JM",
    "name:fin_x_preferred":[
        "Browns Valley"
    ],
    "name:pol_x_preferred":[
        "Browns Valley"
    ],
    "name:rus_x_preferred":[
        "\u0411\u0440\u0430\u0443\u043d\u0441-\u0412\u0430\u043b\u043b\u0438"
    ],
    "wof:name":"Browns Valley",
    "wof:placetype":"locality"
},
  "geometry": {"coordinates":[-77.76666999999998,17.96667],"type":"Point"}
}