{
  "type": "Feature",
  "properties": {
    "gn:admin1_code":"13",
    "gn:admin2_code":"530.0",
    "gn:asciiname":"Belfield",
    "gn:country_code":"JM",
    "gn:dem":171,
    "gn:feature_class":"P",
    "gn:feature_code":"PPL",
    "gn:name":"Belfield",
    "gn:population":0,
    "gn:timezone":"America/Jamaica",
    "iso:country":"JM",
    "name:ceb_x_preferred":[
        "Belfield"
    ],
    "name:deu_x_preferred":[
        "Belfield"
    ],
    "name:pol_x_preferred":[
        "Belfield"
    ],
    "name:swe_x_preferred":[
        "Belfield"
    ],
    "name:und_x_variant":[
        "Bellfield"
    ],
    "wof:name":"Belfield",
    "wof:placetype":"locality"
},
  "geometry": {"coordinates":[-76.84666,18.26088],"type":"Point"}
}