{
  "type": "Feature",
  "properties": {
    "gn:admin1_code":"11",
    "gn:admin2_code":"1114.0",
    "gn:asciiname":"Jointwood",
    "gn:country_code":"JM",
    "gn:dem":416,
    "gn:feature_class":"P",
    "gn:feature_code":"PPL",
    "gn:name":"Jointwood",
    "gn:population":0,
    "gn:timezone":"America/Jamaica",
    "iso:country":"JM",
    "wof:name":"Jointwood",
    "wof:placetype":"locality"
},
  "geometry": {"coordinates":[-77.78655000000001,18.21094],"type":"Point"}
}