{
  "type": "Feature",
  "properties": {
    "gn:admin1_code":"11",
    "gn:admin2_code":"1114.0",
    "gn:asciiname":"Bartons",
    "gn:country_code":"JM",
    "gn:dem":14,
    "gn:feature_class":"P",
    "gn:feature_code":"PPL",
    "gn:name":"Bartons",
    "gn:population":0,
    "gn:timezone":"America/Jamaica",
    "iso:country":"JM",
    "name:und_x_variant":[
        "Barton",
        "Bartons"
    ],
    "wof:name":"Bartons",
    "wof:placetype":"locality"
},
  "geometry": {"coordinates":[-77.73136,18.13565],"type":"Point"}
}