{
  "type": "Feature",
  "properties": {
    "gn:admin1_code":"11",
    "gn:admin2_code":"1118.0",
    "gn:asciiname":"Happy Grove",
    "gn:country_code":"JM",
    "gn:dem":318,
    "gn:feature_class":"P",
    "gn:feature_code":"PPL",
    "gn:name":"Happy Grove",
    "gn:population":0,
    "gn:timezone":"America/Jamaica",
    "iso:country":"JM",
    "name:und_x_variant":[
        "Hazel Grove",
        "Happy Grove"
    ],
    "wof:name":"Happy Grove",
    "wof:placetype":"locality"
},
  "geometry": {"coordinates":[-77.88431,18.14164],"type":"Point"}
}