{
  "type": "Feature",
  "properties": {
    "gn:admin1_code":"16.0",
    "gn:admin2_code":"1035",
    "gn:asciiname":"Ricketts River",
    "gn:country_code":"JM",
    "gn:dem":15,
    "gn:feature_class":"P",
    "gn:feature_code":"PPL",
    "gn:name":"Ricketts River",
    "gn:population":0,
    "gn:timezone":"America/Jamaica",
    "iso:country":"JM",
    "wof:name":"Ricketts River",
    "wof:placetype":"locality"
},
  "geometry": {"coordinates":[-78.14938000000002,18.28687],"type":"Point"}
}