{
  "type": "Feature",
  "properties": {
    "gn:admin1_code":"10.0",
    "gn:admin2_code":"1437",
    "gn:asciiname":"Woodlands",
    "gn:cc2":"JM",
    "gn:country_code":"JM",
    "gn:dem":21,
    "gn:feature_class":"P",
    "gn:feature_code":"PPL",
    "gn:name":"Woodlands",
    "gn:population":0,
    "gn:timezone":"America/Jamaica",
    "iso:country":"JM",
    "name:bar_x_preferred":[
        "Woodlands"
    ],
    "name:ceb_x_preferred":[
        "Woodlands"
    ],
    "name:deu_x_preferred":[
        "Woodlands"
    ],
    "name:ita_x_preferred":[
        "Woodlands"
    ],
    "name:nld_x_preferred":[
        "Woodlands"
    ],
    "name:pol_x_preferred":[
        "Woodlands"
    ],
    "name:rus_x_preferred":[
        "\u0412\u0443\u0434\u043b\u0435\u043d\u0434\u0441"
    ],
    "name:srp_x_preferred":[
        "\u0412\u0443\u0434\u043b\u0430\u043d\u0434\u0441"
    ],
    "name:swe_x_preferred":[
        "Woodlands"
    ],
    "name:und_x_variant":[
        "Woodlands Pen",
        "Woodlands"
    ],
    "wof:name":"Woodlands",
    "wof:placetype":"locality"
},
  "geometry": {"coordinates":[-76.95,17.96667],"type":"Point"}
}