{
  "type": "Feature",
  "properties": {
    "gn:admin1_code":"16",
    "gn:admin2_code":"1035.0",
    "gn:asciiname":"Black Heath",
    "gn:country_code":"JM",
    "gn:dem":15,
    "gn:feature_class":"P",
    "gn:feature_code":"PPL",
    "gn:name":"Black Heath",
    "gn:population":0,
    "gn:timezone":"America/Jamaica",
    "iso:country":"JM",
    "wof:name":"Black Heath",
    "wof:placetype":"locality"
},
  "geometry": {"coordinates":[-78.13333,18.28333],"type":"Point"}
}