{
  "type": "Feature",
  "properties": {
    "gn:admin1_code":"16",
    "gn:admin2_code":"1030.0",
    "gn:asciiname":"Kepham",
    "gn:country_code":"JM",
    "gn:dem":361,
    "gn:feature_class":"P",
    "gn:feature_code":"PPL",
    "gn:name":"Kepham",
    "gn:population":0,
    "gn:timezone":"America/Jamaica",
    "iso:country":"JM",
    "wof:name":"Kepham",
    "wof:placetype":"locality"
},
  "geometry": {"coordinates":[-78.03333000000001,18.25],"type":"Point"}
}