{
  "type": "Feature",
  "properties": {
    "gn:admin1_code":"07",
    "gn:admin2_code":"414.0",
    "gn:asciiname":"Breastworks",
    "gn:country_code":"JM",
    "gn:dem":13,
    "gn:feature_class":"P",
    "gn:feature_code":"PPL",
    "gn:name":"Breastworks",
    "gn:population":0,
    "gn:timezone":"America/Jamaica",
    "iso:country":"JM",
    "wof:name":"Breastworks",
    "wof:placetype":"locality"
},
  "geometry": {"coordinates":[-76.44703,18.16448],"type":"Point"}
}