{
  "type": "Feature",
  "properties": {
    "gn:admin1_code":"11.0",
    "gn:admin2_code":"1158",
    "gn:asciiname":"Malvern Chase",
    "gn:country_code":"JM",
    "gn:dem":457,
    "gn:feature_class":"P",
    "gn:feature_code":"PPL",
    "gn:name":"Malvern Chase",
    "gn:population":0,
    "gn:timezone":"America/Jamaica",
    "iso:country":"JM",
    "wof:name":"Malvern Chase",
    "wof:placetype":"locality"
},
  "geometry": {"coordinates":[-77.68333,17.88332999999999],"type":"Point"}
}