{
  "type": "Feature",
  "properties": {
    "gn:admin1_code":"02",
    "gn:admin2_code":"922.0",
    "gn:asciiname":"Buxton",
    "gn:country_code":"JM",
    "gn:dem":252,
    "gn:feature_class":"P",
    "gn:feature_code":"PPL",
    "gn:name":"Buxton",
    "gn:population":0,
    "gn:timezone":"America/Jamaica",
    "iso:country":"JM",
    "name:azb_x_preferred":[
        "\u0628\u0648\u06a9\u0633\u062a\u0648\u0646"
    ],
    "name:bre_x_preferred":[
        "Buxton"
    ],
    "name:ceb_x_preferred":[
        "Buxton"
    ],
    "name:cym_x_preferred":[
        "Buxton"
    ],
    "name:dan_x_preferred":[
        "Buxton"
    ],
    "name:deu_x_preferred":[
        "Buxton"
    ],
    "name:fas_x_preferred":[
        "\u0628\u0648\u06a9\u0633\u062a\u0648\u0646"
    ],
    "name:fra_x_preferred":[
        "Buxton"
    ],
    "name:gle_x_preferred":[
        "Buxton"
    ],
    "name:ita_x_preferred":[
        "Buxton"
    ],
    "name:kor_x_preferred":[
        "\ubc85\uc2a4\ud134"
    ],
    "name:lat_x_preferred":[
        "Aquae Arnemetiae"
    ],
    "name:nld_x_preferred":[
        "Buxton"
    ],
    "name:nno_x_preferred":[
        "Buxton"
    ],
    "name:nor_x_preferred":[
        "Buxton"
    ],
    "name:pol_x_preferred":[
        "Buxton"
    ],
    "name:por_x_preferred":[
        "Buxton"
    ],
    "name:ron_x_preferred":[
        "Buxton"
    ],
    "name:spa_x_preferred":[
        "Buxton"
    ],
    "name:swe_x_preferred":[
        "Buxton"
    ],
    "name:und_x_variant":[
        "Boxton"
    ],
    "name:zho_x_preferred":[
        "\u5df4\u514b\u65af\u9813"
    ],
    "wof:name":"Buxton",
    "wof:placetype":"locality"
},
  "geometry": {"coordinates":[-78.10245,18.3735],"type":"Point"}
}