{
  "type": "Feature",
  "properties": {
    "gn:admin1_code":"02",
    "gn:admin2_code":"922.0",
    "gn:asciiname":"Buxton",
    "gn:country_code":"JM",
    "gn:dem":252,
    "gn:feature_class":"P",
    "gn:feature_code":"PPL",
    "gn:name":"Buxton",
    "gn:population":0,
    "gn:timezone":"America/Jamaica",
    "iso:country":"JM",
    "name:und_x_variant":[
        "Boxton",
        "Buxton"
    ],
    "wof:name":"Buxton",
    "wof:placetype":"locality"
},
  "geometry": {"coordinates":[-78.10245,18.3735],"type":"Point"}
}