{
  "type": "Feature",
  "properties": {
    "iso:country":"JM",
    "qs:gn_country":"JM",
    "qs:gn_fcode":"PPL",
    "qs:gn_pop":3860,
    "qs:name":"Coleyville",
    "qs:name_adm0":"Jamaica",
    "qs:name_adm1":"Manchester",
    "qs:photos":0,
    "qs:photos_1k":0,
    "qs:photos_9k":0,
    "qs:photos_9r":0,
    "qs:photos_all":0,
    "qs:photos_sr":0,
    "qs:placetype":"Town",
    "qs:pop_sr":"4",
    "qs:woe_adm0":23424858,
    "wd:wordcount":26,
    "wof:name":"Coleyville",
    "wof:placetype":"locality",
    "wof:population":3860
},
  "geometry": {"coordinates":[-77.50754000000001,18.20783],"type":"Point"}
}