{
  "type": "Feature",
  "properties": {
    "gn:admin1_code":"11.0",
    "gn:admin2_code":"1151",
    "gn:asciiname":"Rose Hall",
    "gn:country_code":"JM",
    "gn:dem":583,
    "gn:feature_class":"P",
    "gn:feature_code":"PPL",
    "gn:name":"Rose Hall",
    "gn:population":0,
    "gn:timezone":"America/Jamaica",
    "iso:country":"JM",
    "name:deu_x_preferred":[
        "Rose Hall"
    ],
    "name:und_x_variant":[
        "Rose Hill",
        "Rose Hall"
    ],
    "wof:name":"Rose Hall",
    "wof:placetype":"locality"
},
  "geometry": {"coordinates":[-77.64695,17.92558],"type":"Point"}
}