{
  "type": "Feature",
  "properties": {
    "gn:admin1_code":"07",
    "gn:admin2_code":"442.0",
    "gn:asciiname":"Balcarres",
    "gn:country_code":"JM",
    "gn:dem":240,
    "gn:feature_class":"P",
    "gn:feature_code":"PPL",
    "gn:name":"Balcarres",
    "gn:population":0,
    "gn:timezone":"America/Jamaica",
    "iso:country":"JM",
    "name:und_x_variant":[
        "Belcarres",
        "Batcarres",
        "Balcarres"
    ],
    "wof:name":"Balcarres",
    "wof:placetype":"locality"
},
  "geometry": {"coordinates":[-76.69981999999997,18.16494],"type":"Point"}
}