{
  "type": "Feature",
  "properties": {
    "gn:admin1_code":"12",
    "gn:admin2_code":"847.0",
    "gn:asciiname":"Comfort",
    "gn:country_code":"JM",
    "gn:dem":286,
    "gn:feature_class":"P",
    "gn:feature_code":"PPL",
    "gn:name":"Comfort",
    "gn:population":0,
    "gn:timezone":"America/Jamaica",
    "iso:country":"JM",
    "wof:name":"Comfort",
    "wof:placetype":"locality"
},
  "geometry": {"coordinates":[-77.9179,18.41412],"type":"Point"}
}