{
  "type": "Feature",
  "properties": {
    "gn:admin1_code":"12",
    "gn:admin2_code":"847.0",
    "gn:asciiname":"Comfort",
    "gn:country_code":"JM",
    "gn:dem":286,
    "gn:feature_class":"P",
    "gn:feature_code":"PPL",
    "gn:name":"Comfort",
    "gn:population":0,
    "gn:timezone":"America/Jamaica",
    "iso:country":"JM",
    "name:ara_x_preferred":[
        "\u0631\u0627\u062d\u0629"
    ],
    "name:cat_x_preferred":[
        "Confort"
    ],
    "name:ces_x_preferred":[
        "Komfort"
    ],
    "name:deu_x_preferred":[
        "Komfort"
    ],
    "name:fas_x_preferred":[
        "\u0622\u0633\u0627\u06cc\u0634"
    ],
    "name:fra_x_preferred":[
        "Confort"
    ],
    "name:ita_x_preferred":[
        "Comfort"
    ],
    "name:kan_x_preferred":[
        "\u0ca8\u0cc6\u0cae\u0ccd\u0cae\u0ca6\u0cbf"
    ],
    "name:nld_x_preferred":[
        "Comfort"
    ],
    "name:sme_x_preferred":[
        "Confort"
    ],
    "name:spa_x_preferred":[
        "Confort"
    ],
    "name:swe_x_preferred":[
        "Komfort"
    ],
    "wof:name":"Comfort",
    "wof:placetype":"locality"
},
  "geometry": {"coordinates":[-77.9179,18.41412],"type":"Point"}
}