{
  "type": "Feature",
  "properties": {
    "gn:admin1_code":"11",
    "gn:admin2_code":"1124.0",
    "gn:asciiname":"Barnes Green",
    "gn:country_code":"JM",
    "gn:dem":12,
    "gn:feature_class":"P",
    "gn:feature_code":"PPL",
    "gn:name":"Barnes Green",
    "gn:population":0,
    "gn:timezone":"America/Jamaica",
    "iso:country":"JM",
    "wof:name":"Barnes Green",
    "wof:placetype":"locality"
},
  "geometry": {"coordinates":[-77.86667,18.05],"type":"Point"}
}