{
  "type": "Feature",
  "properties": {
    "gn:admin1_code":"08",
    "gn:admin2_code":"15114.0",
    "gn:asciiname":"Golden Spring",
    "gn:country_code":"JM",
    "gn:dem":372,
    "gn:feature_class":"P",
    "gn:feature_code":"PPL",
    "gn:name":"Golden Spring",
    "gn:population":0,
    "gn:timezone":"America/Jamaica",
    "iso:country":"JM",
    "wof:name":"Golden Spring",
    "wof:placetype":"locality"
},
  "geometry": {"coordinates":[-76.80533,18.0894],"type":"Point"}
}