{
  "type": "Feature",
  "properties": {
    "gn:admin1_code":"01",
    "gn:admin2_code":"1380.0",
    "gn:asciiname":"Chesterfield",
    "gn:country_code":"JM",
    "gn:dem":12,
    "gn:feature_class":"P",
    "gn:feature_code":"PPL",
    "gn:name":"Chesterfield",
    "gn:population":0,
    "gn:timezone":"America/Jamaica",
    "iso:country":"JM",
    "wof:name":"Chesterfield",
    "wof:placetype":"locality"
},
  "geometry": {"coordinates":[-77.24949000000002,17.80363999999999],"type":"Point"}
}