{
  "type": "Feature",
  "properties": {
    "gn:admin1_code":"2.0",
    "gn:admin2_code":"907",
    "gn:asciiname":"Maggotty",
    "gn:cc2":"JM",
    "gn:country_code":"JM",
    "gn:dem":211,
    "gn:feature_class":"P",
    "gn:feature_code":"PPL",
    "gn:name":"Maggotty",
    "gn:population":0,
    "gn:timezone":"America/Jamaica",
    "iso:country":"JM",
    "name:und_x_variant":[
        "Magotty",
        "Maggotty"
    ],
    "wof:name":"Maggotty",
    "wof:placetype":"locality"
},
  "geometry": {"coordinates":[-78.11667,18.41667],"type":"Point"}
}