{
  "type": "Feature",
  "properties": {
    "gn:admin1_code":"16.0",
    "gn:admin2_code":"1043",
    "gn:asciiname":"Negril Spots",
    "gn:country_code":"JM",
    "gn:dem":45,
    "gn:feature_class":"P",
    "gn:feature_code":"PPL",
    "gn:name":"Negril Spots",
    "gn:population":0,
    "gn:timezone":"America/Jamaica",
    "iso:country":"JM",
    "wof:name":"Negril Spots",
    "wof:placetype":"locality"
},
  "geometry": {"coordinates":[-78.28333000000001,18.25],"type":"Point"}
}