{
  "type": "Feature",
  "properties": {
    "gn:admin1_code":"10",
    "gn:admin2_code":"1413.0",
    "gn:asciiname":"Berwick",
    "gn:country_code":"JM",
    "gn:dem":120,
    "gn:feature_class":"P",
    "gn:feature_code":"PPL",
    "gn:name":"Berwick",
    "gn:population":0,
    "gn:timezone":"America/Jamaica",
    "iso:country":"JM",
    "wof:name":"Berwick",
    "wof:placetype":"locality"
},
  "geometry": {"coordinates":[-76.98993,18.1401],"type":"Point"}
}