{
  "type": "Feature",
  "properties": {
    "gn:admin1_code":"10",
    "gn:admin2_code":"1413.0",
    "gn:asciiname":"Berwick",
    "gn:country_code":"JM",
    "gn:dem":120,
    "gn:feature_class":"P",
    "gn:feature_code":"PPL",
    "gn:name":"Berwick",
    "gn:population":0,
    "gn:timezone":"America/Jamaica",
    "iso:country":"JM",
    "name:cat_x_preferred":[
        "Berwick"
    ],
    "name:ceb_x_preferred":[
        "Berwick"
    ],
    "name:deu_x_preferred":[
        "Berwick"
    ],
    "name:fin_x_preferred":[
        "Berwick"
    ],
    "name:fra_x_preferred":[
        "Berwick"
    ],
    "name:fry_x_preferred":[
        "Berwick"
    ],
    "name:gla_x_preferred":[
        "Bearaig"
    ],
    "name:ita_x_preferred":[
        "Berwick"
    ],
    "name:jpn_x_preferred":[
        "\u30d9\u30ea\u30c3\u30af"
    ],
    "name:mlg_x_preferred":[
        "Berwick"
    ],
    "name:nld_x_preferred":[
        "Berwick"
    ],
    "name:pol_x_preferred":[
        "Berwick"
    ],
    "name:por_x_preferred":[
        "Berwick"
    ],
    "name:sco_x_preferred":[
        "Berwick"
    ],
    "name:srp_x_preferred":[
        "\u0412\u0435\u0440\u0432\u0438\u043a"
    ],
    "name:swe_x_preferred":[
        "Berwick"
    ],
    "name:tha_x_preferred":[
        "\u0e40\u0e1a\u0e23\u0e34\u0e01"
    ],
    "name:ukr_x_preferred":[
        "\u0411\u0435\u0440\u0432\u0456\u043a"
    ],
    "name:vol_x_preferred":[
        "Berwick"
    ],
    "wof:name":"Berwick",
    "wof:placetype":"locality"
},
  "geometry": {"coordinates":[-76.98993,18.1401],"type":"Point"}
}