{
  "type": "Feature",
  "properties": {
    "gn:admin1_code":"16.0",
    "gn:admin2_code":"1080",
    "gn:asciiname":"Vinegar Hill",
    "gn:country_code":"JM",
    "gn:dem":401,
    "gn:feature_class":"P",
    "gn:feature_code":"PPL",
    "gn:name":"Vinegar Hill",
    "gn:population":0,
    "gn:timezone":"America/Jamaica",
    "iso:country":"JM",
    "name:ceb_x_preferred":[
        "Vinegar Hill"
    ],
    "name:deu_x_preferred":[
        "Vinegar Hill"
    ],
    "name:swe_x_preferred":[
        "Vinegar Hill"
    ],
    "wof:name":"Vinegar Hill",
    "wof:placetype":"locality"
},
  "geometry": {"coordinates":[-77.96666999999999,18.15],"type":"Point"}
}