{
  "type": "Feature",
  "properties": {
    "gn:admin1_code":"01",
    "gn:admin2_code":"1364.0",
    "gn:asciiname":"Chateau",
    "gn:country_code":"JM",
    "gn:dem":72,
    "gn:feature_class":"P",
    "gn:feature_code":"PPL",
    "gn:name":"Chateau",
    "gn:population":0,
    "gn:timezone":"America/Jamaica",
    "iso:country":"JM",
    "wof:name":"Chateau",
    "wof:placetype":"locality"
},
  "geometry": {"coordinates":[-77.21666999999999,17.96667],"type":"Point"}
}