{
  "type": "Feature",
  "properties": {
    "gn:admin1_code":"1.0",
    "gn:admin2_code":"1337",
    "gn:asciiname":"Stewarton",
    "gn:country_code":"JM",
    "gn:dem":501,
    "gn:feature_class":"P",
    "gn:feature_code":"PPL",
    "gn:name":"Stewarton",
    "gn:population":0,
    "gn:timezone":"America/Jamaica",
    "iso:country":"JM",
    "wof:name":"Stewarton",
    "wof:placetype":"locality"
},
  "geometry": {"coordinates":[-77.35590999999999,18.02661],"type":"Point"}
}