{
  "type": "Feature",
  "properties": {
    "gn:admin1_code":"1.0",
    "gn:admin2_code":"1337",
    "gn:asciiname":"Stewarton",
    "gn:country_code":"JM",
    "gn:dem":501,
    "gn:feature_class":"P",
    "gn:feature_code":"PPL",
    "gn:name":"Stewarton",
    "gn:population":0,
    "gn:timezone":"America/Jamaica",
    "iso:country":"JM",
    "name:azb_x_preferred":[
        "\u0627\u0633\u062a\u0648\u0627\u0631\u062a\u0648\u0646"
    ],
    "name:ceb_x_preferred":[
        "Stewarton"
    ],
    "name:cym_x_preferred":[
        "Stewarton"
    ],
    "name:deu_x_preferred":[
        "Stewarton"
    ],
    "name:eus_x_preferred":[
        "Stewarton"
    ],
    "name:fas_x_preferred":[
        "\u0627\u0633\u062a\u0648\u0627\u0631\u062a\u0648\u0646"
    ],
    "name:ita_x_preferred":[
        "Stewarton"
    ],
    "name:pol_x_preferred":[
        "Stewarton"
    ],
    "name:sco_x_preferred":[
        "Stewartoun"
    ],
    "name:spa_x_preferred":[
        "Stewarton"
    ],
    "name:swe_x_preferred":[
        "Stewarton"
    ],
    "wof:name":"Stewarton",
    "wof:placetype":"locality"
},
  "geometry": {"coordinates":[-77.35590999999999,18.02661],"type":"Point"}
}