{
  "type": "Feature",
  "properties": {
    "gn:admin1_code":"11.0",
    "gn:admin2_code":"1154",
    "gn:asciiname":"Newell",
    "gn:country_code":"JM",
    "gn:dem":40,
    "gn:feature_class":"P",
    "gn:feature_code":"PPL",
    "gn:name":"Newell",
    "gn:population":0,
    "gn:timezone":"America/Jamaica",
    "iso:country":"JM",
    "name:und_x_variant":[
        "Newell Pen",
        "Newell"
    ],
    "wof:name":"Newell",
    "wof:placetype":"locality"
},
  "geometry": {"coordinates":[-77.73838000000001,17.92122],"type":"Point"}
}