{
  "type": "Feature",
  "properties": {
    "gn:admin1_code":"11.0",
    "gn:admin2_code":"1154",
    "gn:asciiname":"Newell",
    "gn:country_code":"JM",
    "gn:dem":40,
    "gn:feature_class":"P",
    "gn:feature_code":"PPL",
    "gn:name":"Newell",
    "gn:population":0,
    "gn:timezone":"America/Jamaica",
    "iso:country":"JM",
    "name:cat_x_preferred":[
        "Newell"
    ],
    "name:ceb_x_preferred":[
        "Newell"
    ],
    "name:ces_x_preferred":[
        "Newell"
    ],
    "name:deu_x_preferred":[
        "Newell"
    ],
    "name:fra_x_preferred":[
        "Newell"
    ],
    "name:ita_x_preferred":[
        "Newell"
    ],
    "name:lav_x_preferred":[
        "\u0145\u016bels"
    ],
    "name:nds_x_preferred":[
        "Newell"
    ],
    "name:nld_x_preferred":[
        "Newell"
    ],
    "name:pol_x_preferred":[
        "Newell"
    ],
    "name:por_x_preferred":[
        "Newell"
    ],
    "name:rus_x_preferred":[
        "\u041d\u044c\u044e\u044d\u043b\u043b"
    ],
    "name:srp_x_preferred":[
        "\u040a\u0443\u0432\u0435\u043b"
    ],
    "name:ukr_x_preferred":[
        "\u041d\u044c\u044e\u0435\u043b"
    ],
    "name:und_x_variant":[
        "Newell Pen",
        "Newell"
    ],
    "name:vol_x_preferred":[
        "Newell"
    ],
    "wof:name":"Newell",
    "wof:placetype":"locality"
},
  "geometry": {"coordinates":[-77.73838000000001,17.92122],"type":"Point"}
}