{
  "type": "Feature",
  "properties": {
    "gn:admin1_code":"11",
    "gn:admin2_code":"1124.0",
    "gn:asciiname":"Ashton",
    "gn:country_code":"JM",
    "gn:dem":12,
    "gn:feature_class":"P",
    "gn:feature_code":"PPL",
    "gn:name":"Ashton",
    "gn:population":0,
    "gn:timezone":"America/Jamaica",
    "iso:country":"JM",
    "name:ceb_x_preferred":[
        "Ashton"
    ],
    "name:deu_x_preferred":[
        "Ashton"
    ],
    "name:est_x_preferred":[
        "Ashton"
    ],
    "name:fas_x_preferred":[
        "\u0627\u0634\u062a\u0648\u0646"
    ],
    "name:fra_x_preferred":[
        "Ashton"
    ],
    "name:ita_x_preferred":[
        "Ashton"
    ],
    "name:jpn_x_preferred":[
        "\u30a2\u30b7\u30e5\u30c8\u30f3"
    ],
    "name:nds_x_preferred":[
        "Ashton"
    ],
    "name:nld_x_preferred":[
        "Ashton"
    ],
    "name:pol_x_preferred":[
        "Ashton"
    ],
    "name:por_x_preferred":[
        "Ashton"
    ],
    "name:rus_x_preferred":[
        "\u042d\u0448\u0442\u043e\u043d"
    ],
    "name:srp_x_preferred":[
        "\u0415\u0448\u0442\u043e\u043d"
    ],
    "name:swe_x_preferred":[
        "Ashton"
    ],
    "name:ukr_x_preferred":[
        "\u0415\u0448\u0442\u043e\u043d"
    ],
    "name:vol_x_preferred":[
        "Ashton"
    ],
    "wof:name":"Ashton",
    "wof:placetype":"locality"
},
  "geometry": {"coordinates":[-77.86667,18.05],"type":"Point"}
}