{
  "type": "Feature",
  "properties": {
    "gn:admin1_code":"13.0",
    "gn:admin2_code":"525",
    "gn:asciiname":"The Cottage",
    "gn:country_code":"JM",
    "gn:dem":239,
    "gn:feature_class":"P",
    "gn:feature_code":"PPL",
    "gn:name":"The Cottage",
    "gn:population":0,
    "gn:timezone":"America/Jamaica",
    "iso:country":"JM",
    "wof:name":"The Cottage",
    "wof:placetype":"locality"
},
  "geometry": {"coordinates":[-76.88868000000002,18.26358],"type":"Point"}
}