{
  "type": "Feature",
  "properties": {
    "gn:admin1_code":"10.0",
    "gn:admin2_code":"1423",
    "gn:asciiname":"Watermount",
    "gn:country_code":"JM",
    "gn:dem":383,
    "gn:feature_class":"P",
    "gn:feature_code":"PPL",
    "gn:name":"Watermount",
    "gn:population":0,
    "gn:timezone":"America/Jamaica",
    "iso:country":"JM",
    "wof:name":"Watermount",
    "wof:placetype":"locality"
},
  "geometry": {"coordinates":[-77.09999999999999,18.06667],"type":"Point"}
}