{
  "type": "Feature",
  "properties": {
    "gn:admin1_code":"14.0",
    "gn:admin2_code":"325",
    "gn:asciiname":"Panton Town",
    "gn:country_code":"JM",
    "gn:dem":154,
    "gn:feature_class":"P",
    "gn:feature_code":"PPL",
    "gn:name":"Panton Town",
    "gn:population":0,
    "gn:timezone":"America/Jamaica",
    "iso:country":"JM",
    "wof:name":"Panton Town",
    "wof:placetype":"locality"
},
  "geometry": {"coordinates":[-76.34999999999999,17.91667],"type":"Point"}
}