{
  "type": "Feature",
  "properties": {
    "gn:admin1_code":"10.0",
    "gn:admin2_code":"1443",
    "gn:asciiname":"Port Henderson",
    "gn:country_code":"JM",
    "gn:dem":5,
    "gn:feature_class":"P",
    "gn:feature_code":"PPL",
    "gn:name":"Port Henderson",
    "gn:population":0,
    "gn:timezone":"America/Jamaica",
    "iso:country":"JM",
    "name:eus_x_preferred":[
        "Port Henderson"
    ],
    "name:gle_x_preferred":[
        "Portaigil"
    ],
    "name:nld_x_preferred":[
        "Port Henderson"
    ],
    "name:und_x_variant":[
        "Fort Henderson",
        "Port Henderson"
    ],
    "wof:name":"Port Henderson",
    "wof:placetype":"locality"
},
  "geometry": {"coordinates":[-76.87385999999999,17.95215],"type":"Point"}
}