{
  "type": "Feature",
  "properties": {
    "gn:admin1_code":"04",
    "gn:admin2_code":"1273.0",
    "gn:asciiname":"Asia",
    "gn:country_code":"JM",
    "gn:dem":503,
    "gn:feature_class":"P",
    "gn:feature_code":"PPL",
    "gn:name":"Asia",
    "gn:population":0,
    "gn:timezone":"America/Jamaica",
    "iso:country":"JM",
    "wof:name":"Asia",
    "wof:placetype":"locality"
},
  "geometry": {"coordinates":[-77.43165999999999,17.91788],"type":"Point"}
}