{
  "type": "Feature",
  "properties": {
    "gn:admin1_code":"10",
    "gn:admin2_code":"1402.0",
    "gn:asciiname":"Falkland",
    "gn:cc2":"JM",
    "gn:country_code":"JM",
    "gn:dem":166,
    "gn:feature_class":"P",
    "gn:feature_code":"PPL",
    "gn:name":"Falkland",
    "gn:population":0,
    "gn:timezone":"America/Jamaica",
    "iso:country":"JM",
    "name:cat_x_preferred":[
        "Falkland"
    ],
    "name:deu_x_preferred":[
        "Falkland"
    ],
    "name:fas_x_preferred":[
        "\u0641\u0627\u0644\u06a9\u0644\u0646\u062f"
    ],
    "name:fin_x_preferred":[
        "Falkland"
    ],
    "name:fra_x_preferred":[
        "Falkland"
    ],
    "name:ita_x_preferred":[
        "Falkland"
    ],
    "name:jpn_x_preferred":[
        "\u30d5\u30a9\u30fc\u30af\u30e9\u30f3\u30c9"
    ],
    "name:nld_x_preferred":[
        "Falkland"
    ],
    "name:pol_x_preferred":[
        "Falkland"
    ],
    "name:sco_x_preferred":[
        "Falkland"
    ],
    "name:und_x_variant":[
        "Nutshell"
    ],
    "wof:name":"Falkland",
    "wof:placetype":"locality"
},
  "geometry": {"coordinates":[-77.06667,18.16667],"type":"Point"}
}