{
  "type": "Feature",
  "properties": {
    "gn:admin1_code":"01",
    "gn:asciiname":"Alva",
    "gn:country_code":"JM",
    "gn:dem":667,
    "gn:feature_class":"P",
    "gn:feature_code":"PPL",
    "gn:name":"Alva",
    "gn:population":0,
    "gn:timezone":"America/Jamaica",
    "iso:country":"JM",
    "name:bul_x_preferred":[
        "\u0410\u043b\u0432\u0430"
    ],
    "name:cat_x_preferred":[
        "Alva"
    ],
    "name:ceb_x_preferred":[
        "Alva"
    ],
    "name:cym_x_preferred":[
        "Alva"
    ],
    "name:deu_x_preferred":[
        "Alva"
    ],
    "name:fra_x_preferred":[
        "Alva"
    ],
    "name:ita_x_preferred":[
        "Alva"
    ],
    "name:jpn_x_preferred":[
        "\u30a2\u30eb\u30f4\u30a1"
    ],
    "name:nld_x_preferred":[
        "Alva"
    ],
    "name:pol_x_preferred":[
        "Alva"
    ],
    "name:por_x_preferred":[
        "Alva"
    ],
    "name:rus_x_preferred":[
        "\u0410\u043b\u0432\u0430"
    ],
    "name:srp_x_preferred":[
        "\u0410\u043b\u0432\u0430"
    ],
    "name:swe_x_preferred":[
        "Alva"
    ],
    "name:ukr_x_preferred":[
        "\u0410\u043b\u0432\u0430"
    ],
    "name:vol_x_preferred":[
        "Alva"
    ],
    "wof:name":"Alva",
    "wof:placetype":"locality"
},
  "geometry": {"coordinates":[-77.32884,18.29866],"type":"Point"}
}