{
  "type": "Feature",
  "properties": {
    "gn:admin1_code":"01",
    "gn:asciiname":"Alva",
    "gn:country_code":"JM",
    "gn:dem":667,
    "gn:feature_class":"P",
    "gn:feature_code":"PPL",
    "gn:name":"Alva",
    "gn:population":0,
    "gn:timezone":"America/Jamaica",
    "iso:country":"JM",
    "wof:name":"Alva",
    "wof:placetype":"locality"
},
  "geometry": {"coordinates":[-77.32884,18.29866],"type":"Point"}
}