{
  "type": "Feature",
  "properties": {
    "gn:admin1_code":"04",
    "gn:admin2_code":"1245.0",
    "gn:asciiname":"Hope",
    "gn:country_code":"JM",
    "gn:dem":498,
    "gn:feature_class":"P",
    "gn:feature_code":"PPL",
    "gn:name":"Hope",
    "gn:population":0,
    "gn:timezone":"America/Jamaica",
    "iso:country":"JM",
    "wof:name":"Hope",
    "wof:placetype":"locality"
},
  "geometry": {"coordinates":[-77.45,18.05],"type":"Point"}
}