{
  "type": "Feature",
  "properties": {
    "gn:admin1_code":"07",
    "gn:admin2_code":"435.0",
    "gn:asciiname":"Bloomfield",
    "gn:country_code":"JM",
    "gn:dem":110,
    "gn:feature_class":"P",
    "gn:feature_code":"PPL",
    "gn:name":"Bloomfield",
    "gn:population":0,
    "gn:timezone":"America/Jamaica",
    "iso:country":"JM",
    "name:cat_x_preferred":[
        "Bloomfield"
    ],
    "name:ceb_x_preferred":[
        "Bloomfield"
    ],
    "name:ces_x_preferred":[
        "Bloomfield"
    ],
    "name:deu_x_preferred":[
        "Bloomfield"
    ],
    "name:epo_x_preferred":[
        "Bloomfield"
    ],
    "name:fas_x_preferred":[
        "\u0628\u0644\u0648\u0645\u0641\u06cc\u0644\u062f"
    ],
    "name:fra_x_preferred":[
        "Bloomfield"
    ],
    "name:heb_x_preferred":[
        "\u05d1\u05dc\u05d5\u05de\u05e4\u05d9\u05dc\u05d3"
    ],
    "name:hun_x_preferred":[
        "Bloomfield"
    ],
    "name:ido_x_preferred":[
        "Bloomfield"
    ],
    "name:ita_x_preferred":[
        "Bloomfield"
    ],
    "name:jpn_x_preferred":[
        "\u30d6\u30eb\u30fc\u30e0\u30d5\u30a3\u30fc\u30eb\u30c9"
    ],
    "name:kor_x_preferred":[
        "\ube14\ub8f8\ud544\ub4dc"
    ],
    "name:nds_x_preferred":[
        "Bloomfield"
    ],
    "name:nld_x_preferred":[
        "Bloomfield"
    ],
    "name:pol_x_preferred":[
        "Bloomfield"
    ],
    "name:por_x_preferred":[
        "Bloomfield"
    ],
    "name:rus_x_preferred":[
        "\u0411\u043b\u0443\u043c\u0444\u0438\u043b\u0434"
    ],
    "name:spa_x_preferred":[
        "Bloomfield"
    ],
    "name:srp_x_preferred":[
        "\u0411\u043b\u0443\u043c\u0444\u0438\u043b\u0434"
    ],
    "name:swe_x_preferred":[
        "Bloomfield"
    ],
    "name:ukr_x_preferred":[
        "\u0411\u043b\u0443\u043c\u0444\u0456\u043b\u0434"
    ],
    "name:urd_x_preferred":[
        "\u0628\u0644\u0648\u0645 \u0641\u06cc\u0644\u0688"
    ],
    "name:vol_x_preferred":[
        "Bloomfield"
    ],
    "wof:name":"Bloomfield",
    "wof:placetype":"locality"
},
  "geometry": {"coordinates":[-76.58793,18.15729],"type":"Point"}
}