{
  "type": "Feature",
  "properties": {
    "gn:admin1_code":"07",
    "gn:admin2_code":"414.0",
    "gn:asciiname":"Fellowship",
    "gn:country_code":"JM",
    "gn:dem":78,
    "gn:feature_class":"P",
    "gn:feature_code":"PPL",
    "gn:name":"Fellowship",
    "gn:population":0,
    "gn:timezone":"America/Jamaica",
    "iso:country":"JM",
    "name:und_x_variant":[
        "Fellowship School",
        "Fellowship"
    ],
    "wof:name":"Fellowship",
    "wof:placetype":"locality"
},
  "geometry": {"coordinates":[-76.44994,18.14289],"type":"Point"}
}