{
  "type": "Feature",
  "properties": {
    "gn:admin1_code":"2.0",
    "gn:admin2_code":"912",
    "gn:asciiname":"Lethe",
    "gn:country_code":"JM",
    "gn:dem":114,
    "gn:feature_class":"P",
    "gn:feature_code":"PPL",
    "gn:name":"Lethe",
    "gn:population":0,
    "gn:timezone":"America/Jamaica",
    "iso:country":"JM",
    "wof:name":"Lethe",
    "wof:placetype":"locality"
},
  "geometry": {"coordinates":[-77.96719,18.39327],"type":"Point"}
}