{
  "type": "Feature",
  "properties": {
    "gn:admin1_code":"4.0",
    "gn:admin2_code":"1273",
    "gn:asciiname":"Pratville",
    "gn:country_code":"JM",
    "gn:dem":525,
    "gn:feature_class":"P",
    "gn:feature_code":"PPL",
    "gn:name":"Pratville",
    "gn:population":0,
    "gn:timezone":"America/Jamaica",
    "iso:country":"JM",
    "wof:name":"Pratville",
    "wof:placetype":"locality"
},
  "geometry": {"coordinates":[-77.41471,17.91509],"type":"Point"}
}