{
  "type": "Feature",
  "properties": {
    "gn:admin1_code":"4.0",
    "gn:admin2_code":"1247",
    "gn:asciiname":"Reeves Wood",
    "gn:country_code":"JM",
    "gn:dem":169,
    "gn:feature_class":"P",
    "gn:feature_code":"PPL",
    "gn:name":"Reeves Wood",
    "gn:population":0,
    "gn:timezone":"America/Jamaica",
    "iso:country":"JM",
    "wof:name":"Reeves Wood",
    "wof:placetype":"locality"
},
  "geometry": {"coordinates":[-77.41736,18.01105],"type":"Point"}
}