{
  "type": "Feature",
  "properties": {
    "gn:admin1_code":"12",
    "gn:admin2_code":"824.0",
    "gn:asciiname":"Adelphi",
    "gn:country_code":"JM",
    "gn:dem":147,
    "gn:feature_class":"P",
    "gn:feature_code":"PPL",
    "gn:name":"Adelphi",
    "gn:population":0,
    "gn:timezone":"America/Jamaica",
    "iso:country":"JM",
    "wof:name":"Adelphi",
    "wof:placetype":"locality"
},
  "geometry": {"coordinates":[-77.79318000000001,18.44675],"type":"Point"}
}