{
  "type": "Feature",
  "properties": {
    "gn:admin1_code":"12",
    "gn:admin2_code":"824.0",
    "gn:asciiname":"Adelphi",
    "gn:country_code":"JM",
    "gn:dem":147,
    "gn:feature_class":"P",
    "gn:feature_code":"PPL",
    "gn:name":"Adelphi",
    "gn:population":0,
    "gn:timezone":"America/Jamaica",
    "iso:country":"JM",
    "name:ceb_x_preferred":[
        "Adelphi"
    ],
    "name:deu_x_preferred":[
        "Adelphi"
    ],
    "name:fra_x_preferred":[
        "Adelphi"
    ],
    "name:ita_x_preferred":[
        "Adelphi"
    ],
    "name:nld_x_preferred":[
        "Adelphi"
    ],
    "name:nor_x_preferred":[
        "Adelphi"
    ],
    "name:pol_x_preferred":[
        "Adelphi"
    ],
    "name:por_x_preferred":[
        "Adelphi"
    ],
    "name:spa_x_preferred":[
        "Adelphi"
    ],
    "name:srp_x_preferred":[
        "\u0410\u0434\u0435\u043b\u0444\u0438"
    ],
    "name:swe_x_preferred":[
        "Adelphi"
    ],
    "name:ukr_x_preferred":[
        "\u0410\u0434\u0435\u043b\u0444\u0456"
    ],
    "wof:name":"Adelphi",
    "wof:placetype":"locality"
},
  "geometry": {"coordinates":[-77.79318000000001,18.44675],"type":"Point"}
}