{
  "type": "Feature",
  "properties": {
    "gn:admin1_code":"13.0",
    "gn:admin2_code":"521",
    "gn:asciiname":"Wallingford",
    "gn:country_code":"JM",
    "gn:dem":396,
    "gn:feature_class":"P",
    "gn:feature_code":"PPL",
    "gn:name":"Wallingford",
    "gn:population":0,
    "gn:timezone":"America/Jamaica",
    "iso:country":"JM",
    "name:bul_x_preferred":[
        "\u0423\u043e\u043b\u0438\u043d\u0433\u0444\u043e\u0440\u0434"
    ],
    "name:cat_x_preferred":[
        "Wallingford"
    ],
    "name:ceb_x_preferred":[
        "Wallingford"
    ],
    "name:deu_x_preferred":[
        "Wallingford"
    ],
    "name:fra_x_preferred":[
        "Wallingford"
    ],
    "name:ita_x_preferred":[
        "Wallingford"
    ],
    "name:kor_x_preferred":[
        "\uc6d4\ub9c1\ud37c\ub4dc"
    ],
    "name:nld_x_preferred":[
        "Wallingford"
    ],
    "name:pol_x_preferred":[
        "Wallingford"
    ],
    "name:rus_x_preferred":[
        "\u0423\u043e\u043b\u043b\u0438\u043d\u0433\u0444\u043e\u0440\u0434"
    ],
    "name:spa_x_preferred":[
        "Wallingford"
    ],
    "name:srp_x_preferred":[
        "\u0412\u043e\u043b\u0438\u043d\u0433\u0444\u043e\u0440\u0434"
    ],
    "name:swe_x_preferred":[
        "Wallingford"
    ],
    "name:und_x_variant":[
        "Waltingford",
        "Walingford",
        "Wallingford"
    ],
    "name:vol_x_preferred":[
        "Wallingford"
    ],
    "wof:name":"Wallingford",
    "wof:placetype":"locality"
},
  "geometry": {"coordinates":[-76.99679999999999,18.27223],"type":"Point"}
}