{
  "type": "Feature",
  "properties": {
    "gn:admin1_code":"13.0",
    "gn:admin2_code":"521",
    "gn:asciiname":"Wallingford",
    "gn:country_code":"JM",
    "gn:dem":396,
    "gn:feature_class":"P",
    "gn:feature_code":"PPL",
    "gn:name":"Wallingford",
    "gn:population":0,
    "gn:timezone":"America/Jamaica",
    "iso:country":"JM",
    "name:und_x_variant":[
        "Waltingford",
        "Walingford",
        "Wallingford"
    ],
    "wof:name":"Wallingford",
    "wof:placetype":"locality"
},
  "geometry": {"coordinates":[-76.99679999999999,18.27223],"type":"Point"}
}