{
  "type": "Feature",
  "properties": {
    "iso:country":"JM",
    "name:unk_x_variant":[
        "Barbicon"
    ],
    "qs:gn_country":"JM",
    "qs:gn_fcode":"PPL",
    "qs:gn_pop":0,
    "qs:name":"Barbican",
    "qs:name_adm0":"Jamaica",
    "qs:name_adm1":"Hanover",
    "qs:photos":17,
    "qs:photos_1k":3,
    "qs:photos_9k":1,
    "qs:photos_9r":1,
    "qs:photos_all":17,
    "qs:photos_sr":1,
    "qs:placetype":"Town",
    "qs:pop_sr":"0",
    "qs:woe_adm0":23424858,
    "wd:wordcount":321,
    "wof:name":"Barbican",
    "wof:placetype":"locality"
},
  "geometry": {"coordinates":[-78.10142,18.45038],"type":"Point"}
}