{
  "type": "Feature",
  "properties": {
    "iso:country":"JM",
    "name:ara_x_preferred":[
        "\u0645\u0631\u0642\u0628"
    ],
    "name:bel_x_preferred":[
        "\u0411\u0430\u0440\u0431\u0430\u043a\u0430\u043d"
    ],
    "name:bul_x_preferred":[
        "\u0411\u0430\u0440\u0431\u0430\u043a\u0430\u043d"
    ],
    "name:cat_x_preferred":[
        "barbacana"
    ],
    "name:ces_x_preferred":[
        "barbakan"
    ],
    "name:deu_x_preferred":[
        "Barbakane"
    ],
    "name:ell_x_preferred":[
        "\u03c0\u03b1\u03c1\u03b1\u03c4\u03b7\u03c1\u03b7\u03c4\u03ae\u03c1\u03b9\u03bf"
    ],
    "name:eng_x_preferred":[
        "barbican"
    ],
    "name:epo_x_preferred":[
        "Barbakano"
    ],
    "name:est_x_preferred":[
        "Barbakaan"
    ],
    "name:eus_x_preferred":[
        "Barbakana"
    ],
    "name:fas_x_preferred":[
        "\u0628\u0631\u062c \u062f\u06cc\u062f\u0628\u0627\u0646"
    ],
    "name:fin_x_preferred":[
        "Barbakaani"
    ],
    "name:fra_x_preferred":[
        "barbacane"
    ],
    "name:gle_x_preferred":[
        "barbac\u00e1n"
    ],
    "name:heb_x_preferred":[
        "\u05d1\u05e8\u05d1\u05d9\u05e7\u05df"
    ],
    "name:hrv_x_preferred":[
        "Barbakan"
    ],
    "name:hun_x_preferred":[
        "barbak\u00e1n"
    ],
    "name:ido_x_preferred":[
        "Barbakano"
    ],
    "name:ita_x_preferred":[
        "Barbacane"
    ],
    "name:jpn_x_preferred":[
        "\u7515\u57ce"
    ],
    "name:kor_x_preferred":[
        "\uc639\uc131"
    ],
    "name:lav_x_preferred":[
        "barbak\u0101ns"
    ],
    "name:lim_x_preferred":[
        "Barbacane"
    ],
    "name:lit_x_preferred":[
        "Barbakanas"
    ],
    "name:nld_x_preferred":[
        "Barbacane"
    ],
    "name:nld_x_variant":[
        "barbacane"
    ],
    "name:nob_x_preferred":[
        "barbakan"
    ],
    "name:pol_x_preferred":[
        "barbakan"
    ],
    "name:por_x_preferred":[
        "barbac\u00e3"
    ],
    "name:ron_x_preferred":[
        "Barbacan\u0103"
    ],
    "name:rus_x_preferred":[
        "\u0411\u0430\u0440\u0431\u0430\u043a\u0430\u043d"
    ],
    "name:scn_x_preferred":[
        "Varvacani"
    ],
    "name:slk_x_preferred":[
        "Barbak\u00e1n"
    ],
    "name:slv_x_preferred":[
        "Barbakan"
    ],
    "name:spa_x_preferred":[
        "Barbacana"
    ],
    "name:spa_x_variant":[
        "barbacana"
    ],
    "name:srp_x_preferred":[
        "\u0431\u0430\u0440\u0431\u0430\u043a\u0430\u043d"
    ],
    "name:tur_x_preferred":[
        "Barbakan"
    ],
    "name:ukr_x_preferred":[
        "\u0411\u0430\u0440\u0431\u0430\u043a\u0430\u043d"
    ],
    "name:und_x_variant":[
        "Barbicon"
    ],
    "name:zho_x_preferred":[
        "\u74ee\u57ce"
    ],
    "qs:gn_country":"JM",
    "qs:gn_fcode":"PPL",
    "qs:gn_pop":0,
    "qs:name":"Barbican",
    "qs:name_adm0":"Jamaica",
    "qs:name_adm1":"Hanover",
    "qs:photos":17,
    "qs:photos_1k":3,
    "qs:photos_9k":1,
    "qs:photos_9r":1,
    "qs:photos_all":17,
    "qs:photos_sr":1,
    "qs:placetype":"Town",
    "qs:pop_sr":"0",
    "qs:woe_adm0":23424858,
    "wd:wordcount":321,
    "wof:name":"Barbican",
    "wof:placetype":"locality"
},
  "geometry": {"coordinates":[-78.10142,18.45038],"type":"Point"}
}