{
  "type": "Feature",
  "properties": {
    "gn:admin1_code":"14",
    "gn:admin2_code":"301.0",
    "gn:asciiname":"Penlyne Castle",
    "gn:country_code":"JM",
    "gn:dem":1113,
    "gn:feature_class":"P",
    "gn:feature_code":"PPL",
    "gn:name":"Penlyne Castle",
    "gn:population":0,
    "gn:timezone":"America/Jamaica",
    "iso:country":"JM",
    "wof:name":"Penlyne Castle",
    "wof:placetype":"locality"
},
  "geometry": {"coordinates":[-76.6356,18.04693],"type":"Point"}
}