{
  "type": "Feature",
  "properties": {
    "gn:admin1_code":"09",
    "gn:admin2_code":"648.0",
    "gn:asciiname":"Aboukir",
    "gn:country_code":"JM",
    "gn:dem":618,
    "gn:feature_class":"P",
    "gn:feature_code":"PPL",
    "gn:name":"Aboukir",
    "gn:population":0,
    "gn:timezone":"America/Jamaica",
    "iso:country":"JM",
    "name:und_x_variant":[
        "Abourkir",
        "Aboukir"
    ],
    "wof:name":"Aboukir",
    "wof:placetype":"locality"
},
  "geometry": {"coordinates":[-77.35916999999998,18.25378],"type":"Point"}
}