{
  "type": "Feature",
  "properties": {
    "gn:admin1_code":"1.0",
    "gn:admin2_code":"1302",
    "gn:asciiname":"Spaldings",
    "gn:country_code":"JM",
    "gn:dem":818,
    "gn:feature_class":"P",
    "gn:feature_code":"PPL",
    "gn:name":"Spaldings",
    "gn:population":0,
    "gn:timezone":"America/Jamaica",
    "iso:country":"JM",
    "name:und_x_variant":[
        "Village of Spaldings",
        "Spaldings"
    ],
    "wof:name":"Spaldings",
    "wof:placetype":"locality"
},
  "geometry": {"coordinates":[-77.45775,18.15549],"type":"Point"}
}