{
  "type": "Feature",
  "properties": {
    "gn:admin1_code":"10",
    "gn:admin2_code":"1416.0",
    "gn:asciiname":"Blue Hole",
    "gn:country_code":"JM",
    "gn:dem":4,
    "gn:feature_class":"P",
    "gn:feature_code":"PPL",
    "gn:name":"Blue Hole",
    "gn:population":0,
    "gn:timezone":"America/Jamaica",
    "iso:country":"JM",
    "wof:name":"Blue Hole",
    "wof:placetype":"locality"
},
  "geometry": {"coordinates":[-76.90000000000001,18.03333],"type":"Point"}
}