{
  "type": "Feature",
  "properties": {
    "gn:admin1_code":"9.0",
    "gn:admin2_code":"632",
    "gn:asciiname":"Salisbury",
    "gn:country_code":"JM",
    "gn:dem":439,
    "gn:feature_class":"P",
    "gn:feature_code":"PPL",
    "gn:name":"Salisbury",
    "gn:population":0,
    "gn:timezone":"America/Jamaica",
    "iso:country":"JM",
    "wof:name":"Salisbury",
    "wof:placetype":"locality"
},
  "geometry": {"coordinates":[-77.1048,18.35008],"type":"Point"}
}