{
  "type": "Feature",
  "properties": {
    "gn:country":"JM",
    "gn:fcode":"PPL",
    "gn:pop":2631,
    "iso:country":"JM",
    "name:dut_x_preferred":[
        "Kellits"
    ],
    "name:eng_x_preferred":[
        "Kellits"
    ],
    "name:unk_x_variant":[
        "Kellets"
    ],
    "qs:name":"Kellits",
    "qs:photos_9r":0,
    "qs:photos_sr":0,
    "qs:pop_sr":"4",
    "wd:wordcount":115,
    "wof:name":"Kellits",
    "wof:placetype":"locality",
    "wof:population":2631
},
  "geometry": {"coordinates":[-77.23333,18.15],"type":"Point"}
}