{
  "type": "Feature",
  "properties": {
    "gn:admin1_code":"04",
    "gn:admin2_code":"1221.0",
    "gn:asciiname":"Adams Valley",
    "gn:country_code":"JM",
    "gn:dem":820,
    "gn:feature_class":"P",
    "gn:feature_code":"PPL",
    "gn:name":"Adams Valley",
    "gn:population":0,
    "gn:timezone":"America/Jamaica",
    "iso:country":"JM",
    "wof:name":"Adams Valley",
    "wof:placetype":"locality"
},
  "geometry": {"coordinates":[-77.59999999999999,18.11667000000001],"type":"Point"}
}