{
  "type": "Feature",
  "properties": {
    "gn:admin1_code":"13.0",
    "gn:admin2_code":"525",
    "gn:asciiname":"Whitehall",
    "gn:country_code":"JM",
    "gn:dem":151,
    "gn:feature_class":"P",
    "gn:feature_code":"PPL",
    "gn:name":"Whitehall",
    "gn:population":0,
    "gn:timezone":"America/Jamaica",
    "iso:country":"JM",
    "wof:name":"Whitehall",
    "wof:placetype":"locality"
},
  "geometry": {"coordinates":[-76.89237,18.29138],"type":"Point"}
}