{
  "type": "Feature",
  "properties": {
    "gn:admin1_code":"14.0",
    "gn:asciiname":"Mahogany Vale",
    "gn:country_code":"JM",
    "gn:dem":655,
    "gn:feature_class":"P",
    "gn:feature_code":"PPL",
    "gn:name":"Mahogany Vale",
    "gn:population":0,
    "gn:timezone":"America/Jamaica",
    "iso:country":"JM",
    "wof:name":"Mahogany Vale",
    "wof:placetype":"locality"
},
  "geometry": {"coordinates":[-76.63330000000001,18.0167],"type":"Point"}
}