{
  "type": "Feature",
  "properties": {
    "gn:admin1_code":"1.0",
    "gn:admin2_code":"1343",
    "gn:asciiname":"Woodside",
    "gn:country_code":"JM",
    "gn:dem":56,
    "gn:feature_class":"P",
    "gn:feature_code":"PPL",
    "gn:name":"Woodside",
    "gn:population":0,
    "gn:timezone":"America/Jamaica",
    "iso:country":"JM",
    "wof:name":"Woodside",
    "wof:placetype":"locality"
},
  "geometry": {"coordinates":[-77.28333000000001,17.98333],"type":"Point"}
}