{
  "type": "Feature",
  "properties": {
    "gn:admin1_code":"1.0",
    "gn:admin2_code":"1353",
    "gn:asciiname":"Warsop",
    "gn:country_code":"JM",
    "gn:dem":73,
    "gn:feature_class":"P",
    "gn:feature_code":"PPL",
    "gn:name":"Warsop",
    "gn:population":0,
    "gn:timezone":"America/Jamaica",
    "iso:country":"JM",
    "name:ceb_x_preferred":[
        "Market Warsop"
    ],
    "name:fas_x_preferred":[
        "\u0648\u0627\u0631\u0633\u0648\u0646"
    ],
    "name:gle_x_preferred":[
        "Warsop"
    ],
    "name:ita_x_preferred":[
        "Warsop"
    ],
    "name:nld_x_preferred":[
        "Warsop"
    ],
    "name:nno_x_preferred":[
        "Warsop"
    ],
    "name:pol_x_preferred":[
        "Market Warsop"
    ],
    "name:swe_x_preferred":[
        "Market Warsop"
    ],
    "wof:name":"Warsop",
    "wof:placetype":"locality"
},
  "geometry": {"coordinates":[-77.25,17.96667],"type":"Point"}
}