{
  "type": "Feature",
  "properties": {
    "gn:admin1_code":"13",
    "gn:admin2_code":"521.0",
    "gn:asciiname":"Decoy Estate",
    "gn:country_code":"JM",
    "gn:dem":380,
    "gn:feature_class":"P",
    "gn:feature_code":"PPL",
    "gn:name":"Decoy Estate",
    "gn:population":0,
    "gn:timezone":"America/Jamaica",
    "iso:country":"JM",
    "wof:name":"Decoy Estate",
    "wof:placetype":"locality"
},
  "geometry": {"coordinates":[-76.98333000000002,18.28333],"type":"Point"}
}