{
  "type": "Feature",
  "properties": {
    "iso:country":"JM",
    "name:bul_x_preferred":[
        "\u0414\u0430\u0440\u043b\u0438\u0441\u0442\u043e\u043d"
    ],
    "name:deu_x_preferred":[
        "Darliston"
    ],
    "name:eng_x_preferred":[
        "Darliston"
    ],
    "name:fra_x_preferred":[
        "Darliston"
    ],
    "name:nld_x_preferred":[
        "Darliston"
    ],
    "name:swe_x_preferred":[
        "Darliston"
    ],
    "name:unk_x_variant":[
        "Darlingston"
    ],
    "qs:gn_country":"JM",
    "qs:gn_fcode":"PPL",
    "qs:gn_pop":1583,
    "qs:name":"Darliston",
    "qs:name_adm0":"Jamaica",
    "qs:name_adm1":"Westmoreland",
    "qs:photos":0,
    "qs:photos_1k":0,
    "qs:photos_9k":0,
    "qs:photos_9r":0,
    "qs:photos_all":0,
    "qs:photos_sr":0,
    "qs:placetype":"Town",
    "qs:pop_sr":"3",
    "qs:woe_adm0":23424858,
    "wd:wordcount":141,
    "wof:name":"Darliston",
    "wof:placetype":"locality",
    "wof:population":1583
},
  "geometry": {"coordinates":[-77.97626,18.23731],"type":"Point"}
}