{
  "type": "Feature",
  "properties": {
    "gn:admin1_code":"7.0",
    "gn:admin2_code":"437",
    "gn:asciiname":"Shirley Pen",
    "gn:country_code":"JM",
    "gn:dem":172,
    "gn:feature_class":"P",
    "gn:feature_code":"PPL",
    "gn:name":"Shirley Pen",
    "gn:population":0,
    "gn:timezone":"America/Jamaica",
    "iso:country":"JM",
    "wof:name":"Shirley Pen",
    "wof:placetype":"locality"
},
  "geometry": {"coordinates":[-76.63333,18.18333],"type":"Point"}
}