{
  "type": "Feature",
  "properties": {
    "gn:admin1_code":"16.0",
    "gn:admin2_code":"1042",
    "gn:asciiname":"Orange Hill",
    "gn:country_code":"JM",
    "gn:dem":58,
    "gn:feature_class":"P",
    "gn:feature_code":"PPL",
    "gn:name":"Orange Hill",
    "gn:population":0,
    "gn:timezone":"America/Jamaica",
    "iso:country":"JM",
    "wof:name":"Orange Hill",
    "wof:placetype":"locality"
},
  "geometry": {"coordinates":[-78.31667,18.23333],"type":"Point"}
}