{
  "type": "Feature",
  "properties": {
    "gn:admin1_code":"08",
    "gn:admin2_code":"15125.0",
    "gn:asciiname":"Gayle Mountain",
    "gn:country_code":"JM",
    "gn:dem":303,
    "gn:feature_class":"P",
    "gn:feature_code":"PPL",
    "gn:name":"Gayle Mountain",
    "gn:population":0,
    "gn:timezone":"America/Jamaica",
    "iso:country":"JM",
    "name:eng_x_preferred":[
        "Gayle Mt."
    ],
    "wof:name":"Gayle Mountain",
    "wof:placetype":"locality"
},
  "geometry": {"coordinates":[-76.72843,18.03444],"type":"Point"}
}