{
  "type": "Feature",
  "properties": {
    "gn:admin1_code":"14.0",
    "gn:admin2_code":"314",
    "gn:asciiname":"Spring Bank",
    "gn:country_code":"JM",
    "gn:dem":173,
    "gn:feature_class":"P",
    "gn:feature_code":"PPL",
    "gn:name":"Spring Bank",
    "gn:population":0,
    "gn:timezone":"America/Jamaica",
    "iso:country":"JM",
    "wof:name":"Spring Bank",
    "wof:placetype":"locality"
},
  "geometry": {"coordinates":[-76.32608,17.96394],"type":"Point"}
}