{
  "type": "Feature",
  "properties": {
    "gn:admin1_code":"11",
    "gn:admin2_code":"1121.0",
    "gn:asciiname":"Colon",
    "gn:country_code":"JM",
    "gn:dem":457,
    "gn:feature_class":"P",
    "gn:feature_code":"PPL",
    "gn:name":"Colon",
    "gn:population":0,
    "gn:timezone":"America/Jamaica",
    "iso:country":"JM",
    "wof:name":"Colon",
    "wof:placetype":"locality"
},
  "geometry": {"coordinates":[-77.91438000000002,18.12124],"type":"Point"}
}