{
  "type": "Feature",
  "properties": {
    "gn:admin1_code":"16",
    "gn:admin2_code":"1048.0",
    "gn:asciiname":"Jane Marks",
    "gn:cc2":"JM",
    "gn:country_code":"JM",
    "gn:dem":10,
    "gn:feature_class":"P",
    "gn:feature_code":"PPL",
    "gn:name":"Jane Marks",
    "gn:population":0,
    "gn:timezone":"America/Jamaica",
    "iso:country":"JM",
    "name:und_x_variant":[
        "Jane Marks Village",
        "Jane Marks"
    ],
    "wof:name":"Jane Marks",
    "wof:placetype":"locality"
},
  "geometry": {"coordinates":[-78.13333,18.26667],"type":"Point"}
}