{
  "type": "Feature",
  "properties": {
    "gn:admin1_code":"09",
    "gn:admin2_code":"652.0",
    "gn:asciiname":"Clover Hill",
    "gn:country_code":"JM",
    "gn:dem":762,
    "gn:feature_class":"P",
    "gn:feature_code":"PPL",
    "gn:name":"Clover Hill",
    "gn:population":0,
    "gn:timezone":"America/Jamaica",
    "iso:country":"JM",
    "name:ceb_x_preferred":[
        "Clover Hill"
    ],
    "name:deu_x_preferred":[
        "Clover Hill"
    ],
    "wof:name":"Clover Hill",
    "wof:placetype":"locality"
},
  "geometry": {"coordinates":[-77.15000000000001,18.21667],"type":"Point"}
}