{
  "type": "Feature",
  "properties": {
    "iso:country":"JM",
    "name:ceb_x_preferred":[
        "Camperdown"
    ],
    "name:deu_x_preferred":[
        "Camperdown"
    ],
    "name:eng_x_preferred":[
        "Camperdown"
    ],
    "name:pol_x_preferred":[
        "Camperdown"
    ],
    "name:slv_x_preferred":[
        "Camperdown"
    ],
    "name:swe_x_preferred":[
        "Camperdown"
    ],
    "qs:gn_adm0_cc":"JM",
    "qs:gn_local":3489854,
    "qs:local_max":911,
    "qs:local_sum":2314,
    "qs:localhoods":10,
    "qs:name":"Camperdown",
    "qs:name_adm0":"Jamaica",
    "qs:name_adm1":"Saint Andrew",
    "qs:name_local":"Kingston",
    "qs:photo_max":36,
    "qs:photo_sum":160,
    "qs:placetype":"Suburb",
    "qs:quad_count":19,
    "qs:woe_adm0":23424858,
    "qs:woe_adm1":2345916,
    "qs:woe_adm2":0,
    "qs:woe_lau":0,
    "qs:woe_local":109251,
    "qs:woe_ver":"7.10.0",
    "wof:lang":[
        "eng"
    ],
    "wof:name":"Camperdown",
    "wof:placetype":"neighbourhood"
},
  "geometry": {"coordinates":[-76.795756,18.015977],"type":"Point"}
}