{
  "type": "Feature",
  "properties": {
    "gn:admin1_code":"13",
    "gn:admin2_code":"506.0",
    "gn:asciiname":"Airy Hill",
    "gn:country_code":"JM",
    "gn:dem":163,
    "gn:feature_class":"P",
    "gn:feature_code":"PPL",
    "gn:name":"Airy Hill",
    "gn:population":0,
    "gn:timezone":"America/Jamaica",
    "iso:country":"JM",
    "wof:name":"Airy Hill",
    "wof:placetype":"locality"
},
  "geometry": {"coordinates":[-76.93638,18.39818],"type":"Point"}
}