{
  "type": "Feature",
  "properties": {
    "gn:admin1_code":"10.0",
    "gn:admin2_code":"1409",
    "gn:asciiname":"Williamsfield",
    "gn:country_code":"JM",
    "gn:dem":229,
    "gn:feature_class":"P",
    "gn:feature_code":"PPL",
    "gn:name":"Williamsfield",
    "gn:population":0,
    "gn:timezone":"America/Jamaica",
    "iso:country":"JM",
    "name:ceb_x_preferred":[
        "Williamsfield"
    ],
    "name:fra_x_preferred":[
        "Williamsfield"
    ],
    "name:pol_x_preferred":[
        "Williamsfield"
    ],
    "name:swe_x_preferred":[
        "Williamsfield"
    ],
    "name:vol_x_preferred":[
        "Williamsfield"
    ],
    "wof:name":"Williamsfield",
    "wof:placetype":"locality"
},
  "geometry": {"coordinates":[-76.94015999999998,18.17029],"type":"Point"}
}