{
  "type": "Feature",
  "properties": {
    "gn:admin1_code":"16.0",
    "gn:admin2_code":"1045",
    "gn:asciiname":"Little Broughton",
    "gn:country_code":"JM",
    "gn:dem":9,
    "gn:feature_class":"P",
    "gn:feature_code":"PPL",
    "gn:name":"Little Broughton",
    "gn:population":0,
    "gn:timezone":"America/Jamaica",
    "iso:country":"JM",
    "name:cym_x_preferred":[
        "Little Broughton"
    ],
    "name:pol_x_preferred":[
        "Little Broughton"
    ],
    "name:und_x_variant":[
        "Broughton"
    ],
    "wof:name":"Little Broughton",
    "wof:placetype":"locality"
},
  "geometry": {"coordinates":[-78.22503,18.22682],"type":"Point"}
}