{
  "type": "Feature",
  "properties": {
    "gn:admin1_code":"10.0",
    "gn:admin2_code":"1413",
    "gn:asciiname":"Little Angels",
    "gn:cc2":"JM",
    "gn:country_code":"JM",
    "gn:dem":236,
    "gn:feature_class":"P",
    "gn:feature_code":"PPL",
    "gn:name":"Little Angels",
    "gn:population":0,
    "gn:timezone":"America/Jamaica",
    "iso:country":"JM",
    "name:deu_x_preferred":[
        "Little Angels"
    ],
    "name:ita_x_preferred":[
        "Little Angels"
    ],
    "name:spa_x_preferred":[
        "Little Angels"
    ],
    "name:und_x_variant":[
        "Little Angles",
        "Little Angels"
    ],
    "wof:name":"Little Angels",
    "wof:placetype":"locality"
},
  "geometry": {"coordinates":[-76.96666999999999,18.06667],"type":"Point"}
}