{
  "type": "Feature",
  "properties": {
    "gn:admin1_code":"07",
    "gn:admin2_code":"427.0",
    "gn:asciiname":"Flat Grass",
    "gn:country_code":"JM",
    "gn:dem":100,
    "gn:feature_class":"P",
    "gn:feature_code":"PPL",
    "gn:name":"Flat Grass",
    "gn:population":0,
    "gn:timezone":"America/Jamaica",
    "iso:country":"JM",
    "wof:name":"Flat Grass",
    "wof:placetype":"locality"
},
  "geometry": {"coordinates":[-76.28333000000001,18.01667],"type":"Point"}
}