{
  "type": "Feature",
  "properties": {
    "gn:admin1_code":"16",
    "gn:admin2_code":"1084.0",
    "gn:asciiname":"Culloden",
    "gn:country_code":"JM",
    "gn:dem":36,
    "gn:feature_class":"P",
    "gn:feature_code":"PPL",
    "gn:name":"Culloden",
    "gn:population":0,
    "gn:timezone":"America/Jamaica",
    "iso:country":"JM",
    "name:ceb_x_preferred":[
        "Culloden"
    ],
    "name:ces_x_preferred":[
        "Culloden"
    ],
    "name:deu_x_preferred":[
        "Culloden"
    ],
    "name:fra_x_preferred":[
        "Culloden"
    ],
    "name:ita_x_preferred":[
        "Culloden"
    ],
    "name:jpn_x_preferred":[
        "\u30ab\u30ed\u30fc\u30c7\u30f3"
    ],
    "name:nld_x_preferred":[
        "Culloden"
    ],
    "name:pol_x_preferred":[
        "Culloden"
    ],
    "name:por_x_preferred":[
        "Culloden"
    ],
    "name:srp_x_preferred":[
        "\u041a\u0443\u043b\u043e\u0434\u0435\u043d"
    ],
    "name:ukr_x_preferred":[
        "\u041a\u0430\u043b\u043b\u043e\u0434\u0435\u043d"
    ],
    "name:und_x_variant":[
        "Culldden"
    ],
    "name:vol_x_preferred":[
        "Culloden"
    ],
    "wof:name":"Culloden",
    "wof:placetype":"locality"
},
  "geometry": {"coordinates":[-77.97855,18.1055],"type":"Point"}
}