{
  "type": "Feature",
  "properties": {
    "gn:admin1_code":"16",
    "gn:admin2_code":"1084.0",
    "gn:asciiname":"Culloden",
    "gn:country_code":"JM",
    "gn:dem":36,
    "gn:feature_class":"P",
    "gn:feature_code":"PPL",
    "gn:name":"Culloden",
    "gn:population":0,
    "gn:timezone":"America/Jamaica",
    "iso:country":"JM",
    "name:und_x_variant":[
        "Culldden",
        "Culloden"
    ],
    "wof:name":"Culloden",
    "wof:placetype":"locality"
},
  "geometry": {"coordinates":[-77.97855,18.1055],"type":"Point"}
}