{
  "type": "Feature",
  "properties": {
    "gn:admin1_code":"09",
    "gn:admin2_code":"638.0",
    "gn:asciiname":"Dorothy Pen",
    "gn:cc2":"JM",
    "gn:country_code":"JM",
    "gn:dem":623,
    "gn:feature_class":"P",
    "gn:feature_code":"PPL",
    "gn:name":"Dorothy Pen",
    "gn:population":0,
    "gn:timezone":"America/Jamaica",
    "iso:country":"JM",
    "name:und_x_variant":[
        "Dorothy",
        "Dorothy Pen"
    ],
    "wof:name":"Dorothy Pen",
    "wof:placetype":"locality"
},
  "geometry": {"coordinates":[-77.38333,18.28333],"type":"Point"}
}