{
  "type": "Feature",
  "properties": {
    "gn:admin1_code":"02",
    "gn:admin2_code":"905.0",
    "gn:asciiname":"Jew Hill",
    "gn:country_code":"JM",
    "gn:dem":68,
    "gn:feature_class":"P",
    "gn:feature_code":"PPL",
    "gn:name":"Jew Hill",
    "gn:population":0,
    "gn:timezone":"America/Jamaica",
    "iso:country":"JM",
    "wof:name":"Jew Hill",
    "wof:placetype":"locality"
},
  "geometry": {"coordinates":[-78.15000000000001,18.43333],"type":"Point"}
}