{
  "type": "Feature",
  "properties": {
    "gn:admin1_code":"01",
    "gn:admin2_code":"1312.0",
    "gn:asciiname":"Brandon Hill",
    "gn:country_code":"JM",
    "gn:dem":563,
    "gn:feature_class":"P",
    "gn:feature_code":"PPL",
    "gn:name":"Brandon Hill",
    "gn:population":0,
    "gn:timezone":"America/Jamaica",
    "iso:country":"JM",
    "wof:name":"Brandon Hill",
    "wof:placetype":"locality"
},
  "geometry": {"coordinates":[-77.24600000000002,18.14867000000001],"type":"Point"}
}