{
  "type": "Feature",
  "properties": {
    "iso:country":"JM",
    "name:dut_x_preferred":[
        "Trinity Ville"
    ],
    "name:eng_x_preferred":[
        "Trinity Ville"
    ],
    "qs:gn_country":"JM",
    "qs:gn_fcode":"PPL",
    "qs:gn_pop":2895,
    "qs:name":"Trinity Ville",
    "qs:name_adm0":"Jamaica",
    "qs:name_adm1":"Saint Thomas",
    "qs:photos":0,
    "qs:photos_1k":0,
    "qs:photos_9k":0,
    "qs:photos_9r":0,
    "qs:photos_all":0,
    "qs:photos_sr":0,
    "qs:placetype":"Town",
    "qs:pop_sr":"4",
    "qs:woe_adm0":23424858,
    "wd:wordcount":61,
    "wof:name":"Trinity Ville",
    "wof:placetype":"locality",
    "wof:population":2895
},
  "geometry": {"coordinates":[-76.51427,17.96076],"type":"Point"}
}