{
  "type": "Feature",
  "properties": {
    "gn:admin1_code":"10.0",
    "gn:admin2_code":"1422",
    "gn:asciiname":"Seven Doubloons",
    "gn:country_code":"JM",
    "gn:dem":114,
    "gn:feature_class":"P",
    "gn:feature_code":"PPL",
    "gn:name":"Seven Doubloons",
    "gn:population":0,
    "gn:timezone":"America/Jamaica",
    "iso:country":"JM",
    "wof:name":"Seven Doubloons",
    "wof:placetype":"locality"
},
  "geometry": {"coordinates":[-77.01666999999998,18.01667],"type":"Point"}
}