{
  "type": "Feature",
  "properties": {
    "gn:admin1_code":"7.0",
    "gn:admin2_code":"409",
    "gn:asciiname":"Little Spring Garden",
    "gn:country_code":"JM",
    "gn:dem":309,
    "gn:feature_class":"P",
    "gn:feature_code":"PPLL",
    "gn:name":"Little Spring Garden",
    "gn:population":0,
    "gn:timezone":"America/Jamaica",
    "iso:country":"JM",
    "name:und_x_variant":[
        "Spring Garden",
        "Little Spring Garden"
    ],
    "wof:name":"Little Spring Garden",
    "wof:placetype":"locality"
},
  "geometry": {"coordinates":[-76.5333,18.1833],"type":"Point"}
}