{
  "type": "Feature",
  "properties": {
    "gn:admin1_code":"01",
    "gn:admin2_code":"1314.0",
    "gn:asciiname":"Crooked River",
    "gn:country_code":"JM",
    "gn:dem":352,
    "gn:feature_class":"P",
    "gn:feature_code":"PPL",
    "gn:name":"Crooked River",
    "gn:population":0,
    "gn:timezone":"America/Jamaica",
    "iso:country":"JM",
    "name:ceb_x_preferred":[
        "Crooked River"
    ],
    "name:deu_x_preferred":[
        "Crooked River"
    ],
    "name:fra_x_preferred":[
        "Crooked"
    ],
    "name:ita_x_preferred":[
        "Crooked River"
    ],
    "name:swe_x_preferred":[
        "Crooked River"
    ],
    "wof:name":"Crooked River",
    "wof:placetype":"locality"
},
  "geometry": {"coordinates":[-77.31118000000002,18.13261],"type":"Point"}
}