{
  "type": "Feature",
  "properties": {
    "gn:admin1_code":"10.0",
    "gn:admin2_code":"1404",
    "gn:asciiname":"Simmers Valley",
    "gn:country_code":"JM",
    "gn:dem":557,
    "gn:feature_class":"P",
    "gn:feature_code":"PPL",
    "gn:name":"Simmers Valley",
    "gn:population":0,
    "gn:timezone":"America/Jamaica",
    "iso:country":"JM",
    "wof:name":"Simmers Valley",
    "wof:placetype":"locality"
},
  "geometry": {"coordinates":[-77.01666999999998,18.23333],"type":"Point"}
}