{
  "type": "Feature",
  "properties": {
    "gn:admin1_code":"04",
    "gn:admin2_code":"1233.0",
    "gn:asciiname":"Kendal",
    "gn:country_code":"JM",
    "gn:dem":358,
    "gn:feature_class":"P",
    "gn:feature_code":"PPL",
    "gn:name":"Kendal",
    "gn:population":0,
    "gn:timezone":"America/Jamaica",
    "iso:country":"JM",
    "wof:name":"Kendal",
    "wof:placetype":"locality"
},
  "geometry": {"coordinates":[-77.4815,18.08721],"type":"Point"}
}