{
  "type": "Feature",
  "properties": {
    "gn:admin1_code":"11",
    "gn:admin2_code":"1122.0",
    "gn:asciiname":"Dallingtober",
    "gn:cc2":"JM",
    "gn:country_code":"JM",
    "gn:dem":29,
    "gn:feature_class":"P",
    "gn:feature_code":"PPL",
    "gn:name":"Dallingtober",
    "gn:population":0,
    "gn:timezone":"America/Jamaica",
    "iso:country":"JM",
    "name:und_x_variant":[
        "Dollingtabor",
        "Dalingtober",
        "Dalentobur",
        "Dallingtober"
    ],
    "wof:name":"Dallingtober",
    "wof:placetype":"locality"
},
  "geometry": {"coordinates":[-77.93333,18.05],"type":"Point"}
}