{
  "type": "Feature",
  "properties": {
    "gn:country":"JM",
    "gn:fcode":"PPLA",
    "gn:population":6289,
    "iso:country":"JM",
    "name:ara_x_preferred":[
        "\u0644\u0648\u0633\u064a\u0627\u060c \u062c\u0627\u0645\u0627\u064a\u0643\u0627"
    ],
    "name:ara_x_variant":[
        "\u0644\u0648\u0633\u064a\u0627"
    ],
    "name:bel_x_preferred":[
        "\u041b\u0443\u0441\u0435\u0430"
    ],
    "name:cat_x_preferred":[
        "Lucea"
    ],
    "name:ceb_x_preferred":[
        "Lucea"
    ],
    "name:deu_x_preferred":[
        "Lucea"
    ],
    "name:ell_x_preferred":[
        "\u039b\u03bf\u03cd\u03c3\u03b5\u03b1"
    ],
    "name:eng_x_preferred":[
        "Lucea"
    ],
    "name:fra_x_preferred":[
        "Lucea"
    ],
    "name:glg_x_preferred":[
        "Lucea"
    ],
    "name:hye_x_preferred":[
        "\u053c\u0578\u0582\u057d\u0565\u0561"
    ],
    "name:ita_x_preferred":[
        "Lucea"
    ],
    "name:jam_x_preferred":[
        "Luusi"
    ],
    "name:jpn_x_preferred":[
        "\u30eb\u30bb\u30a2"
    ],
    "name:nld_x_preferred":[
        "Lucea"
    ],
    "name:pol_x_preferred":[
        "Lucea"
    ],
    "name:por_x_preferred":[
        "Lucea"
    ],
    "name:rus_x_preferred":[
        "\u041b\u0443\u0441\u0435\u0430"
    ],
    "name:spa_x_preferred":[
        "Lucea"
    ],
    "name:swe_x_preferred":[
        "Lucea"
    ],
    "name:zho_x_preferred":[
        "\u76e7\u897f"
    ],
    "qs_pg:aaroncc":"JM",
    "qs_pg:gn_country":"JM",
    "qs_pg:gn_fcode":"PPLA",
    "qs_pg:gn_pop":6289,
    "qs_pg:name":"Lucea",
    "qs_pg:photos_9r":0,
    "qs_pg:photos_sr":0,
    "qs_pg:pop_sr":5,
    "qs_pg:qs_pg_placetype":"locality",
    "wof:name":"Lucea",
    "wof:placetype":"locality",
    "wof:population":6289
},
  "geometry": {"coordinates":[-78.17355999999999,18.45095],"type":"Point"}
}