{
  "type": "Feature",
  "properties": {
    "gn:admin1_code":"11.0",
    "gn:admin2_code":"1132",
    "gn:asciiname":"Pepper",
    "gn:country_code":"JM",
    "gn:dem":134,
    "gn:feature_class":"P",
    "gn:feature_code":"PPL",
    "gn:name":"Pepper",
    "gn:population":0,
    "gn:timezone":"America/Jamaica",
    "iso:country":"JM",
    "name:ara_x_preferred":[
        "\u0641\u0644\u0641\u0644"
    ],
    "name:chv_x_preferred":[
        "\u041f\u0103\u0440\u0103\u00e7"
    ],
    "name:dan_x_preferred":[
        "Peber"
    ],
    "name:deu_x_preferred":[
        "Pepper"
    ],
    "name:fas_x_preferred":[
        "\u0641\u0644\u0641\u0644"
    ],
    "name:fra_x_preferred":[
        "Pepper"
    ],
    "name:heb_x_preferred":[
        "\u05e4\u05dc\u05e4\u05dc"
    ],
    "name:ita_x_preferred":[
        "Pepper"
    ],
    "name:jpn_x_preferred":[
        "\u30da\u30c3\u30d1\u30fc"
    ],
    "name:por_x_preferred":[
        "Pepper"
    ],
    "name:rus_x_preferred":[
        "\u041f\u0435\u0440\u0435\u0446"
    ],
    "name:ukr_x_preferred":[
        "\u041f\u0435\u0440\u0435\u0446\u044c"
    ],
    "name:vie_x_preferred":[
        "H\u1ea1t ti\u00eau"
    ],
    "wof:name":"Pepper",
    "wof:placetype":"locality"
},
  "geometry": {"coordinates":[-77.59999999999999,18.01667],"type":"Point"}
}