{
  "type": "Feature",
  "properties": {
    "gn:admin1_code":"11.0",
    "gn:admin2_code":"1132",
    "gn:asciiname":"Pepper",
    "gn:country_code":"JM",
    "gn:dem":134,
    "gn:feature_class":"P",
    "gn:feature_code":"PPL",
    "gn:name":"Pepper",
    "gn:population":0,
    "gn:timezone":"America/Jamaica",
    "iso:country":"JM",
    "wof:name":"Pepper",
    "wof:placetype":"locality"
},
  "geometry": {"coordinates":[-77.59999999999999,18.01667],"type":"Point"}
}